Workbook
Name zsupermetrics_refreshAll: SupermetricsQueries!$H$5
Name zsupermetrics_xhBK48cDeYRNkKTgEkN3NSS83QBpNp: TK!$H$6:$S$65
Name zsupermetrics_forceRefresh: SupermetricsQueries!$H$4
Name zsupermetrics_refreshAllSilent: SupermetricsQueries!$H$6

Sheet DATOS MENSUALES
A1: ENERO
A3: PRODUCTO | B3: VENTAS | C3: PROVEEDOR | D3: LOGISTICA | E3: DEVOLUCION | F3: TIK TOK ADS | G3: FACEBOOK ADS | H3: M PRIMA | I3: UTILIDAD | J3: =IFERROR( IF(OR($K10=0, SUM($J10:P10)=0), "", "ENTREGAS "&TEXT(J10/SUM($J10:P10), "0%")) ,"") -> ENTREGAS 54% | K3: =IFERROR( IF(OR($K10=0, SUM($J10:P10)=0), "", "DEVOLUCION "&TEXT(K10/SUM($J10:P10), "0%")) ,"") -> DEVOLUCION 22% | L3: =IFERROR( IF(OR($K10=0, SUM($J10:P10)=0), "", "PROCESO "&TEXT(L10/SUM($J10:P10), "0%")) ,"") -> PROCESO 0% | M3: =IFERROR( IF(OR($K10=0, SUM($J10:P10)=0), "", "NOVEDAD "&TEXT(M10/SUM($J10:P10), "0%")) ,"") -> NOVEDAD 0% | N3: =IFERROR( IF(OR($K10=0, SUM($J10:P10)=0), "", "PENDIENTES "&TEXT(N10/SUM($J10:P10), "0%")) ,"") -> PENDIENTES 14% | O3: =IFERROR( IF(OR($K10=0, SUM($J10:P10)=0), "", "CANCELADOS "&TEXT(O10/SUM($J10:P10), "0%")) ,"") -> CANCELADOS 7% | P3: =IFERROR( IF(OR($K10=0, SUM($J10:P10)=0), "", "REVISAR "&TEXT(P10/SUM($J10:P10), "0%")) ,"") -> REVISAR 3%
A4: =IFERROR(__xludf.DUMMYFUNCTION("UNIQUE( FILTER( TRIM( FLATTEN( SPLIT(ENERO!D2:D1000, "";"") ) ), FLATTEN( SPLIT(ENERO!D2:D1000, "";"") )<>"""" ) )"),"Llave Multifuncional 360™") -> Llave Multifuncional 360™ | B4: =IF(A4="","",SUMIF(ENERO!D:D, A4, ENERO!G:G)) -> 1519.75 | C4: =IF(A4="","",SUMIF(ENERO!D:D, A4, ENERO!E:E)) -> 485 | D4: =IF(A4="","",SUMIF(ENERO!D:D, A4, ENERO!J:J)) -> 345.33 | E4: =IF(A4="","",SUMIF(ENERO!D:D, A4, ENERO!L:L)) -> 115.45 | F4: =IFERROR(__xludf.DUMMYFUNCTION("IFERROR( IF(A4="""","""",SUM( FILTER( VALUE(SUBSTITUTE(TK!B:B,""."","","")), REGEXMATCH(TK!A:A,A4), MONTH( DATE( VALUE(RIGHT(LEFT(TK!A:A,10),4)), VALUE(MID(TK!A:A,4,2)), VALUE(LEFT(TK!A:A,2)) ) )=1 ) )), """") "),0.0) -> 0 | G4: =IFERROR(__xludf.DUMMYFUNCTION("IF( A4="""", """", SUM( FILTER( VALUE(SUBSTITUTE(FB!D:D, ""."", "","")), REGEXMATCH(FB!B:B, A4), MONTH(FB!E:E)=1 ) ) * 1.2 ) "),525.564) -> 525.564 | I4: =IF(A4="","",B4-SUM(C4:G4)) -> 48.406 | J4: =IF(A4="","",COUNTIFS(ENERO!D:D,A4,ENERO!O:O,"ENTREGADO")) -> 61 | K4: =IF(A4="","",COUNTIFS(ENERO!D:D,A4,ENERO!O:O,"DEVOLUCION")) -> 23 | L4: =IF(A4="","",COUNTIFS(ENERO!D:D,A4,ENERO!O:O,"PROCESO")) -> 0 | M4: =IF(A4="","",COUNTIFS(ENERO!D:D,A4,ENERO!O:O,"NOVEDAD")) -> 0 | N4: =IF(A4="","",COUNTIFS(ENERO!D:D,A4,ENERO!O:O,"PENDIENTE")) -> 6 | O4: =IF(A4="","",COUNTIFS(ENERO!D:D,A4,ENERO!O:O,"CANCELADO")) -> 12 | P4: =IF(A4="","",COUNTIFS(ENERO!D:D,A4,ENERO!O:O,"REVISAR")) -> 7
A5: =IFERROR(__xludf.DUMMYFUNCTION("""COMPUTED_VALUE"""),"FilmPro®") -> FilmPro® | B5: =IF(A5="","",SUMIF(ENERO!D:D, A5, ENERO!G:G)) -> 8355 | C5: =IF(A5="","",SUMIF(ENERO!D:D, A5, ENERO!E:E)) -> 1694.37 | D5: =IF(A5="","",SUMIF(ENERO!D:D, A5, ENERO!J:J)) -> 1972.23 | E5: =IF(A5="","",SUMIF(ENERO!D:D, A5, ENERO!L:L)) -> 683.79 | F5: =IFERROR(__xludf.DUMMYFUNCTION("IFERROR( IF(A5="""","""",SUM( FILTER( VALUE(SUBSTITUTE(TK!B:B,""."","","")), REGEXMATCH(TK!A:A,A5), MONTH( DATE( VALUE(RIGHT(LEFT(TK!A:A,10),4)), VALUE(MID(TK!A:A,4,2)), VALUE(LEFT(TK!A:A,2)) ) )=1 ) )), """") "),127.08) -> 127.08 | G5: =IFERROR(__xludf.DUMMYFUNCTION("IF( A5="""", """", SUM( FILTER( VALUE(SUBSTITUTE(FB!D:D, ""."", "","")), REGEXMATCH(FB!B:B, A5), MONTH(FB!E:E)=1 ) ) * 1.2 ) "),1875.828) -> 1875.828 | I5: =IF(A5="","",B5-SUM(C5:G5)) -> 2001.702 | J5: =IF(A5="","",COUNTIFS(ENERO!D:D,A5,ENERO!O:O,"ENTREGADO")) -> 329 | K5: =IF(A5="","",COUNTIFS(ENERO!D:D,A5,ENERO!O:O,"DEVOLUCION")) -> 133 | L5: =IF(A5="","",COUNTIFS(ENERO!D:D,A5,ENERO!O:O,"PROCESO")) -> 0 | M5: =IF(A5="","",COUNTIFS(ENERO!D:D,A5,ENERO!O:O,"NOVEDAD")) -> 0 | N5: =IF(A5="","",COUNTIFS(ENERO!D:D,A5,ENERO!O:O,"PENDIENTE")) -> 107 | O5: =IF(A5="","",COUNTIFS(ENERO!D:D,A5,ENERO!O:O,"CANCELADO")) -> 48 | P5: =IF(A5="","",COUNTIFS(ENERO!D:D,A5,ENERO!O:O,"REVISAR")) -> 0
A6: =IFERROR(__xludf.DUMMYFUNCTION("""COMPUTED_VALUE"""),"FLORA FRESH PRO™") -> FLORA FRESH PRO™ | B6: =IF(A6="","",SUMIF(ENERO!D:D, A6, ENERO!G:G)) -> 194 | C6: =IF(A6="","",SUMIF(ENERO!D:D, A6, ENERO!E:E)) -> 55 | D6: =IF(A6="","",SUMIF(ENERO!D:D, A6, ENERO!J:J)) -> 42.79 | E6: =IF(A6="","",SUMIF(ENERO!D:D, A6, ENERO!L:L)) -> 34.17 | F6: =IFERROR(__xludf.DUMMYFUNCTION("IFERROR( IF(A6="""","""",SUM( FILTER( VALUE(SUBSTITUTE(TK!B:B,""."","","")), REGEXMATCH(TK!A:A,A6), MONTH( DATE( VALUE(RIGHT(LEFT(TK!A:A,10),4)), VALUE(MID(TK!A:A,4,2)), VALUE(LEFT(TK!A:A,2)) ) )=1 ) )), """") "),"") | G6: =IFERROR(__xludf.DUMMYFUNCTION("IF( A6="""", """", SUM( FILTER( VALUE(SUBSTITUTE(FB!D:D, ""."", "","")), REGEXMATCH(FB!B:B, A6), MONTH(FB!E:E)=1 ) ) * 1.2 ) "),87.432) -> 87.432 | I6: =IF(A6="","",B6-SUM(C6:G6)) -> -25.392 | J6: =IF(A6="","",COUNTIFS(ENERO!D:D,A6,ENERO!O:O,"ENTREGADO")) -> 7 | K6: =IF(A6="","",COUNTIFS(ENERO!D:D,A6,ENERO!O:O,"DEVOLUCION")) -> 7 | L6: =IF(A6="","",COUNTIFS(ENERO!D:D,A6,ENERO!O:O,"PROCESO")) -> 0 | M6: =IF(A6="","",COUNTIFS(ENERO!D:D,A6,ENERO!O:O,"NOVEDAD")) -> 0 | N6: =IF(A6="","",COUNTIFS(ENERO!D:D,A6,ENERO!O:O,"PENDIENTE")) -> 0 | O6: =IF(A6="","",COUNTIFS(ENERO!D:D,A6,ENERO!O:O,"CANCELADO")) -> 3 | P6: =IF(A6="","",COUNTIFS(ENERO!D:D,A6,ENERO!O:O,"REVISAR")) -> 0
A7: =IFERROR(__xludf.DUMMYFUNCTION("""COMPUTED_VALUE"""),"Cuchillo Tazaki™") -> Cuchillo Tazaki™ | B7: =IF(A7="","",SUMIF(ENERO!D:D, A7, ENERO!G:G)) -> 4104.9 | C7: =IF(A7="","",SUMIF(ENERO!D:D, A7, ENERO!E:E)) -> 1086.4 | D7: =IF(A7="","",SUMIF(ENERO!D:D, A7, ENERO!J:J)) -> 1017.41 | E7: =IF(A7="","",SUMIF(ENERO!D:D, A7, ENERO!L:L)) -> 343.16 | F7: =IFERROR(__xludf.DUMMYFUNCTION("IFERROR( IF(A7="""","""",SUM( FILTER( VALUE(SUBSTITUTE(TK!B:B,""."","","")), REGEXMATCH(TK!A:A,A7), MONTH( DATE( VALUE(RIGHT(LEFT(TK!A:A,10),4)), VALUE(MID(TK!A:A,4,2)), VALUE(LEFT(TK!A:A,2)) ) )=1 ) )), """") "),"") | G7: =IFERROR(__xludf.DUMMYFUNCTION("IF( A7="""", """", SUM( FILTER( VALUE(SUBSTITUTE(FB!D:D, ""."", "","")), REGEXMATCH(FB!B:B, A7), MONTH(FB!E:E)=1 ) ) * 1.2 ) "),909.0) -> 909 | I7: =IF(A7="","",B7-SUM(C7:G7)) -> 748.93 | J7: =IF(A7="","",COUNTIFS(ENERO!D:D,A7,ENERO!O:O,"ENTREGADO")) -> 168 | K7: =IF(A7="","",COUNTIFS(ENERO!D:D,A7,ENERO!O:O,"DEVOLUCION")) -> 66 | L7: =IF(A7="","",COUNTIFS(ENERO!D:D,A7,ENERO!O:O,"PROCESO")) -> 0 | M7: =IF(A7="","",COUNTIFS(ENERO!D:D,A7,ENERO!O:O,"NOVEDAD")) -> 0 | N7: =IF(A7="","",COUNTIFS(ENERO!D:D,A7,ENERO!O:O,"PENDIENTE")) -> 37 | O7: =IF(A7="","",COUNTIFS(ENERO!D:D,A7,ENERO!O:O,"CANCELADO")) -> 16 | P7: =IF(A7="","",COUNTIFS(ENERO!D:D,A7,ENERO!O:O,"REVISAR")) -> 6
A8: =IFERROR(__xludf.DUMMYFUNCTION("""COMPUTED_VALUE"""),"FURBLADE™") -> FURBLADE™ | B8: =IF(A8="","",SUMIF(ENERO!D:D, A8, ENERO!G:G)) -> 39.99 | C8: =IF(A8="","",SUMIF(ENERO!D:D, A8, ENERO!E:E)) -> 7 | D8: =IF(A8="","",SUMIF(ENERO!D:D, A8, ENERO!J:J)) -> 9.9 | E8: =IF(A8="","",SUMIF(ENERO!D:D, A8, ENERO!L:L)) -> 0 | F8: =IFERROR(__xludf.DUMMYFUNCTION("IFERROR( IF(A8="""","""",SUM( FILTER( VALUE(SUBSTITUTE(TK!B:B,""."","","")), REGEXMATCH(TK!A:A,A8), MONTH( DATE( VALUE(RIGHT(LEFT(TK!A:A,10),4)), VALUE(MID(TK!A:A,4,2)), VALUE(LEFT(TK!A:A,2)) ) )=1 ) )), """") "),27.01) -> 27.01 | G8: =IFERROR(__xludf.DUMMYFUNCTION("IF( A8="""", """", SUM( FILTER( VALUE(SUBSTITUTE(FB!D:D, ""."", "","")), REGEXMATCH(FB!B:B, A8), MONTH(FB!E:E)=1 ) ) * 1.2 ) "),16.284) -> 16.284 | I8: =IF(A8="","",B8-SUM(C8:G8)) -> -20.204 | J8: =IF(A8="","",COUNTIFS(ENERO!D:D,A8,ENERO!O:O,"ENTREGADO")) -> 2 | K8: =IF(A8="","",COUNTIFS(ENERO!D:D,A8,ENERO!O:O,"DEVOLUCION")) -> 0 | L8: =IF(A8="","",COUNTIFS(ENERO!D:D,A8,ENERO!O:O,"PROCESO")) -> 0 | M8: =IF(A8="","",COUNTIFS(ENERO!D:D,A8,ENERO!O:O,"NOVEDAD")) -> 0 | N8: =IF(A8="","",COUNTIFS(ENERO!D:D,A8,ENERO!O:O,"PENDIENTE")) -> 2 | O8: =IF(A8="","",COUNTIFS(ENERO!D:D,A8,ENERO!O:O,"CANCELADO")) -> 0 | P8: =IF(A8="","",COUNTIFS(ENERO!D:D,A8,ENERO!O:O,"REVISAR")) -> 0
A9: =IFERROR(__xludf.DUMMYFUNCTION("""COMPUTED_VALUE"""),"REVISAR") -> REVISAR | B9: =IF(A9="","",SUMIF(ENERO!D:D, A9, ENERO!G:G)) -> 0 | D9: =IF(A9="","",SUMIF(ENERO!D:D, A9, ENERO!J:J)) -> 0 | I9: =IF(A9="","",B9-SUM(C9:G9)) -> 0 | J9: =IF(A9="","",COUNTIFS(ENERO!D:D,A9,ENERO!O:O,"ENTREGADO")) -> 0 | L9: =IF(A9="","",COUNTIFS(ENERO!D:D,A9,ENERO!O:O,"PROCESO")) -> 0 | M9: =IF(A9="","",COUNTIFS(ENERO!D:D,A9,ENERO!O:O,"NOVEDAD")) -> 0 | N9: =IF(A9="","",COUNTIFS(ENERO!D:D,A9,ENERO!O:O,"PENDIENTE")) -> 0 | O9: =IF(A9="","",COUNTIFS(ENERO!D:D,A9,ENERO!O:O,"CANCELADO")) -> 0 | P9: =IF(A9="","",COUNTIFS(ENERO!D:D,A9,ENERO!O:O,"REVISAR")) -> 15
A10: TOTAL | B10: =SUM(B4:B9) -> 14213.64 | C10: =SUM(C4:C9) -> 3327.77 | D10: =SUM(D4:D9) -> 3387.66 | E10: =SUM(E4:E9) -> 1176.57 | F10: =SUM(F4:F9) -> 154.09 | G10: =SUM(G4:G9) -> 3414.108 | H10: =SUM(H4:H9) -> 0 | I10: =SUM(I4:I9) -> 2753.442 | ... P10: =SUM(P4:P9) -> 28
A11: FEBRERO
A13: PRODUCTO | B13: VENTAS | C13: PROVEEDOR | D13: LOGISTICA | E13: DEVOLUCION | F13: TIK TOK ADS | G13: FACEBOOK ADS | H13: M PRIMA | I13: UTILIDAD | J13: =IFERROR( IF( SUM($J20:P20)=0, "", "ENTREGAS "&TEXT(J20/SUM($J20:P20), "0%") ), "" ) -> ENTREGAS 53% | K13: =IFERROR( IF( SUM($J20:P20)=0, "", "DEVOLUCION "&TEXT(K20/SUM($J20:P20), "0%") ), "" ) -> DEVOLUCION 17% | L13: =IFERROR( IF( SUM($J20:P20)=0, "", "PROCESO "&TEXT(L20/SUM($J20:P20), "0%") ), "" ) -> PROCESO 0% | M13: =IFERROR( IF( SUM($J20:P20)=0, "", "NOVEDAD "&TEXT(M20/SUM($J20:P20), "0%") ), "" ) -> NOVEDAD 0% | N13: =IFERROR( IF( SUM($J20:P20)=0, "", "PENDIENTES "&TEXT(N20/SUM($J20:P20), "0%") ), "" ) -> PENDIENTES 23% | O13: =IFERROR( IF( SUM($J20:P20)=0, "", "CANCELADOS "&TEXT(O20/SUM($J20:P20), "0%") ), "" ) -> CANCELADOS 6% | P13: =IFERROR( IF( SUM($J20:P20)=0, "", "REVISAR "&TEXT(P20/SUM($J20:P20), "0%") ), "" ) -> REVISAR 2%
A14: =IFERROR(__xludf.DUMMYFUNCTION("UNIQUE( FILTER( TRIM( FLATTEN( SPLIT(FEBRERO!D12:D1000, "";"") ) ), FLATTEN( SPLIT(FEBRERO!D12:D1000, "";"") )<>"""" ) )"),"Llave Multifuncional 360™") -> Llave Multifuncional 360™ | B14: =IF(A14="","",SUMIF(FEBRERO!D:D, A14, FEBRERO!G:G)) -> 431.86 | C14: =IF(A14="","",SUMIF(FEBRERO!D:D, A14, FEBRERO!E:E)) -> 114 | D14: =IF(A14="","",SUMIF(FEBRERO!D:D, A14, FEBRERO!J:J)) -> 119.29 | E14: =IF(A14="","",SUMIF(FEBRERO!D:D, A14, FEBRERO!L:L)) -> 53.61 | F14: =IFERROR(__xludf.DUMMYFUNCTION("IFERROR( IF(A14="""","""",SUM( FILTER( VALUE(SUBSTITUTE(TK!B:B,""."","","")), REGEXMATCH(TK!A:A,A14), MONTH( DATE( VALUE(RIGHT(LEFT(TK!A:A,10),4)), VALUE(MID(TK!A:A,4,2)), VALUE(LEFT(TK!A:A,2)) ) )=2 ) )), """") "),"") | G14: =IFERROR(__xludf.DUMMYFUNCTION("IF( A4="""", """", SUM( FILTER( VALUE(SUBSTITUTE(FB!D:D, ""."", "","")), REGEXMATCH(FB!B:B, A14), MONTH(FB!E:E)=2 ) ) * 1.2 ) "),190.66799999999998) -> 190.668 | I14: =IF(A14="","",B14-SUM(C14:G14)) -> -45.708 | J14: =IF(A14="","",COUNTIFS(FEBRERO!D:D,A14,FEBRERO!O:O,"ENTREGADO")) -> 20 | K14: =IF(A14="","",COUNTIFS(FEBRERO!D:D,A14,FEBRERO!O:O,"DEVOLUCION")) -> 11 | L14: =IF(A14="","",COUNTIFS(FEBRERO!D:D,A14,FEBRERO!O:O,"PROCESO")) -> 0 | M14: =IF(A14="","",COUNTIFS(FEBRERO!D:D,A14,FEBRERO!O:O,"NOVEDAD")) -> 0 | N14: =IF(A14="","",COUNTIFS(FEBRERO!D:D,A14,FEBRERO!O:O,"PENDIENTE")) -> 7 | O14: =IF(A14="","",COUNTIFS(FEBRERO!D:D,A14,FEBRERO!O:O,"CANCELADO")) -> 1 | P14: =IF(A14="","",COUNTIFS(FEBRERO!D:D,A14,FEBRERO!O:O,"REVISAR")) -> 0
A15: =IFERROR(__xludf.DUMMYFUNCTION("""COMPUTED_VALUE"""),"Cuchillo Tazaki™") -> Cuchillo Tazaki™ | B15: =IF(A15="","",SUMIF(FEBRERO!D:D, A15, FEBRERO!G:G)) -> 3869.68 | C15: =IF(A15="","",SUMIF(FEBRERO!D:D, A15, FEBRERO!E:E)) -> 1214.4 | D15: =IF(A15="","",SUMIF(FEBRERO!D:D, A15, FEBRERO!J:J)) -> 938.37 | E15: =IF(A15="","",SUMIF(FEBRERO!D:D, A15, FEBRERO!L:L)) -> 145.53 | F15: =IFERROR(__xludf.DUMMYFUNCTION("IFERROR( IF(A15="""","""",SUM( FILTER( VALUE(SUBSTITUTE(TK!B:B,""."","","")), REGEXMATCH(TK!A:A,A15), MONTH( DATE( VALUE(RIGHT(LEFT(TK!A:A,10),4)), VALUE(MID(TK!A:A,4,2)), VALUE(LEFT(TK!A:A,2)) ) )=2 ) )), """") "),"") | G15: =IFERROR(__xludf.DUMMYFUNCTION("IF( A5="""", """", SUM( FILTER( VALUE(SUBSTITUTE(FB!D:D, ""."", "","")), REGEXMATCH(FB!B:B, A15), MONTH(FB!E:E)=2 ) ) * 1.2 ) "),1425.2160000000001) -> 1425.216 | I15: =IF(A15="","",B15-SUM(C15:G15)) -> 146.164 | J15: =IF(A15="","",COUNTIFS(FEBRERO!D:D,A15,FEBRERO!O:O,"ENTREGADO")) -> 159 | K15: =IF(A15="","",COUNTIFS(FEBRERO!D:D,A15,FEBRERO!O:O,"DEVOLUCION")) -> 57 | L15: =IF(A15="","",COUNTIFS(FEBRERO!D:D,A15,FEBRERO!O:O,"PROCESO")) -> 0 | M15: =IF(A15="","",COUNTIFS(FEBRERO!D:D,A15,FEBRERO!O:O,"NOVEDAD")) -> 0 | N15: =IF(A15="","",COUNTIFS(FEBRERO!D:D,A15,FEBRERO!O:O,"PENDIENTE")) -> 79 | O15: =IF(A15="","",COUNTIFS(FEBRERO!D:D,A15,FEBRERO!O:O,"CANCELADO")) -> 17 | P15: =IF(A15="","",COUNTIFS(FEBRERO!D:D,A15,FEBRERO!O:O,"REVISAR")) -> 1
A16: =IFERROR(__xludf.DUMMYFUNCTION("""COMPUTED_VALUE"""),"FilmPro®") -> FilmPro® | B16: =IF(A16="","",SUMIF(FEBRERO!D:D, A16, FEBRERO!G:G)) -> 4990 | C16: =IF(A16="","",SUMIF(FEBRERO!D:D, A16, FEBRERO!E:E)) -> 952.7 | D16: =IF(A16="","",SUMIF(FEBRERO!D:D, A16, FEBRERO!J:J)) -> 1132.38 | E16: =IF(A16="","",SUMIF(FEBRERO!D:D, A16, FEBRERO!L:L)) -> 116.18 | F16: =IFERROR(__xludf.DUMMYFUNCTION("IFERROR( IF(A16="""","""",SUM( FILTER( VALUE(SUBSTITUTE(TK!B:B,""."","","")), REGEXMATCH(TK!A:A,A16), MONTH( DATE( VALUE(RIGHT(LEFT(TK!A:A,10),4)), VALUE(MID(TK!A:A,4,2)), VALUE(LEFT(TK!A:A,2)) ) )=2 ) )), """") "),300.71) -> 300.71 | G16: =IFERROR(__xludf.DUMMYFUNCTION("IF( A6="""", """", SUM( FILTER( VALUE(SUBSTITUTE(FB!D:D, ""."", "","")), REGEXMATCH(FB!B:B, A16), MONTH(FB!E:E)=2 ) ) * 1.2 ) "),1246.488) -> 1246.488 | I16: =IF(A16="","",B16-SUM(C16:G16)) -> 1241.542 | J16: =IF(A16="","",COUNTIFS(FEBRERO!D:D,A16,FEBRERO!O:O,"ENTREGADO")) -> 197 | K16: =IF(A16="","",COUNTIFS(FEBRERO!D:D,A16,FEBRERO!O:O,"DEVOLUCION")) -> 52 | L16: =IF(A16="","",COUNTIFS(FEBRERO!D:D,A16,FEBRERO!O:O,"PROCESO")) -> 1 | M16: =IF(A16="","",COUNTIFS(FEBRERO!D:D,A16,FEBRERO!O:O,"NOVEDAD")) -> 1 | N16: =IF(A16="","",COUNTIFS(FEBRERO!D:D,A16,FEBRERO!O:O,"PENDIENTE")) -> 74 | O16: =IF(A16="","",COUNTIFS(FEBRERO!D:D,A16,FEBRERO!O:O,"CANCELADO")) -> 22 | P16: =IF(A16="","",COUNTIFS(FEBRERO!D:D,A16,FEBRERO!O:O,"REVISAR")) -> 1
A17: =IFERROR(__xludf.DUMMYFUNCTION("""COMPUTED_VALUE"""),"REVISAR") -> REVISAR | B17: =IF(A17="","",SUMIF(FEBRERO!D:D, A17, FEBRERO!G:G)) -> 0 | C17: =IF(A17="","",SUMIF(FEBRERO!D:D, A17, FEBRERO!E:E)) -> 0 | D17: =IF(A17="","",SUMIF(FEBRERO!D:D, A17, FEBRERO!J:J)) -> 0 | E17: =IF(A17="","",SUMIF(FEBRERO!D:D, A17, FEBRERO!L:L)) -> 0 | F17: =IFERROR(__xludf.DUMMYFUNCTION("IFERROR( IF(A17="""","""",SUM( FILTER( VALUE(SUBSTITUTE(TK!B:B,""."","","")), REGEXMATCH(TK!A:A,A17), MONTH( DATE( VALUE(RIGHT(LEFT(TK!A:A,10),4)), VALUE(MID(TK!A:A,4,2)), VALUE(LEFT(TK!A:A,2)) ) )=2 ) )), """") "),"") | I17: =IF(A17="","",B17-SUM(C17:G17)) -> 0 | J17: =IF(A17="","",COUNTIFS(FEBRERO!D:D,A17,FEBRERO!O:O,"ENTREGADO")) -> 0 | K17: =IF(A17="","",COUNTIFS(FEBRERO!D:D,A17,FEBRERO!O:O,"DEVOLUCION")) -> 0 | L17: =IF(A17="","",COUNTIFS(FEBRERO!D:D,A17,FEBRERO!O:O,"PROCESO")) -> 0 | M17: =IF(A17="","",COUNTIFS(FEBRERO!D:D,A17,FEBRERO!O:O,"NOVEDAD")) -> 0 | N17: =IF(A17="","",COUNTIFS(FEBRERO!D:D,A17,FEBRERO!O:O,"PENDIENTE")) -> 0 | O17: =IF(A17="","",COUNTIFS(FEBRERO!D:D,A17,FEBRERO!O:O,"CANCELADO")) -> 0 | P17: =IF(A17="","",COUNTIFS(FEBRERO!D:D,A17,FEBRERO!O:O,"REVISAR")) -> 12
A18: =IFERROR(__xludf.DUMMYFUNCTION("""COMPUTED_VALUE"""),"FreeBeat Adapter") -> FreeBeat Adapter | B18: =IF(A18="","",SUMIF(FEBRERO!D:D, A18, FEBRERO!G:G)) -> 152.92 | C18: =IF(A18="","",SUMIF(FEBRERO!D:D, A18, FEBRERO!E:E)) -> 70 | D18: =IF(A18="","",SUMIF(FEBRERO!D:D, A18, FEBRERO!J:J)) -> 37.85 | E18: =IF(A18="","",SUMIF(FEBRERO!D:D, A18, FEBRERO!L:L)) -> 0 | F18: =IFERROR(__xludf.DUMMYFUNCTION("IFERROR( IF(A18="""","""",SUM( FILTER( VALUE(SUBSTITUTE(TK!B:B,""."","","")), REGEXMATCH(TK!A:A,A18), MONTH( DATE( VALUE(RIGHT(LEFT(TK!A:A,10),4)), VALUE(MID(TK!A:A,4,2)), VALUE(LEFT(TK!A:A,2)) ) )=2 ) )), """") "),"") | G18: =IFERROR(__xludf.DUMMYFUNCTION("IF( A8="""", """", SUM( FILTER( VALUE(SUBSTITUTE(FB!D:D, ""."", "","")), REGEXMATCH(FB!B:B, A18), MONTH(FB!E:E)=2 ) ) * 1.2 ) "),29.483999999999998) -> 29.484 | I18: =IF(A18="","",B18-SUM(C18:G18)) -> 15.586 | J18: =IF(A18="","",COUNTIFS(FEBRERO!D:D,A18,FEBRERO!O:O,"ENTREGADO")) -> 6 | K18: =IF(A18="","",COUNTIFS(FEBRERO!D:D,A18,FEBRERO!O:O,"DEVOLUCION")) -> 1 | L18: =IF(A18="","",COUNTIFS(FEBRERO!D:D,A18,FEBRERO!O:O,"PROCESO")) -> 0 | M18: =IF(A18="","",COUNTIFS(FEBRERO!D:D,A18,FEBRERO!O:O,"NOVEDAD")) -> 0 | N18: =IF(A18="","",COUNTIFS(FEBRERO!D:D,A18,FEBRERO!O:O,"PENDIENTE")) -> 6 | O18: =IF(A18="","",COUNTIFS(FEBRERO!D:D,A18,FEBRERO!O:O,"CANCELADO")) -> 0 | P18: =IF(A18="","",COUNTIFS(FEBRERO!D:D,A18,FEBRERO!O:O,"REVISAR")) -> 0
A19: =IFERROR(__xludf.DUMMYFUNCTION("""COMPUTED_VALUE"""),"DrainGuard Pro™") -> DrainGuard Pro™ | B19: =IF(A19="","",SUMIF(FEBRERO!D:D, A19, FEBRERO!G:G)) -> 57.01 | C19: =IF(A19="","",SUMIF(FEBRERO!D:D, A19, FEBRERO!E:E)) -> 20 | D19: =IF(A19="","",SUMIF(FEBRERO!D:D, A19, FEBRERO!J:J)) -> 8.98 | E19: =IF(A19="","",SUMIF(FEBRERO!D:D, A19, FEBRERO!L:L)) -> 0 | F19: =IFERROR(__xludf.DUMMYFUNCTION("IFERROR( IF(A19="""","""",SUM( FILTER( VALUE(SUBSTITUTE(TK!B:B,""."","","")), REGEXMATCH(TK!A:A,A19), MONTH( DATE( VALUE(RIGHT(LEFT(TK!A:A,10),4)), VALUE(MID(TK!A:A,4,2)), VALUE(LEFT(TK!A:A,2)) ) )=2 ) )), """") "),"") | G19: =IFERROR(__xludf.DUMMYFUNCTION("IF( A9="""", """", SUM( FILTER( VALUE(SUBSTITUTE(FB!D:D, ""."", "","")), REGEXMATCH(FB!B:B, A19), MONTH(FB!E:E)=2 ) ) * 1.2 ) "),"#N/A") -> #N/A | I19: =IF(A19="","",B19-SUM(C19:G19)) -> #N/A | J19: =IF(A19="","",COUNTIFS(FEBRERO!D:D,A19,FEBRERO!O:O,"ENTREGADO")) -> 2 | K19: =IF(A19="","",COUNTIFS(FEBRERO!D:D,A19,FEBRERO!O:O,"DEVOLUCION")) -> 0 | L19: =IF(A19="","",COUNTIFS(FEBRERO!D:D,A19,FEBRERO!O:O,"PROCESO")) -> 0 | M19: =IF(A19="","",COUNTIFS(FEBRERO!D:D,A19,FEBRERO!O:O,"NOVEDAD")) -> 0 | N19: =IF(A19="","",COUNTIFS(FEBRERO!D:D,A19,FEBRERO!O:O,"PENDIENTE")) -> 0 | O19: =IF(A19="","",COUNTIFS(FEBRERO!D:D,A19,FEBRERO!O:O,"CANCELADO")) -> 0 | P19: =IF(A19="","",COUNTIFS(FEBRERO!D:D,A19,FEBRERO!O:O,"REVISAR")) -> 0
A20: TOTAL | B20: =SUM(B14:B19) -> 9501.47 | C20: =SUM(C14:C19) -> 2371.1 | D20: =SUM(D14:D19) -> 2236.87 | E20: =SUM(E14:E19) -> 315.32 | F20: =SUM(F14:F19) -> 300.71 | G20: =SUM(G14:G19) -> #N/A | H20: =SUM(H14:H19) -> 0 | I20: =SUM(I14:I19) -> #N/A | ... P20: =SUM(P14:P19) -> 14
A21: MARZO
A23: PRODUCTO | B23: VENTAS | C23: PROVEEDOR | D23: LOGISTICA | E23: DEVOLUCION | F23: TIK TOK ADS | G23: FACEBOOK ADS | H23: M PRIMA | I23: UTILIDAD | J23: =IFERROR( IF( SUM($J30:P30)=0, "", "ENTREGAS "&TEXT(J30/SUM($J30:P30), "0%") ), "" ) -> ENTREGAS 49% | K23: =IFERROR( IF( SUM($J30:P30)=0, "", "DEVOLUCION "&TEXT(K30/SUM($J30:P30), "0%") ), "" ) -> DEVOLUCION 8% | L23: =IFERROR( IF( SUM($J30:P30)=0, "", "PROCESO "&TEXT(L30/SUM($J30:P30), "0%") ), "" ) -> PROCESO 8% | M23: =IFERROR( IF( SUM($J30:P30)=0, "", "NOVEDAD "&TEXT(M30/SUM($J30:P30), "0%") ), "" ) -> NOVEDAD 5% | N23: =IFERROR( IF( SUM($J30:P30)=0, "", "PENDIENTES "&TEXT(N30/SUM($J30:P30), "0%") ), "" ) -> PENDIENTES 24% | O23: =IFERROR( IF( SUM($J30:P30)=0, "", "CANCELADOS "&TEXT(O30/SUM($J30:P30), "0%") ), "" ) -> CANCELADOS 5% | P23: =IFERROR( IF( SUM($J30:P30)=0, "", "REVISAR "&TEXT(P30/SUM($J30:P30), "0%") ), "" ) -> REVISAR 1%
A24: =IFERROR(__xludf.DUMMYFUNCTION("UNIQUE( FILTER( TRIM( FLATTEN( SPLIT(MARZO!D22:D1000, "";"") ) ), FLATTEN( SPLIT(MARZO!D22:D1000, "";"") )<>"""" ) )"),"FilmPro®") -> FilmPro® | B24: =IF(A24="","",SUMIF(MARZO!D:D, A24, MARZO!G:G)) -> 3424.94 | C24: =IF(A24="","",SUMIF(MARZO!D:D, A24, MARZO!E:E)) -> 683.82 | D24: =IF(A24="","",SUMIF(MARZO!D:D, A24, MARZO!J:J)) -> 795.02 | E24: =IF(A24="","",SUMIF(MARZO!D:D, A24, MARZO!L:L)) -> 0 | F24: =IFERROR(__xludf.DUMMYFUNCTION("IFERROR( IF(A24="""","""",SUM( FILTER( VALUE(SUBSTITUTE(TK!B:B,""."","","")), REGEXMATCH(TK!A:A,A24), MONTH( DATE( VALUE(RIGHT(LEFT(TK!A:A,10),4)), VALUE(MID(TK!A:A,4,2)), VALUE(LEFT(TK!A:A,2)) ) )=3 ) )), """") "),"") | I24: =IF(A24="","",B24-SUM(C24:G24)) -> 1946.1 | J24: =IF(A24="","",COUNTIFS(MARZO!D:D,A24,MARZO!O:O,"ENTREGADO")) -> 135 | K24: =IF(A24="","",COUNTIFS(MARZO!D:D,A24,MARZO!O:O,"DEVOLUCION")) -> 24 | L24: =IF(A24="","",COUNTIFS(MARZO!D:D,A24,MARZO!O:O,"PROCESO")) -> 24 | M24: =IF(A24="","",COUNTIFS(MARZO!D:D,A24,MARZO!O:O,"NOVEDAD")) -> 12 | N24: =IF(A24="","",COUNTIFS(MARZO!D:D,A24,MARZO!O:O,"PENDIENTE")) -> 52 | O24: =IF(A24="","",COUNTIFS(MARZO!D:D,A24,MARZO!O:O,"CANCELADO")) -> 15 | P24: =IF(A24="","",COUNTIFS(MARZO!D:D,A24,MARZO!O:O,"REVISAR")) -> 1
A25: =IFERROR(__xludf.DUMMYFUNCTION("""COMPUTED_VALUE"""),"Cuchillo Tazaki™") -> Cuchillo Tazaki™ | B25: =IF(A25="","",SUMIF(MARZO!D:D, A25, MARZO!G:G)) -> 465 | C25: =IF(A25="","",SUMIF(MARZO!D:D, A25, MARZO!E:E)) -> 152.55 | D25: =IF(A25="","",SUMIF(MARZO!D:D, A25, MARZO!J:J)) -> 116.31 | E25: =IF(A25="","",SUMIF(MARZO!D:D, A25, MARZO!L:L)) -> 0 | F25: =IFERROR(__xludf.DUMMYFUNCTION("IFERROR( IF(A25="""","""",SUM( FILTER( VALUE(SUBSTITUTE(TK!B:B,""."","","")), REGEXMATCH(TK!A:A,A25), MONTH( DATE( VALUE(RIGHT(LEFT(TK!A:A,10),4)), VALUE(MID(TK!A:A,4,2)), VALUE(LEFT(TK!A:A,2)) ) )=2 ) )), """") "),"") | I25: =IF(A25="","",B25-SUM(C25:G25)) -> 196.14 | J25: =IF(A25="","",COUNTIFS(MARZO!D:D,A25,MARZO!O:O,"ENTREGADO")) -> 20 | K25: =IF(A25="","",COUNTIFS(MARZO!D:D,A25,MARZO!O:O,"DEVOLUCION")) -> 1 | L25: =IF(A25="","",COUNTIFS(MARZO!D:D,A25,MARZO!O:O,"PROCESO")) -> 5 | M25: =IF(A25="","",COUNTIFS(MARZO!D:D,A25,MARZO!O:O,"NOVEDAD")) -> 7 | N25: =IF(A25="","",COUNTIFS(MARZO!D:D,A25,MARZO!O:O,"PENDIENTE")) -> 25 | O25: =IF(A25="","",COUNTIFS(MARZO!D:D,A25,MARZO!O:O,"CANCELADO")) -> 1 | P25: =IF(A25="","",COUNTIFS(MARZO!D:D,A25,MARZO!O:O,"REVISAR")) -> 0
A26: =IFERROR(__xludf.DUMMYFUNCTION("""COMPUTED_VALUE"""),"FreeBeat Adapter") -> FreeBeat Adapter | B26: =IF(A26="","",SUMIF(MARZO!D:D, A26, MARZO!G:G)) -> 276.78 | C26: =IF(A26="","",SUMIF(MARZO!D:D, A26, MARZO!E:E)) -> 130 | D26: =IF(A26="","",SUMIF(MARZO!D:D, A26, MARZO!J:J)) -> 66.33 | E26: =IF(A26="","",SUMIF(MARZO!D:D, A26, MARZO!L:L)) -> 0 | F26: =IFERROR(__xludf.DUMMYFUNCTION("IFERROR( IF(A26="""","""",SUM( FILTER( VALUE(SUBSTITUTE(TK!B:B,""."","","")), REGEXMATCH(TK!A:A,A26), MONTH( DATE( VALUE(RIGHT(LEFT(TK!A:A,10),4)), VALUE(MID(TK!A:A,4,2)), VALUE(LEFT(TK!A:A,2)) ) )=2 ) )), """") "),"") | I26: =IF(A26="","",B26-SUM(C26:G26)) -> 80.45 | J26: =IF(A26="","",COUNTIFS(MARZO!D:D,A26,MARZO!O:O,"ENTREGADO")) -> 11 | K26: =IF(A26="","",COUNTIFS(MARZO!D:D,A26,MARZO!O:O,"DEVOLUCION")) -> 2 | L26: =IF(A26="","",COUNTIFS(MARZO!D:D,A26,MARZO!O:O,"PROCESO")) -> 0 | M26: =IF(A26="","",COUNTIFS(MARZO!D:D,A26,MARZO!O:O,"NOVEDAD")) -> 0 | N26: =IF(A26="","",COUNTIFS(MARZO!D:D,A26,MARZO!O:O,"PENDIENTE")) -> 9 | O26: =IF(A26="","",COUNTIFS(MARZO!D:D,A26,MARZO!O:O,"CANCELADO")) -> 0 | P26: =IF(A26="","",COUNTIFS(MARZO!D:D,A26,MARZO!O:O,"REVISAR")) -> 1
A27: =IFERROR(__xludf.DUMMYFUNCTION("""COMPUTED_VALUE"""),"DrainGuard Pro™") -> DrainGuard Pro™ | B27: =IF(A27="","",SUMIF(MARZO!D:D, A27, MARZO!G:G)) -> 510.05 | C27: =IF(A27="","",SUMIF(MARZO!D:D, A27, MARZO!E:E)) -> 156.5 | D27: =IF(A27="","",SUMIF(MARZO!D:D, A27, MARZO!J:J)) -> 108.68 | E27: =IF(A27="","",SUMIF(MARZO!D:D, A27, MARZO!L:L)) -> 0 | F27: =IFERROR(__xludf.DUMMYFUNCTION("IFERROR( IF(A27="""","""",SUM( FILTER( VALUE(SUBSTITUTE(TK!B:B,""."","","")), REGEXMATCH(TK!A:A,A27), MONTH( DATE( VALUE(RIGHT(LEFT(TK!A:A,10),4)), VALUE(MID(TK!A:A,4,2)), VALUE(LEFT(TK!A:A,2)) ) )=2 ) )), """") "),"") | I27: =IF(A27="","",B27-SUM(C27:G27)) -> 244.87 | J27: =IF(A27="","",COUNTIFS(MARZO!D:D,A27,MARZO!O:O,"ENTREGADO")) -> 19 | K27: =IF(A27="","",COUNTIFS(MARZO!D:D,A27,MARZO!O:O,"DEVOLUCION")) -> 4 | L27: =IF(A27="","",COUNTIFS(MARZO!D:D,A27,MARZO!O:O,"PROCESO")) -> 0 | M27: =IF(A27="","",COUNTIFS(MARZO!D:D,A27,MARZO!O:O,"NOVEDAD")) -> 0 | N27: =IF(A27="","",COUNTIFS(MARZO!D:D,A27,MARZO!O:O,"PENDIENTE")) -> 5 | O27: =IF(A27="","",COUNTIFS(MARZO!D:D,A27,MARZO!O:O,"CANCELADO")) -> 4 | P27: =IF(A27="","",COUNTIFS(MARZO!D:D,A27,MARZO!O:O,"REVISAR")) -> 0
A28: =IFERROR(__xludf.DUMMYFUNCTION("""COMPUTED_VALUE"""),"JBL GO 4") -> JBL GO 4 | B28: =IF(A28="","",SUMIF(FEBRERO!D:D, A28, FEBRERO!G:G)) -> 0 | C28: =IF(A28="","",SUMIF(MARZO!D:D, A28, MARZO!E:E)) -> 0 | D28: =IF(A28="","",SUMIF(MARZO!D:D, A28, MARZO!J:J)) -> 0 | E28: =IF(A28="","",SUMIF(MARZO!D:D, A28, MARZO!L:L)) -> 0 | F28: =IFERROR(__xludf.DUMMYFUNCTION("IFERROR( IF(A28="""","""",SUM( FILTER( VALUE(SUBSTITUTE(TK!B:B,""."","","")), REGEXMATCH(TK!A:A,A28), MONTH( DATE( VALUE(RIGHT(LEFT(TK!A:A,10),4)), VALUE(MID(TK!A:A,4,2)), VALUE(LEFT(TK!A:A,2)) ) )=2 ) )), """") "),"") | I28: =IF(A28="","",B28-SUM(C28:G28)) -> 0 | J28: =IF(A28="","",COUNTIFS(MARZO!D:D,A28,MARZO!O:O,"ENTREGADO")) -> 0 | K28: =IF(A28="","",COUNTIFS(MARZO!D:D,A28,MARZO!O:O,"DEVOLUCION")) -> 1 | L28: =IF(A28="","",COUNTIFS(MARZO!D:D,A28,MARZO!O:O,"PROCESO")) -> 0 | M28: =IF(A28="","",COUNTIFS(MARZO!D:D,A28,MARZO!O:O,"NOVEDAD")) -> 0 | N28: =IF(A28="","",COUNTIFS(MARZO!D:D,A28,MARZO!O:O,"PENDIENTE")) -> 0 | O28: =IF(A28="","",COUNTIFS(MARZO!D:D,A28,MARZO!O:O,"CANCELADO")) -> 0 | P28: =IF(A28="","",COUNTIFS(FEBRERO!D:D,A28,FEBRERO!O:O,"REVISAR")) -> 0
B29: =IF(A29="","",SUMIF(FEBRERO!D:D, A29, FEBRERO!G:G)) | C29: =IF(A29="","",SUMIF(FEBRERO!D:D, A29, FEBRERO!E:E)) | D29: =IF(A29="","",SUMIF(MARZO!D:D, A29, MARZO!J:J)) | E29: =IF(A29="","",SUMIF(FEBRERO!D:D, A29, FEBRERO!L:L)) | F29: =IFERROR(__xludf.DUMMYFUNCTION("IFERROR( IF(A29="""","""",SUM( FILTER( VALUE(SUBSTITUTE(TK!B:B,""."","","")), REGEXMATCH(TK!A:A,A29), MONTH( DATE( VALUE(RIGHT(LEFT(TK!A:A,10),4)), VALUE(MID(TK!A:A,4,2)), VALUE(LEFT(TK!A:A,2)) ) )=2 ) )), """") "),"") | I29: =IF(A29="","",B29-SUM(C29:G29)) | J29: =IF(A29="","",COUNTIFS(MARZO!D:D,A29,MARZO!O:O,"ENTREGADO")) | K29: =IF(A29="","",COUNTIFS(FEBRERO!D:D,A29,FEBRERO!O:O,"DEVOLUCION")) | L29: =IF(A29="","",COUNTIFS(FEBRERO!D:D,A29,FEBRERO!O:O,"PROCESO")) | M29: =IF(A29="","",COUNTIFS(FEBRERO!D:D,A29,FEBRERO!O:O,"NOVEDAD")) | N29: =IF(A29="","",COUNTIFS(FEBRERO!D:D,A29,FEBRERO!O:O,"PENDIENTE")) | O29: =IF(A29="","",COUNTIFS(FEBRERO!D:D,A29,FEBRERO!O:O,"CANCELADO")) | P29: =IF(A29="","",COUNTIFS(FEBRERO!D:D,A29,FEBRERO!O:O,"REVISAR"))
A30: TOTAL | B30: =SUM(B24:B29) -> 4676.77 | C30: =SUM(C24:C29) -> 1122.87 | D30: =SUM(D24:D29) -> 1086.34 | E30: =SUM(E24:E29) -> 0 | F30: =SUM(F24:F29) -> 0 | G30: =SUM(G24:G29) -> 0 | H30: =SUM(H24:H29) -> 0 | I30: =SUM(I24:I29) -> 2467.56 | ... P30: =SUM(P24:P29) -> 2

Sheet TK
A1: Nombre de la campaña | B1: Coste | C1: Moneda
A2: 22/01/2026 - FilmPro® - ABO | B2: 127.08 | C2: USD
A3: 23/01/2025 - FURBLADE™ - ABO | B3: 46049 | C3: USD
A4: 25/01/2025 - Llave Multifuncional 360™ - ABO | B4: 0 | C4: USD
A5: Total: 3 resultados | B5: 154.09 | C5: USD
K6: 10/01 DUPLICADO 09/11/2025-Cuchillo Tazaki™- ABO - 16/11/2025 | L6: 17/01/2026 - FilmPro® - CBO | M6: 27/12/2025 / DUPLICADO CBO / 22/12/2025 /Llave Multifuncional 360™/ ABO | N6: 06/01/2026- FilmPro® - ABO | O6: 25/01/2026- Llave Multifuncional 360™-CBO | P6: 04/01/2026- FLORA FRESH PRO™- ABO | Q6: 27/01/2026 - FURBLADE™ -ABO | R6: JBL / 20-01 / WHATSAPP | S6: 06/01/2026- FLORA FRESH PRO™- ESCALADO -CBO
A7: FEBRERO | J7: 0 | K7: 0 | L7: 0 | M7: 0 | N7: 0 | O7: 0 | P7: 0 | Q7: 0 | R7: 0 | S7: 0
A8: 23/02/2026- FilmPro® - ABO | B8: 54.26 | J8: 0 | K8: 0 | L8: 0 | M8: 0 | N8: 0 | O8: 0 | P8: 0 | Q8: 0 | R8: 0 | S8: 0
A9: 22/02/2026 - FilmPro® - ABO - | B9: 51.54 | J9: 0 | K9: 0 | L9: 0 | M9: 0 | N9: 0 | O9: 0 | P9: 0 | Q9: 0 | R9: 0 | S9: 0
A10: 18/02/2026 - FilmPro® - ABO - | B10: 46.05 | J10: 0 | K10: 0 | L10: 0 | M10: 0 | N10: 0 | O10: 0 | P10: 20.64 | Q10: 0 | R10: 0 | S10: 0
A11: 21/02/2026 - FilmPro® - ABO - | B11: 40.27 | J11: 0 | K11: 0 | L11: 0 | M11: 41.55 | N11: 0 | O11: 0 | P11: 0 | Q11: 0 | R11: 0 | S11: 0
A12: 19/02/2026 - FilmPro® - ABO - | B12: 39.87 | J12: 0 | K12: 0 | L12: 0 | M12: 0 | N12: 0 | O12: 0 | P12: 17.81 | Q12: 0 | R12: 0 | S12: 0
A13: 17/02/2026- FilmPro® - ABO - | B13: 36.39 | J13: 0 | K13: 0 | L13: 0 | M13: 54.25 | N13: 0 | O13: 0 | P13: 0 | Q13: 0 | R13: 0 | S13: 0
A14: 20/02/2026 - FilmPro® - ABO - | B14: 32.33 | J14: 0 | K14: 0 | L14: 0 | M14: 0 | N14: 0 | O14: 0 | P14: 9.33 | Q14: 0 | R14: 0 | S14: 0
J15: 0 | K15: 0 | L15: 0 | M15: 0 | N15: 17.96 | O15: 0 | P15: 0 | Q15: 0 | R15: 0 | S15: 0
J16: 0 | K16: 0 | L16: 0 | M16: 0 | N16: 0 | O16: 0 | P16: 0 | Q16: 0 | R16: 0 | S16: 6.28
J17: 0 | K17: 0 | L17: 0 | M17: 51.74 | N17: 0 | O17: 0 | P17: 0 | Q17: 0 | R17: 0 | S17: 0
J18: 0 | K18: 0 | L18: 0 | M18: 0 | N18: 0 | O18: 0 | P18: 5.89 | Q18: 0 | R18: 0 | S18: 0
J19: 0 | K19: 0 | L19: 0 | M19: 0 | N19: 19.44 | O19: 0 | P19: 0 | Q19: 0 | R19: 0 | S19: 0
J20: 0 | K20: 0 | L20: 0 | M20: 52.45 | N20: 0 | O20: 0 | P20: 0 | Q20: 0 | R20: 0 | S20: 0
J21: 0 | K21: 0 | L21: 0 | M21: 0 | N21: 0 | O21: 0 | P21: 5.96 | Q21: 0 | R21: 0 | S21: 0
J22: 0 | K22: 0 | L22: 0 | M22: 0 | N22: 17.63 | O22: 0 | P22: 0 | Q22: 0 | R22: 0 | S22: 0
J23: 0 | K23: 0 | L23: 0 | M23: 0 | N23: 0 | O23: 0 | P23: 4.72 | Q23: 0 | R23: 0 | S23: 0
J24: 0 | K24: 0 | L24: 0 | M24: 0 | N24: 15.94 | O24: 0 | P24: 0 | Q24: 0 | R24: 0 | S24: 0
J25: 0 | K25: 0 | L25: 0 | M25: 0 | N25: 0 | O25: 0 | P25: 2.23 | Q25: 0 | R25: 0 | S25: 0
J26: 0 | K26: 0 | L26: 0 | M26: 0 | N26: 11.26 | O26: 0 | P26: 0 | Q26: 0 | R26: 0 | S26: 0
... J65: 0 | K65: 0 | L65: 0 | M65: 0 | N65: 0 | O65: 0 | P65: 0 | Q65: 13.57 | R65: 0 | S65: 0

Sheet FB
A1: Nombre de la cuenta | B1: Nombre de la campaña | C1: Divisa | D1: Importe gastado (USD) | E1: Inicio del informe | F1: Fin del informe
C2: USD | D2: 2855.86 | E2: 46023 | F2: 46053
A3: 2 IMPORTEX MODA 2025 CTA PUBLICITARIA | B3: 10/01/ DUPLICADO / 06/01/ FilmPro® - CBO | C3: USD | D3: 853.59 | E3: 46023 | F3: 46053
A4: IMPORTEX MODA 2025 CTA PUBLICITARIA | B4: 10/01 DUPLICADO 09/11/2025-Cuchillo Tazaki™- ABO - 16/11/2025 | C4: USD | D4: 757.5 | E4: 46023 | F4: 46053
A5: IMPORTEX MODA 2025 CTA PUBLICITARIA | B5: 17/01/2026 - FilmPro® - CBO | C5: USD | D5: 539.77 | E5: 46023 | F5: 46053
A6: 2 IMPORTEX MODA 2025 CTA PUBLICITARIA | B6: 25/01/2026- Llave Multifuncional 360™-CBO | C6: USD | D6: 237.98 | E6: 46023 | F6: 46053
A7: IMPORTEX MODA 2025 CTA PUBLICITARIA | B7: 27/12/2025 / DUPLICADO CBO / 22/12/2025 /Llave Multifuncional 360™/ ABO | C7: USD | D7: 199.99 | E7: 46023 | F7: 46053
A8: 2 IMPORTEX MODA 2025 CTA PUBLICITARIA | B8: 06/01/2026- FilmPro® - ABO | C8: USD | D8: 169.83 | E8: 46023 | F8: 46053
A9: 2 IMPORTEX MODA 2025 CTA PUBLICITARIA | B9: 04/01/2026- FLORA FRESH PRO™- ABO | C9: USD | D9: 66.58 | E9: 46023 | F9: 46053
A10: IMPORTEX MODA 2025 CTA PUBLICITARIA | B10: 27/01/2026 - FURBLADE™ -ABO | C10: USD | D10: 13.57 | E10: 46023 | F10: 46053
A11: 3 IMPORTEX 2025 CTA PUBLICITARIA | B11: JBL / 20-01 / WHATSAPP | C11: USD | D11: 10.77 | E11: 46023 | F11: 46053
A12: 2 IMPORTEX MODA 2025 CTA PUBLICITARIA | B12: 06/01/2026- FLORA FRESH PRO™- ESCALADO -CBO | C12: USD | D12: 6.28 | E12: 46023 | F12: 46053
A14: FEBRERO
A16: IMPORTEX MODA 2025 CTA PUBLICITARIA | B16: 10/01 DUPLICADO 09/11/2025-Cuchillo Tazaki™- ABO - 16/11/2025 | C16: USD | D16: 849.36 | E16: 46054 | F16: 46081
A17: IMPORTEX MODA 2025 CTA PUBLICITARIA | B17: 17/01/2026 - FilmPro® - CBO | C17: USD | D17: 849.16 | E17: 46054 | F17: 46081
A18: 2 IMPORTEX MODA 2025 CTA PUBLICITARIA | B18: 17/02/2026 - Cuchillo Tazaki™ - CBO | C18: USD | D18: 338.32 | E18: 46054 | F18: 46081
A19: IMPORTEX MODA 2025 CTA PUBLICITARIA | B19: 12/11/2025- FilmPro®- ABO - / DUPLICADO CBO $50 - 25/02 | C19: USD | D19: 189.58 | E19: 46054 | F19: 46081
A20: 2 IMPORTEX MODA 2025 CTA PUBLICITARIA | B20: 01/02/2026 - Llave Multifuncional 360™- CBO | C20: USD | D20: 158.89 | E20: 46054 | F20: 46081
A21: IMPORTEX MODA 2025 CTA PUBLICITARIA | B21: 27/02/2026 - FreeBeat Adapter - ABO | C21: USD | D21: 24.57 | E21: 46054 | F21: 46081

Sheet SupermetricsQueries
A1: Supermetrics Queries
A3: All the queries created by Supermetrics are stored here, each in its own row.
H4: 17707215
A5: On this sheet you can:
A6: 1. Modify the parameters of a query. Any changes will be visible when you run a refresh.
A8: 2. Remove a query by deleting its row | H8: America/Bogota
A10: 3. Add new queries: type a range address and query parameters, leave the query ID empty. The query will be added when you run a refresh. (Of course, it's much easier to use the sidebar to add new queries.)
A13: Queries are stored with the authentication of the original user that created the query. If you want to transfer a query to the currently active Google Sheets user, delete its query ID from column A and run a refresh. For complete instructions on transferring queries, see https://support.supermetrics.com/support/solutions/articles/19000050074-how-can-i-transfer-queries-from-one-user-to-another-
A16: Don't delete or rename this sheet. If you delete or rename it, your existing queries can no longer be refreshed. Hiding the sheet is OK. Also, don't delete any rows above row 21.
A19: Query ID | D19: Sheet name | E19: Range address | G19: Created | H19: Updated | I19: Last status | J19: Last refresh ID | K19: Results contain sampled data | L19: Execution time (sec) | M19: Object type | N19: Linked chart ID | O19: Data source | Q19: Date range type | R19: Start date | S19: End date | T19: Compare to | U19: Comparison value type | W19: Accounts/views | X19: Metrics | Y19: Dimensions | Z19: Pivot dimensions | AA19: Filters | AB19: Segment ID | AC19: Sort | AD19: Max rows | AE19: Max pivot categories | AF19: Special settings | AG19: Other parameters | AJ19: Result type | AK19: Language/country | AL19: Translate to | AN19: SQL | AO19: Database name | AP19: Range address (static) | AQ19: Report type | AT19: Highlight with colour | AU19: Refresh with user account | AV19: Returned data | AW19: Refresh button number
A20: paramsID | C20: ssID | D20: sheetName | E20: rangeAddress | G20: created | H20: updated | I20: lastStatus | J20: lastqueryID | K20: sampled | L20: runtime_sec | M20: objType | N20: linkedChartID | O20: dataSource | Q20: dateRangeType | R20: startDateString | S20: endDateString | T20: comp | U20: cvt | W20: profiles | X20: metrics | Y20: dimensions | Z20: sd | AA20: filterArr | AB20: segment | AC20: sort | AD20: maxResults | AE20: maxCategories | AF20: specialSettings | AG20: otherParams | AJ20: sds_result_type | AK20: sds_lang | AL20: sds_tolang | AN20: sql | AO20: db_name | AP20: rangeAddressStatic | AQ20: rt | AR20: scopeMZ | AS20: sortMZ | AT20: condform | AU20: authUser | AV20: metaDataToUser | AW20: refreshButtonNumber
A21: xhBK48cDeYRNkKTgEkN3NSS83QBpNp | D21: =IFERROR(__xludf.DUMMYFUNCTION("ARRAY_CONSTRAIN(split(CELL(""ADDRESS"",zsupermetrics_xhBK48cDeYRNkKTgEkN3NSS83QBpNp),""!""),1,1)"),"TK") -> TK | E21: =CELL("ADDRESS",zsupermetrics_xhBK48cDeYRNkKTgEkN3NSS83QBpNp)&":"&address(row(zsupermetrics_xhBK48cDeYRNkKTgEkN3NSS83QBpNp)+rows(zsupermetrics_xhBK48cDeYRNkKTgEkN3NSS83QBpNp)-1,column(zsupermetrics_xhBK48cDeYRNkKTgEkN3NSS83QBpNp)+COLUMNS(zsupermetrics_xhBK48cDeYRNkKTgEkN3NSS83QBpNp)-1) -> TK!$H$6:$S$65 | G21: 2026-01-27 18:00:03.0 | H21: 46063.253 | I21: Refreshed successfully by trigger iP2uL1zbWwAyCOtK9hl6RHQIBb4wLt | J21: 1770721480942 | K21: FALSE | L21: 12 | M21: TABLE | O21: FA | Q21: custom | R21: 46023 | S21: 46049 | W21: ["act_771085292027587`2 IMPORTEX MODA 2025 CTA PUBLICITARIA","act_2201688663608851`3 IMPORTEX 2025 CTA PUBLICITARIA ","act_3035690929930583`IMPORTEX MODA 2025 CTA PUBLICITARIA "] | X21: ["cost"] | Y21: ["Date","campaign_group_name"] | Z21: ["campaign_group_name"] | AA21: [] | AB21: [] | AD21: 10000 | AE21: 50 | AF21: ["BLANKS_TO_ZERO","SHOW_ALL_TIME_VALUES","ACTION_REPORT_TIME_conversion"] | AG21: {} | AP21: TK'!H6:S65 | AU21: 903837718759499

Sheet NOMBRE DE PRODUCTOS
A1: NOMBRE DE PRODUCTO | B1: NOMBRE COMERCIAL
A2: LLAVE TRINQUETE | B2: Llave Multifuncional 360™
A3: PARABRISA | B3: FilmPro®
A4: GEL | B4: FLORA FRESH PRO™
A5: CUCHILLO | B5: Cuchillo Tazaki™
A6: GUANTE | B6: FURBLADE™
A7: FILTRO | B7: DrainGuard Pro™
A8: Receptor Bluetooth | B8: FreeBeat Adapter
A9: JBL | B9: JBL GO 4

Sheet DEVOLUCION
A1: ID | B1: FECHA | C1: TIPO | D1: MONTO | E1: MONTO PREVIO | F1: ORDEN ID | G1: NUMERO DE GUIA | H1: DESCRIPCIÓN | I1: CUENTA | J1: CONCEPTO DE RETIRO
A2: 10115973 | B2: 28-02-2026 00:48 | C2: ENTRADA | D2: 8.66 | E2: 2518.43 | F2: 4622643 | G2: D001362823 | H2: ENTRADA POR GANANCIA EN LA ORDEN COMO DROPSHIPPER: 4622643* GUIA: *D001362823*
A3: 10115604 | B3: 28-02-2026 00:48 | C3: ENTRADA | D3: 7.61 | E3: 2510.82 | F3: 4622389 | G3: D001362824 | H3: ENTRADA POR GANANCIA EN LA ORDEN COMO DROPSHIPPER: 4622389* GUIA: *D001362824*
A4: 10108235 | B4: 28-02-2026 00:46 | C4: ENTRADA | D4: 14.34 | E4: 2496.48 | F4: 4617199 | G4: D001359468 | H4: ENTRADA POR GANANCIA EN LA ORDEN COMO DROPSHIPPER: 4617199* GUIA: *D001359468*
A5: 10090635 | B5: 28-02-2026 00:42 | C5: ENTRADA | D5: 16.79 | E5: 2479.69 | F5: 4598492 | G5: D001359560 | H5: ENTRADA POR GANANCIA EN LA ORDEN COMO DROPSHIPPER: 4598492* GUIA: *D001359560*
A6: 10084440 | B6: 28-02-2026 00:41 | C6: ENTRADA | D6: 16.79 | E6: 2462.9 | F6: 4586637 | G6: D001353667 | H6: ENTRADA POR GANANCIA EN LA ORDEN COMO DROPSHIPPER: 4586637* GUIA: *D001353667*
A7: 10084419 | B7: 28-02-2026 00:41 | C7: ENTRADA | D7: 15.95 | E7: 2446.95 | F7: 4586613 | G7: D001353670 | H7: ENTRADA POR GANANCIA EN LA ORDEN COMO DROPSHIPPER: 4586613* GUIA: *D001353670*
A8: 10084412 | B8: 28-02-2026 00:41 | C8: ENTRADA | D8: 17.83 | E8: 2429.12 | F8: 4586582 | G8: D001353673 | H8: ENTRADA POR GANANCIA EN LA ORDEN COMO DROPSHIPPER: 4586582* GUIA: *D001353673*
A9: 10084391 | B9: 28-02-2026 00:41 | C9: ENTRADA | D9: 16.79 | E9: 2412.33 | F9: 4586535 | G9: D001353675 | H9: ENTRADA POR GANANCIA EN LA ORDEN COMO DROPSHIPPER: 4586535* GUIA: *D001353675*
A10: 10081290 | B10: 28-02-2026 00:40 | C10: ENTRADA | D10: 8.66 | E10: 2403.67 | F10: 4578106 | G10: D001354500 | H10: ENTRADA POR GANANCIA EN LA ORDEN COMO DROPSHIPPER: 4578106* GUIA: *D001354500*
A11: 10080805 | B11: 28-02-2026 00:40 | C11: ENTRADA | D11: 8.66 | E11: 2395.01 | F11: 4576899 | G11: D001354509 | H11: ENTRADA POR GANANCIA EN LA ORDEN COMO DROPSHIPPER: 4576899* GUIA: *D001354509*
A12: 10074574 | B12: 28-02-2026 00:39 | C12: ENTRADA | D12: 16.64 | E12: 2378.37 | F12: 4550422 | G12: D001355665 | H12: ENTRADA POR GANANCIA EN LA ORDEN COMO DROPSHIPPER: 4550422* GUIA: *D001355665*
A13: 10074538 | B13: 28-02-2026 00:39 | C13: ENTRADA | D13: 13.45 | E13: 2364.92 | F13: 4550182 | G13: D001344693 | H13: ENTRADA POR GANANCIA EN LA ORDEN COMO DROPSHIPPER: 4550182* GUIA: *D001344693*
A14: 10074268 | B14: 28-02-2026 00:39 | C14: ENTRADA | D14: 6.8 | E14: 2358.12 | F14: 4548322 | G14: 186796386 | H14: ENTRADA POR GANANCIA EN LA ORDEN COMO DROPSHIPPER: 4548322* GUIA: *186796386*
A15: 10072050 | B15: 28-02-2026 00:38 | C15: ENTRADA | D15: 9.7 | E15: 2348.42 | F15: 4523482 | G15: D001339560 | H15: ENTRADA POR GANANCIA EN LA ORDEN COMO DROPSHIPPER: 4523482* GUIA: *D001339560*
A16: 10071828 | B16: 28-02-2026 00:38 | C16: ENTRADA | D16: 15.85 | E16: 2332.57 | F16: 4521408 | G16: D001340310 | H16: ENTRADA POR GANANCIA EN LA ORDEN COMO DROPSHIPPER: 4521408* GUIA: *D001340310*
A17: 10067051 | B17: 27-02-2026 14:04 | C17: SALIDA | D17: 7.19 | E17: 2339.76 | F17: 4507232 | G17: LC52905133 | H17: SALIDA POR COBRO DE FLETE INICIAL: 4507232
A18: 10065674 | B18: 27-02-2026 03:07 | C18: SALIDA | D18: 5.65 | E18: 2345.41 | F18: 4523515 | G18: D001339559 | H18: SALIDA DE COBRO DE DEVOLUCIÓN POR ENTREGA NO EFECTIVA: 4523515
A19: 10065673 | B19: 27-02-2026 03:07 | C19: SALIDA | D19: 5.13 | E19: 2350.54 | F19: 4523546 | G19: D001339556 | H19: SALIDA DE COBRO DE DEVOLUCIÓN POR ENTREGA NO EFECTIVA: 4523546
A20: 10064705 | B20: 27-02-2026 03:01 | C20: SALIDA | D20: 5.07 | E20: 2355.61 | F20: 4484391 | G20: D001324356 | H20: SALIDA DE COBRO DE DEVOLUCIÓN POR ENTREGA NO EFECTIVA: 4484391
A21: 10064704 | B21: 27-02-2026 03:01 | C21: SALIDA | D21: 5.13 | E21: 2360.74 | F21: 4484661 | G21: D001324354 | H21: SALIDA DE COBRO DE DEVOLUCIÓN POR ENTREGA NO EFECTIVA: 4484661
A22: 10064703 | B22: 27-02-2026 03:01 | C22: SALIDA | D22: 5.13 | E22: 2365.87 | F22: 4485107 | G22: D001324351 | H22: SALIDA DE COBRO DE DEVOLUCIÓN POR ENTREGA NO EFECTIVA: 4485107
A23: 10064701 | B23: 27-02-2026 03:01 | C23: SALIDA | D23: 5.12 | E23: 2370.99 | F23: 4486265 | G23: D001324346 | H23: SALIDA DE COBRO DE DEVOLUCIÓN POR ENTREGA NO EFECTIVA: 4486265
A24: 10064700 | B24: 27-02-2026 03:01 | C24: SALIDA | D24: 5.07 | E24: 2376.06 | F24: 4486979 | G24: D001324338 | H24: SALIDA DE COBRO DE DEVOLUCIÓN POR ENTREGA NO EFECTIVA: 4486979
A25: 10064699 | B25: 27-02-2026 03:01 | C25: SALIDA | D25: 5.07 | E25: 2381.13 | F25: 4487345 | G25: D001324337 | H25: SALIDA DE COBRO DE DEVOLUCIÓN POR ENTREGA NO EFECTIVA: 4487345
A26: 10064698 | B26: 27-02-2026 03:01 | C26: SALIDA | D26: 5.07 | E26: 2386.2 | F26: 4489045 | G26: D001324326 | H26: SALIDA DE COBRO DE DEVOLUCIÓN POR ENTREGA NO EFECTIVA: 4489045
... A30: 10064569 | B30: 27-02-2026 03:01 | C30: SALIDA | D30: 5.11 | E30: 2405.99 | F30: 4490717 | G30: D001322955 | H30: SALIDA DE COBRO DE DEVOLUCIÓN POR ENTREGA NO EFECTIVA: 4490717
A31: 10063636 | B31: 27-02-2026 01:01 | C31: SALIDA | D31: 7.67 | E31: 2413.66 | F31: 4350109 | G31: 186994371 | H31: SALIDA POR COBRO DE FLETE INICIAL: 4350109
A32: 10059773 | B32: 27-02-2026 00:53 | C32: ENTRADA | D32: 18.4 | E32: 2395.26 | F32: 4617647 | G32: D001359464 | H32: ENTRADA POR GANANCIA EN LA ORDEN COMO DROPSHIPPER: 4617647* GUIA: *D001359464*
A33: 10059512 | B33: 27-02-2026 00:53 | C33: ENTRADA | D33: 15.95 | E33: 2379.31 | F33: 4617195 | G33: D001359469 | H33: ENTRADA POR GANANCIA EN LA ORDEN COMO DROPSHIPPER: 4617195* GUIA: *D001359469*
A34: 10032750 | B34: 27-02-2026 00:46 | C34: ENTRADA | D34: 6.8 | E34: 2372.51 | F34: 4596067 | G34: 186573343 | H34: ENTRADA POR GANANCIA EN LA ORDEN COMO DROPSHIPPER: 4596067* GUIA: *186573343*
A35: 10024293 | B35: 27-02-2026 00:44 | C35: ENTRADA | D35: 17.83 | E35: 2354.68 | F35: 4586569 | G35: D001353674 | H35: ENTRADA POR GANANCIA EN LA ORDEN COMO DROPSHIPPER: 4586569* GUIA: *D001353674*
A36: 10024112 | B36: 27-02-2026 00:44 | C36: ENTRADA | D36: 7.2 | E36: 2347.48 | F36: 4586325 | G36: LC52934417 | H36: ENTRADA POR GANANCIA EN LA ORDEN COMO DROPSHIPPER: 4586325* GUIA: *LC52934417*
A37: 10018888 | B37: 27-02-2026 00:43 | C37: ENTRADA | D37: 12.65 | E37: 2334.83 | F37: 4579105 | G37: D001355719 | H37: ENTRADA POR GANANCIA EN LA ORDEN COMO DROPSHIPPER: 4579105* GUIA: *D001355719*
A38: 10009913 | B38: 27-02-2026 00:41 | C38: ENTRADA | D38: 13.45 | E38: 2321.38 | F38: 4559544 | G38: D001344685 | H38: ENTRADA POR GANANCIA EN LA ORDEN COMO DROPSHIPPER: 4559544* GUIA: *D001344685*
A39: 10007401 | B39: 27-02-2026 00:40 | C39: ENTRADA | D39: 14.16 | E39: 2307.22 | F39: 4549546 | G39: 186793629 | H39: ENTRADA POR GANANCIA EN LA ORDEN COMO DROPSHIPPER: 4549546* GUIA: *186793629*
A40: 10003829 | B40: 27-02-2026 00:40 | C40: ENTRADA | D40: 13.67 | E40: 2293.55 | F40: 4535081 | G40: D001340292 | H40: ENTRADA POR GANANCIA EN LA ORDEN COMO DROPSHIPPER: 4535081* GUIA: *D001340292*
A41: 10001604 | B41: 27-02-2026 00:39 | C41: ENTRADA | D41: 8.66 | E41: 2284.89 | F41: 4523556 | G41: D001339554 | H41: ENTRADA POR GANANCIA EN LA ORDEN COMO DROPSHIPPER: 4523556* GUIA: *D001339554*
A42: 10000114 | B42: 27-02-2026 00:39 | C42: ENTRADA | D42: 10.96 | E42: 2273.93 | F42: 4507478 | G42: D001340340 | H42: ENTRADA POR GANANCIA EN LA ORDEN COMO DROPSHIPPER: 4507478* GUIA: *D001340340*
A43: 9999795 | B43: 27-02-2026 00:38 | C43: ENTRADA | D43: 13.45 | E43: 2260.48 | F43: 4502915 | G43: D001343633 | H43: ENTRADA POR GANANCIA EN LA ORDEN COMO DROPSHIPPER: 4502915* GUIA: *D001343633*
A44: 9999337 | B44: 27-02-2026 00:38 | C44: ENTRADA | D44: 10.8 | E44: 2249.68 | F44: 4493703 | G44: 187049570 | H44: ENTRADA POR GANANCIA EN LA ORDEN COMO DROPSHIPPER: 4493703* GUIA: *187049570*
A45: 9999023 | B45: 27-02-2026 00:38 | C45: ENTRADA | D45: 11.31 | E45: 2238.37 | F45: 4484575 | G45: WYB167549543 | H45: ENTRADA POR GANANCIA EN LA ORDEN COMO DROPSHIPPER: 4484575* GUIA: *WYB167549543*
A46: 9996976 | B46: 26-02-2026 16:18 | C46: SALIDA | D46: 7.13 | E46: 2245.5 | F46: 4523430 | G46: LC52899222 | H46: SALIDA POR COBRO DE FLETE INICIAL: 4523430
A47: 9957629 | B47: 26-02-2026 00:45 | C47: ENTRADA | D47: 7.98 | E47: 2237.52 | F47: 4578984 | G47: 186573716 | H47: ENTRADA POR GANANCIA EN LA ORDEN COMO DROPSHIPPER: 4578984* GUIA: *186573716*
A48: 9956833 | B48: 26-02-2026 00:44 | C48: ENTRADA | D48: 9.72 | E48: 2227.8 | F48: 4578164 | G48: D001354498 | H48: ENTRADA POR GANANCIA EN LA ORDEN COMO DROPSHIPPER: 4578164* GUIA: *D001354498*
A49: 9956342 | B49: 26-02-2026 00:44 | C49: ENTRADA | D49: 10.27 | E49: 2217.53 | F49: 4577757 | G49: D001354503 | H49: ENTRADA POR GANANCIA EN LA ORDEN COMO DROPSHIPPER: 4577757* GUIA: *D001354503*
A50: 9953295 | B50: 26-02-2026 00:43 | C50: ENTRADA | D50: 11.33 | E50: 2206.2 | F50: 4575074 | G50: D001354512 | H50: ENTRADA POR GANANCIA EN LA ORDEN COMO DROPSHIPPER: 4575074* GUIA: *D001354512*
A51: 9952476 | B51: 26-02-2026 00:43 | C51: ENTRADA | D51: 11.84 | E51: 2194.36 | F51: 4574109 | G51: D001352902 | H51: ENTRADA POR GANANCIA EN LA ORDEN COMO DROPSHIPPER: 4574109* GUIA: *D001352902*
A52: 9939451 | B52: 26-02-2026 00:40 | C52: ENTRADA | D52: 16.64 | E52: 2177.72 | F52: 4547590 | G52: D001340245 | H52: ENTRADA POR GANANCIA EN LA ORDEN COMO DROPSHIPPER: 4547590* GUIA: *D001340245*
A53: 9936504 | B53: 26-02-2026 00:39 | C53: ENTRADA | D53: 8.66 | E53: 2169.06 | F53: 4534331 | G53: D001339531 | H53: ENTRADA POR GANANCIA EN LA ORDEN COMO DROPSHIPPER: 4534331* GUIA: *D001339531*
A54: 9934460 | B54: 26-02-2026 00:39 | C54: ENTRADA | D54: 10.76 | E54: 2158.3 | F54: 4523623 | G54: D001339547 | H54: ENTRADA POR GANANCIA EN LA ORDEN COMO DROPSHIPPER: 4523623* GUIA: *D001339547*
A55: 9934444 | B55: 26-02-2026 00:39 | C55: ENTRADA | D55: 11.33 | E55: 2146.97 | F55: 4523608 | G55: D001339551 | H55: ENTRADA POR GANANCIA EN LA ORDEN COMO DROPSHIPPER: 4523608* GUIA: *D001339551*
A56: 9934404 | B56: 26-02-2026 00:39 | C56: ENTRADA | D56: 10.27 | E56: 2136.7 | F56: 4523421 | G56: D001339561 | H56: ENTRADA POR GANANCIA EN LA ORDEN COMO DROPSHIPPER: 4523421* GUIA: *D001339561*
A57: 9934397 | B57: 26-02-2026 00:39 | C57: ENTRADA | D57: 12.37 | E57: 2124.33 | F57: 4523416 | G57: D001343264 | H57: ENTRADA POR GANANCIA EN LA ORDEN COMO DROPSHIPPER: 4523416* GUIA: *D001343264*
A58: 9934382 | B58: 26-02-2026 00:39 | C58: ENTRADA | D58: 8.66 | E58: 2115.67 | F58: 4523392 | G58: D001346109 | H58: ENTRADA POR GANANCIA EN LA ORDEN COMO DROPSHIPPER: 4523392* GUIA: *D001346109*
A59: 9933518 | B59: 26-02-2026 00:38 | C59: ENTRADA | D59: 16.64 | E59: 2099.03 | F59: 4513873 | G59: D001340328 | H59: ENTRADA POR GANANCIA EN LA ORDEN COMO DROPSHIPPER: 4513873* GUIA: *D001340328*
... A65: 9930815 | B65: 25-02-2026 13:37 | C65: SALIDA | D65: 7.01 | E65: 2034.02 | F65: 4442399 | G65: LC52844505 | H65: SALIDA POR COBRO DE FLETE INICIAL: 4442399
A66: 9930355 | B66: 25-02-2026 09:51 | C66: SALIDA | D66: 300 | E66: 2334.02 | H66: SALIDA POR PETICION DE RETIRO DE SALDO EN CARTERA | J66: RETORO
A67: 9929377 | B67: 25-02-2026 03:03 | C67: SALIDA | D67: 3.46 | E67: 2337.48 | F67: 4484051 | G67: D001324359 | H67: SALIDA DE COBRO DE DEVOLUCIÓN POR ENTREGA NO EFECTIVA: 4484051
A68: 9929376 | B68: 25-02-2026 03:03 | C68: SALIDA | D68: 3.51 | E68: 2340.99 | F68: 4486712 | G68: D001324340 | H68: SALIDA DE COBRO DE DEVOLUCIÓN POR ENTREGA NO EFECTIVA: 4486712
A69: 9929375 | B69: 25-02-2026 03:03 | C69: SALIDA | D69: 3.46 | E69: 2344.45 | F69: 4487546 | G69: D001324334 | H69: SALIDA DE COBRO DE DEVOLUCIÓN POR ENTREGA NO EFECTIVA: 4487546
A70: 9925406 | B70: 25-02-2026 00:46 | C70: ENTRADA | D70: 16.68 | E70: 2327.77 | F70: 4596610 | G70: 186573850 | H70: ENTRADA POR GANANCIA EN LA ORDEN COMO DROPSHIPPER: 4596610* GUIA: *186573850*
A71: 9910319 | B71: 25-02-2026 00:41 | C71: ENTRADA | D71: 16.64 | E71: 2311.13 | F71: 4562311 | G71: D001344681 | H71: ENTRADA POR GANANCIA EN LA ORDEN COMO DROPSHIPPER: 4562311* GUIA: *D001344681*
A72: 9909119 | B72: 25-02-2026 00:41 | C72: ENTRADA | D72: 11.84 | E72: 2299.29 | F72: 4558764 | G72: D001344687 | H72: ENTRADA POR GANANCIA EN LA ORDEN COMO DROPSHIPPER: 4558764* GUIA: *D001344687*
A73: 9907794 | B73: 25-02-2026 00:41 | C73: ENTRADA | D73: 11.84 | E73: 2287.45 | F73: 4554820 | G73: D001344690 | H73: ENTRADA POR GANANCIA EN LA ORDEN COMO DROPSHIPPER: 4554820* GUIA: *D001344690*
A74: 9901998 | B74: 25-02-2026 00:39 | C74: ENTRADA | D74: 11.84 | E74: 2275.61 | F74: 4523600 | G74: D001340302 | H74: ENTRADA POR GANANCIA EN LA ORDEN COMO DROPSHIPPER: 4523600* GUIA: *D001340302*
A75: 9900012 | B75: 25-02-2026 00:38 | C75: ENTRADA | D75: 14.24 | E75: 2261.37 | F75: 4507155 | G75: D001340343 | H75: ENTRADA POR GANANCIA EN LA ORDEN COMO DROPSHIPPER: 4507155* GUIA: *D001340343*
A76: 9899722 | B76: 25-02-2026 00:38 | C76: ENTRADA | D76: 10.39 | E76: 2250.98 | F76: 4503806 | G76: D001340355 | H76: ENTRADA POR GANANCIA EN LA ORDEN COMO DROPSHIPPER: 4503806* GUIA: *D001340355*
A77: 9899671 | B77: 25-02-2026 00:38 | C77: ENTRADA | D77: 16.64 | E77: 2234.34 | F77: 4503257 | G77: D001340357 | H77: ENTRADA POR GANANCIA EN LA ORDEN COMO DROPSHIPPER: 4503257* GUIA: *D001340357*
A78: 9898153 | B78: 25-02-2026 00:38 | C78: ENTRADA | D78: 12.57 | E78: 2221.77 | F78: 4442348 | G78: D001320043 | H78: ENTRADA POR GANANCIA EN LA ORDEN COMO DROPSHIPPER: 4442348* GUIA: *D001320043*
A79: 9896564 | B79: 24-02-2026 13:25 | C79: SALIDA | D79: 6.9 | E79: 2228.67 | F79: 4442323 | G79: LC52831895 | H79: SALIDA POR COBRO DE FLETE INICIAL: 4442323
A80: 9894780 | B80: 24-02-2026 03:04 | C80: SALIDA | D80: 4.54 | E80: 2233.21 | F80: 4486574 | G80: D001324342 | H80: SALIDA DE COBRO DE DEVOLUCIÓN POR ENTREGA NO EFECTIVA: 4486574
A81: 9894048 | B81: 24-02-2026 03:01 | C81: SALIDA | D81: 5.13 | E81: 2238.34 | F81: 4442366 | G81: D001318309 | H81: SALIDA DE COBRO DE DEVOLUCIÓN POR ENTREGA NO EFECTIVA: 4442366
A82: 9893923 | B82: 24-02-2026 03:01 | C82: SALIDA | D82: 5.12 | E82: 2243.46 | F82: 4432079 | G82: D001316925 | H82: SALIDA DE COBRO DE DEVOLUCIÓN POR ENTREGA NO EFECTIVA: 4432079
A83: 9882065 | B83: 24-02-2026 00:42 | C83: ENTRADA | D83: 16.64 | E83: 2226.82 | F83: 4555047 | G83: D001344689 | H83: ENTRADA POR GANANCIA EN LA ORDEN COMO DROPSHIPPER: 4555047* GUIA: *D001344689*
A84: 9878164 | B84: 24-02-2026 00:41 | C84: ENTRADA | D84: 8.24 | E84: 2218.58 | F84: 4546452 | G84: 186796403 | H84: ENTRADA POR GANANCIA EN LA ORDEN COMO DROPSHIPPER: 4546452* GUIA: *186796403*
A85: 9872155 | B85: 24-02-2026 00:40 | C85: ENTRADA | D85: 10.27 | E85: 2208.31 | F85: 4523574 | G85: D001339553 | H85: ENTRADA POR GANANCIA EN LA ORDEN COMO DROPSHIPPER: 4523574* GUIA: *D001339553*
A86: 9872103 | B86: 24-02-2026 00:40 | C86: ENTRADA | D86: 10.27 | E86: 2198.04 | F86: 4523351 | G86: D001339563 | H86: ENTRADA POR GANANCIA EN LA ORDEN COMO DROPSHIPPER: 4523351* GUIA: *D001339563*
A87: 9872094 | B87: 24-02-2026 00:40 | C87: ENTRADA | D87: 14.24 | E87: 2183.8 | F87: 4523329 | G87: D001343627 | H87: ENTRADA POR GANANCIA EN LA ORDEN COMO DROPSHIPPER: 4523329* GUIA: *D001343627*
A88: 9871713 | B88: 24-02-2026 00:40 | C88: ENTRADA | D88: 11.84 | E88: 2171.96 | F88: 4521284 | G88: D001340311 | H88: ENTRADA POR GANANCIA EN LA ORDEN COMO DROPSHIPPER: 4521284* GUIA: *D001340311*
A89: 9871697 | B89: 24-02-2026 00:40 | C89: ENTRADA | D89: 15.32 | E89: 2156.64 | F89: 4521137 | G89: LC52905130 | H89: ENTRADA POR GANANCIA EN LA ORDEN COMO DROPSHIPPER: 4521137* GUIA: *LC52905130*
A90: 9871378 | B90: 24-02-2026 00:39 | C90: ENTRADA | D90: 14.24 | E90: 2142.4 | F90: 4519287 | G90: D001340317 | H90: ENTRADA POR GANANCIA EN LA ORDEN COMO DROPSHIPPER: 4519287* GUIA: *D001340317*
A91: 9871244 | B91: 24-02-2026 00:39 | C91: ENTRADA | D91: 11.84 | E91: 2130.56 | F91: 4518664 | G91: D001343629 | H91: ENTRADA POR GANANCIA EN LA ORDEN COMO DROPSHIPPER: 4518664* GUIA: *D001343629*
A92: 9870416 | B92: 24-02-2026 00:39 | C92: ENTRADA | D92: 14.98 | E92: 2115.58 | F92: 4514796 | G92: 186793784 | H92: ENTRADA POR GANANCIA EN LA ORDEN COMO DROPSHIPPER: 4514796* GUIA: *186793784*
A93: 9869700 | B93: 24-02-2026 00:39 | C93: ENTRADA | D93: 16.64 | E93: 2098.94 | F93: 4510725 | G93: D001343632 | H93: ENTRADA POR GANANCIA EN LA ORDEN COMO DROPSHIPPER: 4510725* GUIA: *D001343632*
A94: 9868907 | B94: 24-02-2026 00:39 | C94: ENTRADA | D94: 14.24 | E94: 2084.7 | F94: 4506785 | G94: D001340347 | H94: ENTRADA POR GANANCIA EN LA ORDEN COMO DROPSHIPPER: 4506785* GUIA: *D001340347*
A95: 9868669 | B95: 24-02-2026 00:39 | C95: ENTRADA | D95: 10.96 | E95: 2073.74 | F95: 4505102 | G95: D001346406 | H95: ENTRADA POR GANANCIA EN LA ORDEN COMO DROPSHIPPER: 4505102* GUIA: *D001346406*
A96: 9867974 | B96: 24-02-2026 00:39 | C96: ENTRADA | D96: 11.84 | E96: 2061.9 | F96: 4500637 | G96: D001340362 | H96: ENTRADA POR GANANCIA EN LA ORDEN COMO DROPSHIPPER: 4500637* GUIA: *D001340362*
A97: 9867785 | B97: 24-02-2026 00:39 | C97: ENTRADA | D97: 12.86 | E97: 2049.04 | F97: 4498638 | G97: LC52905137 | H97: ENTRADA POR GANANCIA EN LA ORDEN COMO DROPSHIPPER: 4498638* GUIA: *LC52905137*
A98: 9867759 | B98: 24-02-2026 00:39 | C98: ENTRADA | D98: 16.64 | E98: 2032.4 | F98: 4498245 | G98: D001340370 | H98: ENTRADA POR GANANCIA EN LA ORDEN COMO DROPSHIPPER: 4498245* GUIA: *D001340370*
A99: 9867734 | B99: 24-02-2026 00:39 | C99: ENTRADA | D99: 11.86 | E99: 2020.54 | F99: 4498089 | G99: LC52905138 | H99: ENTRADA POR GANANCIA EN LA ORDEN COMO DROPSHIPPER: 4498089* GUIA: *LC52905138*
A100: 9867711 | B100: 24-02-2026 00:39 | C100: ENTRADA | D100: 13.17 | E100: 2007.37 | F100: 4497942 | G100: D001343634 | H100: ENTRADA POR GANANCIA EN LA ORDEN COMO DROPSHIPPER: 4497942* GUIA: *D001343634*
A101: 9867687 | B101: 24-02-2026 00:39 | C101: ENTRADA | D101: 10.96 | E101: 1996.41 | F101: 4497761 | G101: D001340371 | H101: ENTRADA POR GANANCIA EN LA ORDEN COMO DROPSHIPPER: 4497761* GUIA: *D001340371*
A102: 9863759 | B102: 23-02-2026 11:40 | C102: SALIDA | D102: 6.9 | E102: 2003.31 | F102: 4432022 | G102: LC52831534 | H102: SALIDA POR COBRO DE FLETE INICIAL: 4432022
A103: 9862183 | B103: 23-02-2026 03:03 | C103: SALIDA | D103: 4.52 | E103: 2007.83 | F103: 4442315 | G103: D001316570 | H103: SALIDA DE COBRO DE DEVOLUCIÓN POR ENTREGA NO EFECTIVA: 4442315
A104: 9862052 | B104: 23-02-2026 03:02 | C104: SALIDA | D104: 5.11 | E104: 2012.94 | F104: 4442305 | G104: D001315543 | H104: SALIDA DE COBRO DE DEVOLUCIÓN POR ENTREGA NO EFECTIVA: 4442305
... A120: 9859319 | B120: 22-02-2026 03:04 | C120: SALIDA | D120: 3.45 | E120: 2030.14 | F120: 4432091 | G120: D001313023 | H120: SALIDA DE COBRO DE DEVOLUCIÓN POR ENTREGA NO EFECTIVA: 4432091
A121: 9858337 | B121: 22-02-2026 01:04 | C121: SALIDA | D121: 6.24 | E121: 2036.38 | F121: 4352545 | G121: 187001271 | H121: SALIDA POR COBRO DE FLETE INICIAL: 4352545
A122: 9854961 | B122: 22-02-2026 00:42 | C122: ENTRADA | D122: 11.84 | E122: 2024.54 | F122: 4556140 | G122: D001344688 | H122: ENTRADA POR GANANCIA EN LA ORDEN COMO DROPSHIPPER: 4556140* GUIA: *D001344688*
A123: 9852956 | B123: 22-02-2026 00:41 | C123: ENTRADA | D123: 14.24 | E123: 2010.3 | F123: 4551240 | G123: D001344692 | H123: ENTRADA POR GANANCIA EN LA ORDEN COMO DROPSHIPPER: 4551240* GUIA: *D001344692*
...

Sheet PLANTILLAS
A1: PRODUCTO | B1: CONFIRMACION 1 | C1: CONFIRMACION 2 | D1: CONFIRMACION 3 | E1: NOVEDAD 1 | F1: NOVEDAD 2 | G1: NOVEDAD 3
A2: FilmPro® | B2: Hola, {NOMBRE} Queremos confirmar los detalles de tu pedido y la direccion en donde sera entregado: Producto: {CANTIDAD} {PRODUCTO} Valor: ${VALOR} Direccion: {DIRECCION}, {CIUDAD} - {PROVINCIA} Confirmanos si todo esta correcto respondiendo CONFIRMADO
A3: Cuchillo Tazaki™

Sheet PENDIENTES
A1: FECHA | B1: NOMBRE | C1: PRODUCTO | D1: ESTADO | E1: ID | F1: CONTACTO | G1: LINK WHASAPP | H1: OBSERBACIONES
A2: {=IFERROR( INDEX(FEBRERO!B:B, MATCH(E2, FEBRERO!T:T, 0)), IFERROR( INDEX(MARZO!B:B, MATCH(E2, MARZO!T:T, 0)), "" ) )} -> 46054 | B2: =IFERROR(__xludf.DUMMYFUNCTION("FILTER( { FEBRERO!C:C,FEBRERO!D:D,FEBRERO!O:O,FEBRERO!T:T; MARZO!C:C,MARZO!D:D,MARZO!O:O,MARZO!T:T }, { FEBRERO!O:O; MARZO!O:O }=""PENDIENTE"" )"),"Cristian Suarez") -> Cristian Suarez | C2: =IFERROR(__xludf.DUMMYFUNCTION("""COMPUTED_VALUE"""),"FilmPro®") -> FilmPro® | D2: =IFERROR(__xludf.DUMMYFUNCTION("""COMPUTED_VALUE"""),"PENDIENTE") -> PENDIENTE | E2: =IFERROR(__xludf.DUMMYFUNCTION("""COMPUTED_VALUE"""),4370206.0) -> 4370206 | F2: {=IF(E2:E1000="", "", "593"&VLOOKUP(E2:E1000,REPORTE_DROPI!B:F,5,FALSE) )} -> 593992766120
A3: {=IFERROR( INDEX(FEBRERO!B:B, MATCH(E3, FEBRERO!T:T, 0)), IFERROR( INDEX(MARZO!B:B, MATCH(E3, MARZO!T:T, 0)), "" ) )} -> 46054 | B3: =IFERROR(__xludf.DUMMYFUNCTION("""COMPUTED_VALUE"""),"Cecilia Tapia") -> Cecilia Tapia | C3: =IFERROR(__xludf.DUMMYFUNCTION("""COMPUTED_VALUE"""),"Cuchillo Tazaki™") -> Cuchillo Tazaki™ | D3: =IFERROR(__xludf.DUMMYFUNCTION("""COMPUTED_VALUE"""),"PENDIENTE") -> PENDIENTE | E3: =IFERROR(__xludf.DUMMYFUNCTION("""COMPUTED_VALUE"""),4348861.0) -> 4348861 | F3: 593969076621
A4: {=IFERROR( INDEX(FEBRERO!B:B, MATCH(E4, FEBRERO!T:T, 0)), IFERROR( INDEX(MARZO!B:B, MATCH(E4, MARZO!T:T, 0)), "" ) )} -> 46054 | B4: =IFERROR(__xludf.DUMMYFUNCTION("""COMPUTED_VALUE"""),"Jose Cabrera Maya Cabrera Maya") -> Jose Cabrera Maya Cabrera Maya | C4: =IFERROR(__xludf.DUMMYFUNCTION("""COMPUTED_VALUE"""),"FilmPro®") -> FilmPro® | D4: =IFERROR(__xludf.DUMMYFUNCTION("""COMPUTED_VALUE"""),"PENDIENTE") -> PENDIENTE | E4: =IFERROR(__xludf.DUMMYFUNCTION("""COMPUTED_VALUE"""),4370534.0) -> 4370534 | F4: 593983713271
A5: {=IFERROR( INDEX(FEBRERO!B:B, MATCH(E5, FEBRERO!T:T, 0)), IFERROR( INDEX(MARZO!B:B, MATCH(E5, MARZO!T:T, 0)), "" ) )} -> 46054 | B5: =IFERROR(__xludf.DUMMYFUNCTION("""COMPUTED_VALUE"""),"Fabian Molina Molina") -> Fabian Molina Molina | C5: =IFERROR(__xludf.DUMMYFUNCTION("""COMPUTED_VALUE"""),"FilmPro®") -> FilmPro® | D5: =IFERROR(__xludf.DUMMYFUNCTION("""COMPUTED_VALUE"""),"PENDIENTE") -> PENDIENTE | E5: =IFERROR(__xludf.DUMMYFUNCTION("""COMPUTED_VALUE"""),4349540.0) -> 4349540 | F5: 593983076106
A6: {=IFERROR( INDEX(FEBRERO!B:B, MATCH(E6, FEBRERO!T:T, 0)), IFERROR( INDEX(MARZO!B:B, MATCH(E6, MARZO!T:T, 0)), "" ) )} -> 46054 | B6: =IFERROR(__xludf.DUMMYFUNCTION("""COMPUTED_VALUE"""),"Wilson Guerrero") -> Wilson Guerrero | C6: =IFERROR(__xludf.DUMMYFUNCTION("""COMPUTED_VALUE"""),"FilmPro®") -> FilmPro® | D6: =IFERROR(__xludf.DUMMYFUNCTION("""COMPUTED_VALUE"""),"PENDIENTE") -> PENDIENTE | E6: =IFERROR(__xludf.DUMMYFUNCTION("""COMPUTED_VALUE"""),4349603.0) -> 4349603 | F6: 593967599083
A7: {=IFERROR( INDEX(FEBRERO!B:B, MATCH(E7, FEBRERO!T:T, 0)), IFERROR( INDEX(MARZO!B:B, MATCH(E7, MARZO!T:T, 0)), "" ) )} -> 46054 | B7: =IFERROR(__xludf.DUMMYFUNCTION("""COMPUTED_VALUE"""),"Byron Peña") -> Byron Peña | C7: =IFERROR(__xludf.DUMMYFUNCTION("""COMPUTED_VALUE"""),"FilmPro®") -> FilmPro® | D7: =IFERROR(__xludf.DUMMYFUNCTION("""COMPUTED_VALUE"""),"PENDIENTE") -> PENDIENTE | E7: =IFERROR(__xludf.DUMMYFUNCTION("""COMPUTED_VALUE"""),4351675.0) -> 4351675 | F7: 593969345643
A8: {=IFERROR( INDEX(FEBRERO!B:B, MATCH(E8, FEBRERO!T:T, 0)), IFERROR( INDEX(MARZO!B:B, MATCH(E8, MARZO!T:T, 0)), "" ) )} -> 46054 | B8: =IFERROR(__xludf.DUMMYFUNCTION("""COMPUTED_VALUE"""),"Darwin Lopez") -> Darwin Lopez | C8: =IFERROR(__xludf.DUMMYFUNCTION("""COMPUTED_VALUE"""),"FilmPro®") -> FilmPro® | D8: =IFERROR(__xludf.DUMMYFUNCTION("""COMPUTED_VALUE"""),"PENDIENTE") -> PENDIENTE | E8: =IFERROR(__xludf.DUMMYFUNCTION("""COMPUTED_VALUE"""),4352407.0) -> 4352407 | F8: 593991271195
A9: {=IFERROR( INDEX(FEBRERO!B:B, MATCH(E9, FEBRERO!T:T, 0)), IFERROR( INDEX(MARZO!B:B, MATCH(E9, MARZO!T:T, 0)), "" ) )} -> 46054 | B9: =IFERROR(__xludf.DUMMYFUNCTION("""COMPUTED_VALUE""")," Jaime Eduardo Guanopatin silva ") -> Jaime Eduardo Guanopatin silva | C9: =IFERROR(__xludf.DUMMYFUNCTION("""COMPUTED_VALUE"""),"Cuchillo Tazaki™") -> Cuchillo Tazaki™ | D9: =IFERROR(__xludf.DUMMYFUNCTION("""COMPUTED_VALUE"""),"PENDIENTE") -> PENDIENTE | E9: =IFERROR(__xludf.DUMMYFUNCTION("""COMPUTED_VALUE"""),4353478.0) -> 4353478 | F9: 593999909284
A10: {=IFERROR( INDEX(FEBRERO!B:B, MATCH(E10, FEBRERO!T:T, 0)), IFERROR( INDEX(MARZO!B:B, MATCH(E10, MARZO!T:T, 0)), "" ) )} -> 46054 | B10: =IFERROR(__xludf.DUMMYFUNCTION("""COMPUTED_VALUE"""),"LUIS BECERRA") -> LUIS BECERRA | C10: =IFERROR(__xludf.DUMMYFUNCTION("""COMPUTED_VALUE"""),"Llave Multifuncional 360™") -> Llave Multifuncional 360™ | D10: =IFERROR(__xludf.DUMMYFUNCTION("""COMPUTED_VALUE"""),"PENDIENTE") -> PENDIENTE | E10: =IFERROR(__xludf.DUMMYFUNCTION("""COMPUTED_VALUE"""),4353582.0) -> 4353582 | F10: 593994961093
A11: {=IFERROR( INDEX(FEBRERO!B:B, MATCH(E11, FEBRERO!T:T, 0)), IFERROR( INDEX(MARZO!B:B, MATCH(E11, MARZO!T:T, 0)), "" ) )} -> 46054 | B11: =IFERROR(__xludf.DUMMYFUNCTION("""COMPUTED_VALUE"""),"Anibal Tipantasi") -> Anibal Tipantasi | C11: =IFERROR(__xludf.DUMMYFUNCTION("""COMPUTED_VALUE"""),"Llave Multifuncional 360™") -> Llave Multifuncional 360™ | D11: =IFERROR(__xludf.DUMMYFUNCTION("""COMPUTED_VALUE"""),"PENDIENTE") -> PENDIENTE | E11: =IFERROR(__xludf.DUMMYFUNCTION("""COMPUTED_VALUE"""),4356452.0) -> 4356452 | F11: 593998148020
A12: {=IFERROR( INDEX(FEBRERO!B:B, MATCH(E12, FEBRERO!T:T, 0)), IFERROR( INDEX(MARZO!B:B, MATCH(E12, MARZO!T:T, 0)), "" ) )} -> 46054 | B12: =IFERROR(__xludf.DUMMYFUNCTION("""COMPUTED_VALUE"""),"Pablo De La Cruz") -> Pablo De La Cruz | C12: =IFERROR(__xludf.DUMMYFUNCTION("""COMPUTED_VALUE"""),"FilmPro®") -> FilmPro® | D12: =IFERROR(__xludf.DUMMYFUNCTION("""COMPUTED_VALUE"""),"PENDIENTE") -> PENDIENTE | E12: =IFERROR(__xludf.DUMMYFUNCTION("""COMPUTED_VALUE"""),4356619.0) -> 4356619 | F12: 593995649035
A13: {=IFERROR( INDEX(FEBRERO!B:B, MATCH(E13, FEBRERO!T:T, 0)), IFERROR( INDEX(MARZO!B:B, MATCH(E13, MARZO!T:T, 0)), "" ) )} -> 46054 | B13: =IFERROR(__xludf.DUMMYFUNCTION("""COMPUTED_VALUE"""),"Luís Zambrano ") -> Luís Zambrano | C13: =IFERROR(__xludf.DUMMYFUNCTION("""COMPUTED_VALUE"""),"Cuchillo Tazaki™") -> Cuchillo Tazaki™ | D13: =IFERROR(__xludf.DUMMYFUNCTION("""COMPUTED_VALUE"""),"PENDIENTE") -> PENDIENTE | E13: =IFERROR(__xludf.DUMMYFUNCTION("""COMPUTED_VALUE"""),4357933.0) -> 4357933 | F13: 593985391767
A14: {=IFERROR( INDEX(FEBRERO!B:B, MATCH(E14, FEBRERO!T:T, 0)), IFERROR( INDEX(MARZO!B:B, MATCH(E14, MARZO!T:T, 0)), "" ) )} -> 46054 | B14: =IFERROR(__xludf.DUMMYFUNCTION("""COMPUTED_VALUE"""),"Agripino Milciades Fernandez Nupia ") -> Agripino Milciades Fernandez Nupia | C14: =IFERROR(__xludf.DUMMYFUNCTION("""COMPUTED_VALUE"""),"Cuchillo Tazaki™") -> Cuchillo Tazaki™ | D14: =IFERROR(__xludf.DUMMYFUNCTION("""COMPUTED_VALUE"""),"PENDIENTE") -> PENDIENTE | E14: =IFERROR(__xludf.DUMMYFUNCTION("""COMPUTED_VALUE"""),4372035.0) -> 4372035 | F14: 593987912213
A15: {=IFERROR( INDEX(FEBRERO!B:B, MATCH(E15, FEBRERO!T:T, 0)), IFERROR( INDEX(MARZO!B:B, MATCH(E15, MARZO!T:T, 0)), "" ) )} -> 46054 | B15: =IFERROR(__xludf.DUMMYFUNCTION("""COMPUTED_VALUE"""),"Jimmy Villavicencio") -> Jimmy Villavicencio | C15: =IFERROR(__xludf.DUMMYFUNCTION("""COMPUTED_VALUE"""),"FilmPro®") -> FilmPro® | D15: =IFERROR(__xludf.DUMMYFUNCTION("""COMPUTED_VALUE"""),"PENDIENTE") -> PENDIENTE | E15: =IFERROR(__xludf.DUMMYFUNCTION("""COMPUTED_VALUE"""),4359740.0) -> 4359740 | F15: 593987691121
A16: {=IFERROR( INDEX(FEBRERO!B:B, MATCH(E16, FEBRERO!T:T, 0)), IFERROR( INDEX(MARZO!B:B, MATCH(E16, MARZO!T:T, 0)), "" ) )} -> 46054 | B16: =IFERROR(__xludf.DUMMYFUNCTION("""COMPUTED_VALUE"""),"María Jose Yánez") -> María Jose Yánez | C16: =IFERROR(__xludf.DUMMYFUNCTION("""COMPUTED_VALUE"""),"FilmPro®") -> FilmPro® | D16: =IFERROR(__xludf.DUMMYFUNCTION("""COMPUTED_VALUE"""),"PENDIENTE") -> PENDIENTE | E16: =IFERROR(__xludf.DUMMYFUNCTION("""COMPUTED_VALUE"""),4372193.0) -> 4372193 | F16: 593969958828
A17: {=IFERROR( INDEX(FEBRERO!B:B, MATCH(E17, FEBRERO!T:T, 0)), IFERROR( INDEX(MARZO!B:B, MATCH(E17, MARZO!T:T, 0)), "" ) )} -> 46054 | B17: =IFERROR(__xludf.DUMMYFUNCTION("""COMPUTED_VALUE"""),"Nexar Antonio Mero López") -> Nexar Antonio Mero López | C17: =IFERROR(__xludf.DUMMYFUNCTION("""COMPUTED_VALUE"""),"Llave Multifuncional 360™") -> Llave Multifuncional 360™ | D17: =IFERROR(__xludf.DUMMYFUNCTION("""COMPUTED_VALUE"""),"PENDIENTE") -> PENDIENTE | E17: =IFERROR(__xludf.DUMMYFUNCTION("""COMPUTED_VALUE"""),4360337.0) -> 4360337 | F17: 593997233084
A18: {=IFERROR( INDEX(FEBRERO!B:B, MATCH(E18, FEBRERO!T:T, 0)), IFERROR( INDEX(MARZO!B:B, MATCH(E18, MARZO!T:T, 0)), "" ) )} -> 46055 | B18: =IFERROR(__xludf.DUMMYFUNCTION("""COMPUTED_VALUE"""),"Marino Alexis RESTREPO ARCILA") -> Marino Alexis RESTREPO ARCILA | C18: =IFERROR(__xludf.DUMMYFUNCTION("""COMPUTED_VALUE"""),"FilmPro®") -> FilmPro® | D18: =IFERROR(__xludf.DUMMYFUNCTION("""COMPUTED_VALUE"""),"PENDIENTE") -> PENDIENTE | E18: =IFERROR(__xludf.DUMMYFUNCTION("""COMPUTED_VALUE"""),4360690.0) -> 4360690 | F18: 593984645032
A19: {=IFERROR( INDEX(FEBRERO!B:B, MATCH(E19, FEBRERO!T:T, 0)), IFERROR( INDEX(MARZO!B:B, MATCH(E19, MARZO!T:T, 0)), "" ) )} -> 46055 | B19: =IFERROR(__xludf.DUMMYFUNCTION("""COMPUTED_VALUE"""),"Jorge Portilla") -> Jorge Portilla | C19: =IFERROR(__xludf.DUMMYFUNCTION("""COMPUTED_VALUE"""),"Llave Multifuncional 360™") -> Llave Multifuncional 360™ | D19: =IFERROR(__xludf.DUMMYFUNCTION("""COMPUTED_VALUE"""),"PENDIENTE") -> PENDIENTE | E19: =IFERROR(__xludf.DUMMYFUNCTION("""COMPUTED_VALUE"""),4361137.0) -> 4361137 | F19: 593999646105
A20: {=IFERROR( INDEX(FEBRERO!B:B, MATCH(E20, FEBRERO!T:T, 0)), IFERROR( INDEX(MARZO!B:B, MATCH(E20, MARZO!T:T, 0)), "" ) )} -> 46055 | B20: =IFERROR(__xludf.DUMMYFUNCTION("""COMPUTED_VALUE"""),"Jose Carrillo Cedeño") -> Jose Carrillo Cedeño | C20: =IFERROR(__xludf.DUMMYFUNCTION("""COMPUTED_VALUE"""),"Cuchillo Tazaki™") -> Cuchillo Tazaki™ | D20: =IFERROR(__xludf.DUMMYFUNCTION("""COMPUTED_VALUE"""),"PENDIENTE") -> PENDIENTE | E20: =IFERROR(__xludf.DUMMYFUNCTION("""COMPUTED_VALUE"""),4362434.0) -> 4362434 | F20: 593992777624
A21: {=IFERROR( INDEX(FEBRERO!B:B, MATCH(E21, FEBRERO!T:T, 0)), IFERROR( INDEX(MARZO!B:B, MATCH(E21, MARZO!T:T, 0)), "" ) )} -> 46055 | B21: =IFERROR(__xludf.DUMMYFUNCTION("""COMPUTED_VALUE"""),"Alfonso Chacha") -> Alfonso Chacha | C21: =IFERROR(__xludf.DUMMYFUNCTION("""COMPUTED_VALUE"""),"Llave Multifuncional 360™") -> Llave Multifuncional 360™ | D21: =IFERROR(__xludf.DUMMYFUNCTION("""COMPUTED_VALUE"""),"PENDIENTE") -> PENDIENTE | E21: =IFERROR(__xludf.DUMMYFUNCTION("""COMPUTED_VALUE"""),4363609.0) -> 4363609 | F21: 593995414068
A22: {=IFERROR( INDEX(FEBRERO!B:B, MATCH(E22, FEBRERO!T:T, 0)), IFERROR( INDEX(MARZO!B:B, MATCH(E22, MARZO!T:T, 0)), "" ) )} -> 46055 | B22: =IFERROR(__xludf.DUMMYFUNCTION("""COMPUTED_VALUE"""),"Luis Rubén") -> Luis Rubén | C22: =IFERROR(__xludf.DUMMYFUNCTION("""COMPUTED_VALUE"""),"FilmPro®") -> FilmPro® | D22: =IFERROR(__xludf.DUMMYFUNCTION("""COMPUTED_VALUE"""),"PENDIENTE") -> PENDIENTE | E22: =IFERROR(__xludf.DUMMYFUNCTION("""COMPUTED_VALUE"""),4363816.0) -> 4363816 | F22: 593993223824
A23: {=IFERROR( INDEX(FEBRERO!B:B, MATCH(E23, FEBRERO!T:T, 0)), IFERROR( INDEX(MARZO!B:B, MATCH(E23, MARZO!T:T, 0)), "" ) )} -> 46055 | B23: =IFERROR(__xludf.DUMMYFUNCTION("""COMPUTED_VALUE"""),"Jose luis ibujes") -> Jose luis ibujes | C23: =IFERROR(__xludf.DUMMYFUNCTION("""COMPUTED_VALUE"""),"Llave Multifuncional 360™") -> Llave Multifuncional 360™ | D23: =IFERROR(__xludf.DUMMYFUNCTION("""COMPUTED_VALUE"""),"PENDIENTE") -> PENDIENTE | E23: =IFERROR(__xludf.DUMMYFUNCTION("""COMPUTED_VALUE"""),4364765.0) -> 4364765 | F23: 593994181004
A24: {=IFERROR( INDEX(FEBRERO!B:B, MATCH(E24, FEBRERO!T:T, 0)), IFERROR( INDEX(MARZO!B:B, MATCH(E24, MARZO!T:T, 0)), "" ) )} -> 46058 | B24: =IFERROR(__xludf.DUMMYFUNCTION("""COMPUTED_VALUE"""),"Franklin Mauricio Sanmartín Fajardo") -> Franklin Mauricio Sanmartín Fajardo | C24: =IFERROR(__xludf.DUMMYFUNCTION("""COMPUTED_VALUE"""),"Cuchillo Tazaki™") -> Cuchillo Tazaki™ | D24: =IFERROR(__xludf.DUMMYFUNCTION("""COMPUTED_VALUE"""),"PENDIENTE") -> PENDIENTE | E24: =IFERROR(__xludf.DUMMYFUNCTION("""COMPUTED_VALUE"""),4404690.0) -> 4404690 | F24: 593988810361
A25: {=IFERROR( INDEX(FEBRERO!B:B, MATCH(E25, FEBRERO!T:T, 0)), IFERROR( INDEX(MARZO!B:B, MATCH(E25, MARZO!T:T, 0)), "" ) )} -> 46058 | B25: =IFERROR(__xludf.DUMMYFUNCTION("""COMPUTED_VALUE"""),"Verónica Moncayo") -> Verónica Moncayo | C25: =IFERROR(__xludf.DUMMYFUNCTION("""COMPUTED_VALUE"""),"FilmPro®") -> FilmPro® | D25: =IFERROR(__xludf.DUMMYFUNCTION("""COMPUTED_VALUE"""),"PENDIENTE") -> PENDIENTE | E25: =IFERROR(__xludf.DUMMYFUNCTION("""COMPUTED_VALUE"""),4405388.0) -> 4405388 | F25: 593983960630
A26: {=IFERROR( INDEX(FEBRERO!B:B, MATCH(E26, FEBRERO!T:T, 0)), IFERROR( INDEX(MARZO!B:B, MATCH(E26, MARZO!T:T, 0)), "" ) )} -> 46058 | B26: =IFERROR(__xludf.DUMMYFUNCTION("""COMPUTED_VALUE"""),"Gabriela Estefanía Vince mora 0981673958") -> Gabriela Estefanía Vince mora 0981673958 | C26: =IFERROR(__xludf.DUMMYFUNCTION("""COMPUTED_VALUE"""),"FilmPro®") -> FilmPro® | D26: =IFERROR(__xludf.DUMMYFUNCTION("""COMPUTED_VALUE"""),"PENDIENTE") -> PENDIENTE | E26: =IFERROR(__xludf.DUMMYFUNCTION("""COMPUTED_VALUE"""),4406660.0) -> 4406660 | F26: 593981673958
A27: {=IFERROR( INDEX(FEBRERO!B:B, MATCH(E27, FEBRERO!T:T, 0)), IFERROR( INDEX(MARZO!B:B, MATCH(E27, MARZO!T:T, 0)), "" ) )} -> 46058 | B27: =IFERROR(__xludf.DUMMYFUNCTION("""COMPUTED_VALUE"""),"Alexis Mero") -> Alexis Mero | C27: =IFERROR(__xludf.DUMMYFUNCTION("""COMPUTED_VALUE"""),"FilmPro®") -> FilmPro® | D27: =IFERROR(__xludf.DUMMYFUNCTION("""COMPUTED_VALUE"""),"PENDIENTE") -> PENDIENTE | E27: =IFERROR(__xludf.DUMMYFUNCTION("""COMPUTED_VALUE"""),4418776.0) -> 4418776 | F27: 593998844838
A28: {=IFERROR( INDEX(FEBRERO!B:B, MATCH(E28, FEBRERO!T:T, 0)), IFERROR( INDEX(MARZO!B:B, MATCH(E28, MARZO!T:T, 0)), "" ) )} -> 46058 | B28: =IFERROR(__xludf.DUMMYFUNCTION("""COMPUTED_VALUE"""),"Tito Andrade") -> Tito Andrade | C28: =IFERROR(__xludf.DUMMYFUNCTION("""COMPUTED_VALUE"""),"Cuchillo Tazaki™") -> Cuchillo Tazaki™ | D28: =IFERROR(__xludf.DUMMYFUNCTION("""COMPUTED_VALUE"""),"PENDIENTE") -> PENDIENTE | E28: =IFERROR(__xludf.DUMMYFUNCTION("""COMPUTED_VALUE"""),4418766.0) -> 4418766 | F28: 593993044886
A29: {=IFERROR( INDEX(FEBRERO!B:B, MATCH(E29, FEBRERO!T:T, 0)), IFERROR( INDEX(MARZO!B:B, MATCH(E29, MARZO!T:T, 0)), "" ) )} -> 46058 | B29: =IFERROR(__xludf.DUMMYFUNCTION("""COMPUTED_VALUE"""),"Erik Obando") -> Erik Obando | C29: =IFERROR(__xludf.DUMMYFUNCTION("""COMPUTED_VALUE"""),"FilmPro®") -> FilmPro® | D29: =IFERROR(__xludf.DUMMYFUNCTION("""COMPUTED_VALUE"""),"PENDIENTE") -> PENDIENTE | E29: =IFERROR(__xludf.DUMMYFUNCTION("""COMPUTED_VALUE"""),4420847.0) -> 4420847 | F29: 593998930648
A30: {=IFERROR( INDEX(FEBRERO!B:B, MATCH(E30, FEBRERO!T:T, 0)), IFERROR( INDEX(MARZO!B:B, MATCH(E30, MARZO!T:T, 0)), "" ) )} -> 46058 | B30: =IFERROR(__xludf.DUMMYFUNCTION("""COMPUTED_VALUE"""),"Hugo Espinoza") -> Hugo Espinoza | C30: =IFERROR(__xludf.DUMMYFUNCTION("""COMPUTED_VALUE"""),"FilmPro®") -> FilmPro® | D30: =IFERROR(__xludf.DUMMYFUNCTION("""COMPUTED_VALUE"""),"PENDIENTE") -> PENDIENTE | E30: =IFERROR(__xludf.DUMMYFUNCTION("""COMPUTED_VALUE"""),4418744.0) -> 4418744 | F30: 593996124553
A31: {=IFERROR( INDEX(FEBRERO!B:B, MATCH(E31, FEBRERO!T:T, 0)), IFERROR( INDEX(MARZO!B:B, MATCH(E31, MARZO!T:T, 0)), "" ) )} -> 46058 | B31: =IFERROR(__xludf.DUMMYFUNCTION("""COMPUTED_VALUE"""),"Dalton Maldonado") -> Dalton Maldonado | C31: =IFERROR(__xludf.DUMMYFUNCTION("""COMPUTED_VALUE"""),"Cuchillo Tazaki™") -> Cuchillo Tazaki™ | D31: =IFERROR(__xludf.DUMMYFUNCTION("""COMPUTED_VALUE"""),"PENDIENTE") -> PENDIENTE | E31: =IFERROR(__xludf.DUMMYFUNCTION("""COMPUTED_VALUE"""),4418732.0) -> 4418732 | F31: 593988017052
A32: {=IFERROR( INDEX(FEBRERO!B:B, MATCH(E32, FEBRERO!T:T, 0)), IFERROR( INDEX(MARZO!B:B, MATCH(E32, MARZO!T:T, 0)), "" ) )} -> 46058 | B32: =IFERROR(__xludf.DUMMYFUNCTION("""COMPUTED_VALUE"""),"Angel Rea") -> Angel Rea | C32: =IFERROR(__xludf.DUMMYFUNCTION("""COMPUTED_VALUE"""),"Cuchillo Tazaki™") -> Cuchillo Tazaki™ | D32: =IFERROR(__xludf.DUMMYFUNCTION("""COMPUTED_VALUE"""),"PENDIENTE") -> PENDIENTE | E32: =IFERROR(__xludf.DUMMYFUNCTION("""COMPUTED_VALUE"""),4418730.0) -> 4418730 | F32: 593988335015
A33: {=IFERROR( INDEX(FEBRERO!B:B, MATCH(E33, FEBRERO!T:T, 0)), IFERROR( INDEX(MARZO!B:B, MATCH(E33, MARZO!T:T, 0)), "" ) )} -> 46058 | B33: =IFERROR(__xludf.DUMMYFUNCTION("""COMPUTED_VALUE"""),"Diego Fernando Barros criollo") -> Diego Fernando Barros criollo | C33: =IFERROR(__xludf.DUMMYFUNCTION("""COMPUTED_VALUE"""),"Cuchillo Tazaki™") -> Cuchillo Tazaki™ | D33: =IFERROR(__xludf.DUMMYFUNCTION("""COMPUTED_VALUE"""),"PENDIENTE") -> PENDIENTE | E33: =IFERROR(__xludf.DUMMYFUNCTION("""COMPUTED_VALUE"""),4418715.0) -> 4418715 | F33: 593986139409
A34: {=IFERROR( INDEX(FEBRERO!B:B, MATCH(E34, FEBRERO!T:T, 0)), IFERROR( INDEX(MARZO!B:B, MATCH(E34, MARZO!T:T, 0)), "" ) )} -> 46058 | B34: =IFERROR(__xludf.DUMMYFUNCTION("""COMPUTED_VALUE"""),"Norma Vera Zambrano") -> Norma Vera Zambrano | C34: =IFERROR(__xludf.DUMMYFUNCTION("""COMPUTED_VALUE"""),"Cuchillo Tazaki™") -> Cuchillo Tazaki™ | D34: =IFERROR(__xludf.DUMMYFUNCTION("""COMPUTED_VALUE"""),"PENDIENTE") -> PENDIENTE | E34: =IFERROR(__xludf.DUMMYFUNCTION("""COMPUTED_VALUE"""),4418710.0) -> 4418710 | F34: 593969236976
A35: {=IFERROR( INDEX(FEBRERO!B:B, MATCH(E35, FEBRERO!T:T, 0)), IFERROR( INDEX(MARZO!B:B, MATCH(E35, MARZO!T:T, 0)), "" ) )} -> 46058 | B35: =IFERROR(__xludf.DUMMYFUNCTION("""COMPUTED_VALUE"""),"Lauro Patiño") -> Lauro Patiño | C35: =IFERROR(__xludf.DUMMYFUNCTION("""COMPUTED_VALUE"""),"FilmPro®") -> FilmPro® | D35: =IFERROR(__xludf.DUMMYFUNCTION("""COMPUTED_VALUE"""),"PENDIENTE") -> PENDIENTE | E35: =IFERROR(__xludf.DUMMYFUNCTION("""COMPUTED_VALUE"""),4418709.0) -> 4418709 | F35: 593984977721
A36: {=IFERROR( INDEX(FEBRERO!B:B, MATCH(E36, FEBRERO!T:T, 0)), IFERROR( INDEX(MARZO!B:B, MATCH(E36, MARZO!T:T, 0)), "" ) )} -> 46058 | B36: =IFERROR(__xludf.DUMMYFUNCTION("""COMPUTED_VALUE"""),"Olga Chuya") -> Olga Chuya | C36: =IFERROR(__xludf.DUMMYFUNCTION("""COMPUTED_VALUE"""),"Cuchillo Tazaki™") -> Cuchillo Tazaki™ | D36: =IFERROR(__xludf.DUMMYFUNCTION("""COMPUTED_VALUE"""),"PENDIENTE") -> PENDIENTE | E36: =IFERROR(__xludf.DUMMYFUNCTION("""COMPUTED_VALUE"""),4418703.0) -> 4418703 | F36: 593999456597
A37: {=IFERROR( INDEX(FEBRERO!B:B, MATCH(E37, FEBRERO!T:T, 0)), IFERROR( INDEX(MARZO!B:B, MATCH(E37, MARZO!T:T, 0)), "" ) )} -> 46059 | B37: =IFERROR(__xludf.DUMMYFUNCTION("""COMPUTED_VALUE"""),"Baldemar Alfredo Guerra García Guerra García") -> Baldemar Alfredo Guerra García Guerra García | C37: =IFERROR(__xludf.DUMMYFUNCTION("""COMPUTED_VALUE"""),"FilmPro®") -> FilmPro® | D37: =IFERROR(__xludf.DUMMYFUNCTION("""COMPUTED_VALUE"""),"PENDIENTE") -> PENDIENTE | E37: =IFERROR(__xludf.DUMMYFUNCTION("""COMPUTED_VALUE"""),4418691.0) -> 4418691 | F37: 593989625886
A38: {=IFERROR( INDEX(FEBRERO!B:B, MATCH(E38, FEBRERO!T:T, 0)), IFERROR( INDEX(MARZO!B:B, MATCH(E38, MARZO!T:T, 0)), "" ) )} -> 46059 | B38: =IFERROR(__xludf.DUMMYFUNCTION("""COMPUTED_VALUE"""),"Enrique Ramón Dàger Rivera") -> Enrique Ramón Dàger Rivera | C38: =IFERROR(__xludf.DUMMYFUNCTION("""COMPUTED_VALUE"""),"Cuchillo Tazaki™") -> Cuchillo Tazaki™ | D38: =IFERROR(__xludf.DUMMYFUNCTION("""COMPUTED_VALUE"""),"PENDIENTE") -> PENDIENTE | E38: =IFERROR(__xludf.DUMMYFUNCTION("""COMPUTED_VALUE"""),4418688.0) -> 4418688 | F38: 593996343002
A39: {=IFERROR( INDEX(FEBRERO!B:B, MATCH(E39, FEBRERO!T:T, 0)), IFERROR( INDEX(MARZO!B:B, MATCH(E39, MARZO!T:T, 0)), "" ) )} -> 46059 | B39: =IFERROR(__xludf.DUMMYFUNCTION("""COMPUTED_VALUE"""),"Fernando Acosta") -> Fernando Acosta | C39: =IFERROR(__xludf.DUMMYFUNCTION("""COMPUTED_VALUE"""),"Cuchillo Tazaki™") -> Cuchillo Tazaki™ | D39: =IFERROR(__xludf.DUMMYFUNCTION("""COMPUTED_VALUE"""),"PENDIENTE") -> PENDIENTE | E39: =IFERROR(__xludf.DUMMYFUNCTION("""COMPUTED_VALUE"""),4418686.0) -> 4418686 | F39: 593993728114
A40: {=IFERROR( INDEX(FEBRERO!B:B, MATCH(E40, FEBRERO!T:T, 0)), IFERROR( INDEX(MARZO!B:B, MATCH(E40, MARZO!T:T, 0)), "" ) )} -> 46059 | B40: =IFERROR(__xludf.DUMMYFUNCTION("""COMPUTED_VALUE"""),"Jaime Gomez") -> Jaime Gomez | C40: =IFERROR(__xludf.DUMMYFUNCTION("""COMPUTED_VALUE"""),"Cuchillo Tazaki™") -> Cuchillo Tazaki™ | D40: =IFERROR(__xludf.DUMMYFUNCTION("""COMPUTED_VALUE"""),"PENDIENTE") -> PENDIENTE | E40: =IFERROR(__xludf.DUMMYFUNCTION("""COMPUTED_VALUE"""),4418684.0) -> 4418684 | F40: 593958650644
A41: {=IFERROR( INDEX(FEBRERO!B:B, MATCH(E41, FEBRERO!T:T, 0)), IFERROR( INDEX(MARZO!B:B, MATCH(E41, MARZO!T:T, 0)), "" ) )} -> 46059 | B41: =IFERROR(__xludf.DUMMYFUNCTION("""COMPUTED_VALUE"""),"Alexandra Contrera") -> Alexandra Contrera | C41: =IFERROR(__xludf.DUMMYFUNCTION("""COMPUTED_VALUE"""),"Cuchillo Tazaki™") -> Cuchillo Tazaki™ | D41: =IFERROR(__xludf.DUMMYFUNCTION("""COMPUTED_VALUE"""),"PENDIENTE") -> PENDIENTE | E41: =IFERROR(__xludf.DUMMYFUNCTION("""COMPUTED_VALUE"""),4418681.0) -> 4418681 | F41: 593999661577
A42: {=IFERROR( INDEX(FEBRERO!B:B, MATCH(E42, FEBRERO!T:T, 0)), IFERROR( INDEX(MARZO!B:B, MATCH(E42, MARZO!T:T, 0)), "" ) )} -> 46059 | B42: =IFERROR(__xludf.DUMMYFUNCTION("""COMPUTED_VALUE"""),"isabel cedeño") -> isabel cedeño | C42: =IFERROR(__xludf.DUMMYFUNCTION("""COMPUTED_VALUE"""),"Cuchillo Tazaki™") -> Cuchillo Tazaki™ | D42: =IFERROR(__xludf.DUMMYFUNCTION("""COMPUTED_VALUE"""),"PENDIENTE") -> PENDIENTE | E42: =IFERROR(__xludf.DUMMYFUNCTION("""COMPUTED_VALUE"""),4421351.0) -> 4421351 | F42: 593984053575
A43: {=IFERROR( INDEX(FEBRERO!B:B, MATCH(E43, FEBRERO!T:T, 0)), IFERROR( INDEX(MARZO!B:B, MATCH(E43, MARZO!T:T, 0)), "" ) )} -> 46059 | B43: =IFERROR(__xludf.DUMMYFUNCTION("""COMPUTED_VALUE"""),"Estela Rodriguez") -> Estela Rodriguez | C43: =IFERROR(__xludf.DUMMYFUNCTION("""COMPUTED_VALUE"""),"Cuchillo Tazaki™") -> Cuchillo Tazaki™ | D43: =IFERROR(__xludf.DUMMYFUNCTION("""COMPUTED_VALUE"""),"PENDIENTE") -> PENDIENTE | E43: =IFERROR(__xludf.DUMMYFUNCTION("""COMPUTED_VALUE"""),4418677.0) -> 4418677 | F43: 593997148250
A44: {=IFERROR( INDEX(FEBRERO!B:B, MATCH(E44, FEBRERO!T:T, 0)), IFERROR( INDEX(MARZO!B:B, MATCH(E44, MARZO!T:T, 0)), "" ) )} -> 46059 | B44: =IFERROR(__xludf.DUMMYFUNCTION("""COMPUTED_VALUE"""),"Maria Carrera") -> Maria Carrera | C44: =IFERROR(__xludf.DUMMYFUNCTION("""COMPUTED_VALUE"""),"Cuchillo Tazaki™") -> Cuchillo Tazaki™ | D44: =IFERROR(__xludf.DUMMYFUNCTION("""COMPUTED_VALUE"""),"PENDIENTE") -> PENDIENTE | E44: =IFERROR(__xludf.DUMMYFUNCTION("""COMPUTED_VALUE"""),4418670.0) -> 4418670 | F44: 593961044285
A45: {=IFERROR( INDEX(FEBRERO!B:B, MATCH(E45, FEBRERO!T:T, 0)), IFERROR( INDEX(MARZO!B:B, MATCH(E45, MARZO!T:T, 0)), "" ) )} -> 46059 | B45: =IFERROR(__xludf.DUMMYFUNCTION("""COMPUTED_VALUE"""),"Junior Marcillo") -> Junior Marcillo | C45: =IFERROR(__xludf.DUMMYFUNCTION("""COMPUTED_VALUE"""),"FilmPro®") -> FilmPro® | D45: =IFERROR(__xludf.DUMMYFUNCTION("""COMPUTED_VALUE"""),"PENDIENTE") -> PENDIENTE | E45: =IFERROR(__xludf.DUMMYFUNCTION("""COMPUTED_VALUE"""),4421453.0) -> 4421453 | F45: 593999633817
A46: {=IFERROR( INDEX(FEBRERO!B:B, MATCH(E46, FEBRERO!T:T, 0)), IFERROR( INDEX(MARZO!B:B, MATCH(E46, MARZO!T:T, 0)), "" ) )} -> 46059 | B46: =IFERROR(__xludf.DUMMYFUNCTION("""COMPUTED_VALUE"""),"Juan carlos Garcia") -> Juan carlos Garcia | C46: =IFERROR(__xludf.DUMMYFUNCTION("""COMPUTED_VALUE"""),"FilmPro®") -> FilmPro® | D46: =IFERROR(__xludf.DUMMYFUNCTION("""COMPUTED_VALUE"""),"PENDIENTE") -> PENDIENTE | E46: =IFERROR(__xludf.DUMMYFUNCTION("""COMPUTED_VALUE"""),4418663.0) -> 4418663 | F46: 593962872062
A47: {=IFERROR( INDEX(FEBRERO!B:B, MATCH(E47, FEBRERO!T:T, 0)), IFERROR( INDEX(MARZO!B:B, MATCH(E47, MARZO!T:T, 0)), "" ) )} -> 46058 | B47: =IFERROR(__xludf.DUMMYFUNCTION("""COMPUTED_VALUE""")," Norma Vera Zambrano ") -> Norma Vera Zambrano | C47: =IFERROR(__xludf.DUMMYFUNCTION("""COMPUTED_VALUE"""),"Cuchillo Tazaki™") -> Cuchillo Tazaki™ | D47: =IFERROR(__xludf.DUMMYFUNCTION("""COMPUTED_VALUE"""),"PENDIENTE") -> PENDIENTE | E47: =IFERROR(__xludf.DUMMYFUNCTION("""COMPUTED_VALUE"""),4418710.0) -> 4418710 | F47: 593969236976
A48: {=IFERROR( INDEX(FEBRERO!B:B, MATCH(E48, FEBRERO!T:T, 0)), IFERROR( INDEX(MARZO!B:B, MATCH(E48, MARZO!T:T, 0)), "" ) )} -> 46059 | B48: =IFERROR(__xludf.DUMMYFUNCTION("""COMPUTED_VALUE"""),"Richard Benavides") -> Richard Benavides | C48: =IFERROR(__xludf.DUMMYFUNCTION("""COMPUTED_VALUE"""),"FilmPro®") -> FilmPro® | D48: =IFERROR(__xludf.DUMMYFUNCTION("""COMPUTED_VALUE"""),"PENDIENTE") -> PENDIENTE | E48: =IFERROR(__xludf.DUMMYFUNCTION("""COMPUTED_VALUE"""),4418635.0) -> 4418635 | F48: 593978800030
A49: {=IFERROR( INDEX(FEBRERO!B:B, MATCH(E49, FEBRERO!T:T, 0)), IFERROR( INDEX(MARZO!B:B, MATCH(E49, MARZO!T:T, 0)), "" ) )} -> 46059 | B49: =IFERROR(__xludf.DUMMYFUNCTION("""COMPUTED_VALUE"""),"Patricio Dávalos") -> Patricio Dávalos | C49: =IFERROR(__xludf.DUMMYFUNCTION("""COMPUTED_VALUE"""),"Cuchillo Tazaki™") -> Cuchillo Tazaki™ | D49: =IFERROR(__xludf.DUMMYFUNCTION("""COMPUTED_VALUE"""),"PENDIENTE") -> PENDIENTE | E49: =IFERROR(__xludf.DUMMYFUNCTION("""COMPUTED_VALUE"""),4421195.0) -> 4421195 | F49: 593999708099
A50: {=IFERROR( INDEX(FEBRERO!B:B, MATCH(E50, FEBRERO!T:T, 0)), IFERROR( INDEX(MARZO!B:B, MATCH(E50, MARZO!T:T, 0)), "" ) )} -> 46059 | B50: =IFERROR(__xludf.DUMMYFUNCTION("""COMPUTED_VALUE"""),"José eduardo Salazar cueva") -> José eduardo Salazar cueva | C50: =IFERROR(__xludf.DUMMYFUNCTION("""COMPUTED_VALUE"""),"Cuchillo Tazaki™") -> Cuchillo Tazaki™ | D50: =IFERROR(__xludf.DUMMYFUNCTION("""COMPUTED_VALUE"""),"PENDIENTE") -> PENDIENTE | E50: =IFERROR(__xludf.DUMMYFUNCTION("""COMPUTED_VALUE"""),4432099.0) -> 4432099 | F50: 593967011199
A51: {=IFERROR( INDEX(FEBRERO!B:B, MATCH(E51, FEBRERO!T:T, 0)), IFERROR( INDEX(MARZO!B:B, MATCH(E51, MARZO!T:T, 0)), "" ) )} -> 46059 | B51: =IFERROR(__xludf.DUMMYFUNCTION("""COMPUTED_VALUE"""),"Cecilia Villarreal") -> Cecilia Villarreal | C51: =IFERROR(__xludf.DUMMYFUNCTION("""COMPUTED_VALUE"""),"FilmPro®") -> FilmPro® | D51: =IFERROR(__xludf.DUMMYFUNCTION("""COMPUTED_VALUE"""),"PENDIENTE") -> PENDIENTE | E51: =IFERROR(__xludf.DUMMYFUNCTION("""COMPUTED_VALUE"""),4432095.0) -> 4432095 | F51: 593998431659
A52: {=IFERROR( INDEX(FEBRERO!B:B, MATCH(E52, FEBRERO!T:T, 0)), IFERROR( INDEX(MARZO!B:B, MATCH(E52, MARZO!T:T, 0)), "" ) )} -> 46060 | B52: =IFERROR(__xludf.DUMMYFUNCTION("""COMPUTED_VALUE"""),"Isabel Cristina SUR") -> Isabel Cristina SUR | C52: =IFERROR(__xludf.DUMMYFUNCTION("""COMPUTED_VALUE"""),"FilmPro®") -> FilmPro® | D52: =IFERROR(__xludf.DUMMYFUNCTION("""COMPUTED_VALUE"""),"PENDIENTE") -> PENDIENTE | E52: =IFERROR(__xludf.DUMMYFUNCTION("""COMPUTED_VALUE"""),4432093.0) -> 4432093 | F52: 593963763707
A53: {=IFERROR( INDEX(FEBRERO!B:B, MATCH(E53, FEBRERO!T:T, 0)), IFERROR( INDEX(MARZO!B:B, MATCH(E53, MARZO!T:T, 0)), "" ) )} -> 46060 | B53: =IFERROR(__xludf.DUMMYFUNCTION("""COMPUTED_VALUE"""),"Miguel Ángel Morocho") -> Miguel Ángel Morocho | C53: =IFERROR(__xludf.DUMMYFUNCTION("""COMPUTED_VALUE"""),"Cuchillo Tazaki™") -> Cuchillo Tazaki™ | D53: =IFERROR(__xludf.DUMMYFUNCTION("""COMPUTED_VALUE"""),"PENDIENTE") -> PENDIENTE | E53: =IFERROR(__xludf.DUMMYFUNCTION("""COMPUTED_VALUE"""),4432088.0) -> 4432088 | F53: 593986019433
A54: {=IFERROR( INDEX(FEBRERO!B:B, MATCH(E54, FEBRERO!T:T, 0)), IFERROR( INDEX(MARZO!B:B, MATCH(E54, MARZO!T:T, 0)), "" ) )} -> 46060 | B54: =IFERROR(__xludf.DUMMYFUNCTION("""COMPUTED_VALUE"""),"Ramón Pacheco") -> Ramón Pacheco | C54: =IFERROR(__xludf.DUMMYFUNCTION("""COMPUTED_VALUE"""),"FilmPro®") -> FilmPro® | D54: =IFERROR(__xludf.DUMMYFUNCTION("""COMPUTED_VALUE"""),"PENDIENTE") -> PENDIENTE | E54: =IFERROR(__xludf.DUMMYFUNCTION("""COMPUTED_VALUE"""),4455062.0) -> 4455062 | F54: 593994568229
A55: {=IFERROR( INDEX(FEBRERO!B:B, MATCH(E55, FEBRERO!T:T, 0)), IFERROR( INDEX(MARZO!B:B, MATCH(E55, MARZO!T:T, 0)), "" ) )} -> 46060 | B55: =IFERROR(__xludf.DUMMYFUNCTION("""COMPUTED_VALUE"""),"Jean Garzón") -> Jean Garzón | C55: =IFERROR(__xludf.DUMMYFUNCTION("""COMPUTED_VALUE"""),"FilmPro®") -> FilmPro® | D55: =IFERROR(__xludf.DUMMYFUNCTION("""COMPUTED_VALUE"""),"PENDIENTE") -> PENDIENTE | E55: =IFERROR(__xludf.DUMMYFUNCTION("""COMPUTED_VALUE"""),4432073.0) -> 4432073 | F55: 593963478988
A56: {=IFERROR( INDEX(FEBRERO!B:B, MATCH(E56, FEBRERO!T:T, 0)), IFERROR( INDEX(MARZO!B:B, MATCH(E56, MARZO!T:T, 0)), "" ) )} -> 46060 | B56: =IFERROR(__xludf.DUMMYFUNCTION("""COMPUTED_VALUE"""),"Verónica Camacho") -> Verónica Camacho | C56: =IFERROR(__xludf.DUMMYFUNCTION("""COMPUTED_VALUE"""),"Cuchillo Tazaki™") -> Cuchillo Tazaki™ | D56: =IFERROR(__xludf.DUMMYFUNCTION("""COMPUTED_VALUE"""),"PENDIENTE") -> PENDIENTE | E56: =IFERROR(__xludf.DUMMYFUNCTION("""COMPUTED_VALUE"""),4457592.0) -> 4457592 | F56: 593987667518
A57: {=IFERROR( INDEX(FEBRERO!B:B, MATCH(E57, FEBRERO!T:T, 0)), IFERROR( INDEX(MARZO!B:B, MATCH(E57, MARZO!T:T, 0)), "" ) )} -> 46060 | B57: =IFERROR(__xludf.DUMMYFUNCTION("""COMPUTED_VALUE"""),"Ángel Guerra") -> Ángel Guerra | C57: =IFERROR(__xludf.DUMMYFUNCTION("""COMPUTED_VALUE"""),"Cuchillo Tazaki™") -> Cuchillo Tazaki™ | D57: =IFERROR(__xludf.DUMMYFUNCTION("""COMPUTED_VALUE"""),"PENDIENTE") -> PENDIENTE | E57: =IFERROR(__xludf.DUMMYFUNCTION("""COMPUTED_VALUE"""),4432027.0) -> 4432027 | F57: 593968553378
A58: {=IFERROR( INDEX(FEBRERO!B:B, MATCH(E58, FEBRERO!T:T, 0)), IFERROR( INDEX(MARZO!B:B, MATCH(E58, MARZO!T:T, 0)), "" ) )} -> 46060 | B58: =IFERROR(__xludf.DUMMYFUNCTION("""COMPUTED_VALUE"""),"Javier Escobar") -> Javier Escobar | C58: =IFERROR(__xludf.DUMMYFUNCTION("""COMPUTED_VALUE"""),"FilmPro®") -> FilmPro® | D58: =IFERROR(__xludf.DUMMYFUNCTION("""COMPUTED_VALUE"""),"PENDIENTE") -> PENDIENTE | E58: =IFERROR(__xludf.DUMMYFUNCTION("""COMPUTED_VALUE"""),4432015.0) -> 4432015 | F58: 593998055705
A59: {=IFERROR( INDEX(FEBRERO!B:B, MATCH(E59, FEBRERO!T:T, 0)), IFERROR( INDEX(MARZO!B:B, MATCH(E59, MARZO!T:T, 0)), "" ) )} -> 46060 | B59: =IFERROR(__xludf.DUMMYFUNCTION("""COMPUTED_VALUE"""),"Marco Bautista") -> Marco Bautista | C59: =IFERROR(__xludf.DUMMYFUNCTION("""COMPUTED_VALUE"""),"FilmPro®") -> FilmPro® | D59: =IFERROR(__xludf.DUMMYFUNCTION("""COMPUTED_VALUE"""),"PENDIENTE") -> PENDIENTE | E59: =IFERROR(__xludf.DUMMYFUNCTION("""COMPUTED_VALUE"""),4442403.0) -> 4442403 | F59: 593980143787
A60: {=IFERROR( INDEX(FEBRERO!B:B, MATCH(E60, FEBRERO!T:T, 0)), IFERROR( INDEX(MARZO!B:B, MATCH(E60, MARZO!T:T, 0)), "" ) )} -> 46060 | B60: =IFERROR(__xludf.DUMMYFUNCTION("""COMPUTED_VALUE"""),"Edison Garcia") -> Edison Garcia | C60: =IFERROR(__xludf.DUMMYFUNCTION("""COMPUTED_VALUE"""),"FilmPro®") -> FilmPro® | D60: =IFERROR(__xludf.DUMMYFUNCTION("""COMPUTED_VALUE"""),"PENDIENTE") -> PENDIENTE | E60: =IFERROR(__xludf.DUMMYFUNCTION("""COMPUTED_VALUE"""),4442400.0) -> 4442400 | F60: 593979879512
A61: {=IFERROR( INDEX(FEBRERO!B:B, MATCH(E61, FEBRERO!T:T, 0)), IFERROR( INDEX(MARZO!B:B, MATCH(E61, MARZO!T:T, 0)), "" ) )} -> 46060 | B61: =IFERROR(__xludf.DUMMYFUNCTION("""COMPUTED_VALUE"""),"Luis Montalvo") -> Luis Montalvo | C61: =IFERROR(__xludf.DUMMYFUNCTION("""COMPUTED_VALUE"""),"Cuchillo Tazaki™") -> Cuchillo Tazaki™ | D61: =IFERROR(__xludf.DUMMYFUNCTION("""COMPUTED_VALUE"""),"PENDIENTE") -> PENDIENTE | E61: =IFERROR(__xludf.DUMMYFUNCTION("""COMPUTED_VALUE"""),4442374.0) -> 4442374 | F61: 593991287604
A62: {=IFERROR( INDEX(FEBRERO!B:B, MATCH(E62, FEBRERO!T:T, 0)), IFERROR( INDEX(MARZO!B:B, MATCH(E62, MARZO!T:T, 0)), "" ) )} -> 46180 | B62: =IFERROR(__xludf.DUMMYFUNCTION("""COMPUTED_VALUE"""),"Elsa Castro") -> Elsa Castro | C62: =IFERROR(__xludf.DUMMYFUNCTION("""COMPUTED_VALUE"""),"Cuchillo Tazaki™") -> Cuchillo Tazaki™ | D62: =IFERROR(__xludf.DUMMYFUNCTION("""COMPUTED_VALUE"""),"PENDIENTE") -> PENDIENTE | E62: =IFERROR(__xludf.DUMMYFUNCTION("""COMPUTED_VALUE"""),4442362.0) -> 4442362 | F62: 593990524711
A63: {=IFERROR( INDEX(FEBRERO!B:B, MATCH(E63, FEBRERO!T:T, 0)), IFERROR( INDEX(MARZO!B:B, MATCH(E63, MARZO!T:T, 0)), "" ) )} -> 46061 | B63: =IFERROR(__xludf.DUMMYFUNCTION("""COMPUTED_VALUE"""),"Marco Benalcazar") -> Marco Benalcazar | C63: =IFERROR(__xludf.DUMMYFUNCTION("""COMPUTED_VALUE"""),"Cuchillo Tazaki™") -> Cuchillo Tazaki™ | D63: =IFERROR(__xludf.DUMMYFUNCTION("""COMPUTED_VALUE"""),"PENDIENTE") -> PENDIENTE | E63: =IFERROR(__xludf.DUMMYFUNCTION("""COMPUTED_VALUE"""),4442343.0) -> 4442343 | F63: 593960207439
A64: {=IFERROR( INDEX(FEBRERO!B:B, MATCH(E64, FEBRERO!T:T, 0)), IFERROR( INDEX(MARZO!B:B, MATCH(E64, MARZO!T:T, 0)), "" ) )} -> 46061 | B64: =IFERROR(__xludf.DUMMYFUNCTION("""COMPUTED_VALUE"""),"María sarango Sarango") -> María sarango Sarango | C64: =IFERROR(__xludf.DUMMYFUNCTION("""COMPUTED_VALUE"""),"Cuchillo Tazaki™") -> Cuchillo Tazaki™ | D64: =IFERROR(__xludf.DUMMYFUNCTION("""COMPUTED_VALUE"""),"PENDIENTE") -> PENDIENTE | E64: =IFERROR(__xludf.DUMMYFUNCTION("""COMPUTED_VALUE"""),4459428.0) -> 4459428 | F64: 593967935298
A65: {=IFERROR( INDEX(FEBRERO!B:B, MATCH(E65, FEBRERO!T:T, 0)), IFERROR( INDEX(MARZO!B:B, MATCH(E65, MARZO!T:T, 0)), "" ) )} -> 46061 | B65: =IFERROR(__xludf.DUMMYFUNCTION("""COMPUTED_VALUE"""),"German Villao") -> German Villao | C65: =IFERROR(__xludf.DUMMYFUNCTION("""COMPUTED_VALUE"""),"FilmPro®") -> FilmPro® | D65: =IFERROR(__xludf.DUMMYFUNCTION("""COMPUTED_VALUE"""),"PENDIENTE") -> PENDIENTE | E65: =IFERROR(__xludf.DUMMYFUNCTION("""COMPUTED_VALUE"""),4727865.0) -> 4727865 | F65: 593980988097
A66: {=IFERROR( INDEX(FEBRERO!B:B, MATCH(E66, FEBRERO!T:T, 0)), IFERROR( INDEX(MARZO!B:B, MATCH(E66, MARZO!T:T, 0)), "" ) )} -> 46061 | B66: =IFERROR(__xludf.DUMMYFUNCTION("""COMPUTED_VALUE"""),"Juan Carlos Guerrero Veliz") -> Juan Carlos Guerrero Veliz | C66: =IFERROR(__xludf.DUMMYFUNCTION("""COMPUTED_VALUE"""),"FilmPro®") -> FilmPro® | D66: =IFERROR(__xludf.DUMMYFUNCTION("""COMPUTED_VALUE"""),"PENDIENTE") -> PENDIENTE | E66: =IFERROR(__xludf.DUMMYFUNCTION("""COMPUTED_VALUE"""),4442321.0) -> 4442321 | F66: 593990022748
A67: {=IFERROR( INDEX(FEBRERO!B:B, MATCH(E67, FEBRERO!T:T, 0)), IFERROR( INDEX(MARZO!B:B, MATCH(E67, MARZO!T:T, 0)), "" ) )} -> 46061 | B67: =IFERROR(__xludf.DUMMYFUNCTION("""COMPUTED_VALUE"""),"Carlos Byron BERMEO LEÓN") -> Carlos Byron BERMEO LEÓN | C67: =IFERROR(__xludf.DUMMYFUNCTION("""COMPUTED_VALUE"""),"FilmPro®") -> FilmPro® | D67: =IFERROR(__xludf.DUMMYFUNCTION("""COMPUTED_VALUE"""),"PENDIENTE") -> PENDIENTE | E67: =IFERROR(__xludf.DUMMYFUNCTION("""COMPUTED_VALUE"""),4442318.0) -> 4442318 | F67: 593995612120
A68: {=IFERROR( INDEX(FEBRERO!B:B, MATCH(E68, FEBRERO!T:T, 0)), IFERROR( INDEX(MARZO!B:B, MATCH(E68, MARZO!T:T, 0)), "" ) )} -> 46061 | B68: =IFERROR(__xludf.DUMMYFUNCTION("""COMPUTED_VALUE"""),"Jose Avila") -> Jose Avila | C68: =IFERROR(__xludf.DUMMYFUNCTION("""COMPUTED_VALUE"""),"Llave Multifuncional 360™") -> Llave Multifuncional 360™ | D68: =IFERROR(__xludf.DUMMYFUNCTION("""COMPUTED_VALUE"""),"PENDIENTE") -> PENDIENTE | E68: =IFERROR(__xludf.DUMMYFUNCTION("""COMPUTED_VALUE"""),4451899.0) -> 4451899 | F68: 593990686703
A69: {=IFERROR( INDEX(FEBRERO!B:B, MATCH(E69, FEBRERO!T:T, 0)), IFERROR( INDEX(MARZO!B:B, MATCH(E69, MARZO!T:T, 0)), "" ) )} -> 46064 | B69: =IFERROR(__xludf.DUMMYFUNCTION("""COMPUTED_VALUE"""),"Rodrigo Jaramillo") -> Rodrigo Jaramillo | C69: =IFERROR(__xludf.DUMMYFUNCTION("""COMPUTED_VALUE"""),"FilmPro®") -> FilmPro® | D69: =IFERROR(__xludf.DUMMYFUNCTION("""COMPUTED_VALUE"""),"PENDIENTE") -> PENDIENTE | E69: =IFERROR(__xludf.DUMMYFUNCTION("""COMPUTED_VALUE"""),4490156.0) -> 4490156 | F69: 593994896232
A70: {=IFERROR( INDEX(FEBRERO!B:B, MATCH(E70, FEBRERO!T:T, 0)), IFERROR( INDEX(MARZO!B:B, MATCH(E70, MARZO!T:T, 0)), "" ) )} -> 46064 | B70: =IFERROR(__xludf.DUMMYFUNCTION("""COMPUTED_VALUE"""),"Mauricio Junez") -> Mauricio Junez | C70: =IFERROR(__xludf.DUMMYFUNCTION("""COMPUTED_VALUE"""),"FilmPro®") -> FilmPro® | D70: =IFERROR(__xludf.DUMMYFUNCTION("""COMPUTED_VALUE"""),"PENDIENTE") -> PENDIENTE | E70: =IFERROR(__xludf.DUMMYFUNCTION("""COMPUTED_VALUE"""),4483380.0) -> 4483380 | F70: 593992579210
A71: {=IFERROR( INDEX(FEBRERO!B:B, MATCH(E71, FEBRERO!T:T, 0)), IFERROR( INDEX(MARZO!B:B, MATCH(E71, MARZO!T:T, 0)), "" ) )} -> 46064 | B71: =IFERROR(__xludf.DUMMYFUNCTION("""COMPUTED_VALUE"""),"Welinton Torres") -> Welinton Torres | C71: =IFERROR(__xludf.DUMMYFUNCTION("""COMPUTED_VALUE"""),"FilmPro®") -> FilmPro® | D71: =IFERROR(__xludf.DUMMYFUNCTION("""COMPUTED_VALUE"""),"PENDIENTE") -> PENDIENTE | E71: =IFERROR(__xludf.DUMMYFUNCTION("""COMPUTED_VALUE"""),4483559.0) -> 4483559 | F71: 593986406970
A72: {=IFERROR( INDEX(FEBRERO!B:B, MATCH(E72, FEBRERO!T:T, 0)), IFERROR( INDEX(MARZO!B:B, MATCH(E72, MARZO!T:T, 0)), "" ) )} -> 46064 | B72: =IFERROR(__xludf.DUMMYFUNCTION("""COMPUTED_VALUE"""),"Roberto Cristobal Cristobal") -> Roberto Cristobal Cristobal | C72: =IFERROR(__xludf.DUMMYFUNCTION("""COMPUTED_VALUE"""),"FilmPro®") -> FilmPro® | D72: =IFERROR(__xludf.DUMMYFUNCTION("""COMPUTED_VALUE"""),"PENDIENTE") -> PENDIENTE | E72: =IFERROR(__xludf.DUMMYFUNCTION("""COMPUTED_VALUE"""),4483587.0) -> 4483587 | F72: 593967629742
A73: {=IFERROR( INDEX(FEBRERO!B:B, MATCH(E73, FEBRERO!T:T, 0)), IFERROR( INDEX(MARZO!B:B, MATCH(E73, MARZO!T:T, 0)), "" ) )} -> 46064 | B73: =IFERROR(__xludf.DUMMYFUNCTION("""COMPUTED_VALUE"""),"Paola Sevilla") -> Paola Sevilla | C73: =IFERROR(__xludf.DUMMYFUNCTION("""COMPUTED_VALUE"""),"FilmPro®") -> FilmPro® | D73: =IFERROR(__xludf.DUMMYFUNCTION("""COMPUTED_VALUE"""),"PENDIENTE") -> PENDIENTE | E73: =IFERROR(__xludf.DUMMYFUNCTION("""COMPUTED_VALUE"""),4483794.0) -> 4483794 | F73: 593984162851
A74: {=IFERROR( INDEX(FEBRERO!B:B, MATCH(E74, FEBRERO!T:T, 0)), IFERROR( INDEX(MARZO!B:B, MATCH(E74, MARZO!T:T, 0)), "" ) )} -> 46064 | B74: =IFERROR(__xludf.DUMMYFUNCTION("""COMPUTED_VALUE"""),"Patricio Moreta") -> Patricio Moreta | C74: =IFERROR(__xludf.DUMMYFUNCTION("""COMPUTED_VALUE"""),"Cuchillo Tazaki™") -> Cuchillo Tazaki™ | D74: =IFERROR(__xludf.DUMMYFUNCTION("""COMPUTED_VALUE"""),"PENDIENTE") -> PENDIENTE | E74: =IFERROR(__xludf.DUMMYFUNCTION("""COMPUTED_VALUE"""),4484906.0) -> 4484906 | F74: 593939578560
A75: {=IFERROR( INDEX(FEBRERO!B:B, MATCH(E75, FEBRERO!T:T, 0)), IFERROR( INDEX(MARZO!B:B, MATCH(E75, MARZO!T:T, 0)), "" ) )} -> 46065 | B75: =IFERROR(__xludf.DUMMYFUNCTION("""COMPUTED_VALUE"""),"Mario Nunez") -> Mario Nunez | C75: =IFERROR(__xludf.DUMMYFUNCTION("""COMPUTED_VALUE"""),"FilmPro®") -> FilmPro® | D75: =IFERROR(__xludf.DUMMYFUNCTION("""COMPUTED_VALUE"""),"PENDIENTE") -> PENDIENTE | E75: =IFERROR(__xludf.DUMMYFUNCTION("""COMPUTED_VALUE"""),4486547.0) -> 4486547 | F75: 593983029548
A76: {=IFERROR( INDEX(FEBRERO!B:B, MATCH(E76, FEBRERO!T:T, 0)), IFERROR( INDEX(MARZO!B:B, MATCH(E76, MARZO!T:T, 0)), "" ) )} -> 46065 | B76: =IFERROR(__xludf.DUMMYFUNCTION("""COMPUTED_VALUE"""),"Peter Aichholzer") -> Peter Aichholzer | C76: =IFERROR(__xludf.DUMMYFUNCTION("""COMPUTED_VALUE"""),"Cuchillo Tazaki™") -> Cuchillo Tazaki™ | D76: =IFERROR(__xludf.DUMMYFUNCTION("""COMPUTED_VALUE"""),"PENDIENTE") -> PENDIENTE | E76: =IFERROR(__xludf.DUMMYFUNCTION("""COMPUTED_VALUE"""),4487157.0) -> 4487157 | F76: 593996215180
A77: {=IFERROR( INDEX(FEBRERO!B:B, MATCH(E77, FEBRERO!T:T, 0)), IFERROR( INDEX(MARZO!B:B, MATCH(E77, MARZO!T:T, 0)), "" ) )} -> 46065 | B77: =IFERROR(__xludf.DUMMYFUNCTION("""COMPUTED_VALUE"""),"Ñusta Carmelina Poma González") -> Ñusta Carmelina Poma González | C77: =IFERROR(__xludf.DUMMYFUNCTION("""COMPUTED_VALUE"""),"FilmPro®") -> FilmPro® | D77: =IFERROR(__xludf.DUMMYFUNCTION("""COMPUTED_VALUE"""),"PENDIENTE") -> PENDIENTE | E77: =IFERROR(__xludf.DUMMYFUNCTION("""COMPUTED_VALUE"""),4489655.0) -> 4489655 | F77: 593996477023
A78: {=IFERROR( INDEX(FEBRERO!B:B, MATCH(E78, FEBRERO!T:T, 0)), IFERROR( INDEX(MARZO!B:B, MATCH(E78, MARZO!T:T, 0)), "" ) )} -> 46065 | B78: =IFERROR(__xludf.DUMMYFUNCTION("""COMPUTED_VALUE"""),"José Avelino Valencia Avelino Valencia") -> José Avelino Valencia Avelino Valencia | C78: =IFERROR(__xludf.DUMMYFUNCTION("""COMPUTED_VALUE"""),"Cuchillo Tazaki™") -> Cuchillo Tazaki™ | D78: =IFERROR(__xludf.DUMMYFUNCTION("""COMPUTED_VALUE"""),"PENDIENTE") -> PENDIENTE | E78: =IFERROR(__xludf.DUMMYFUNCTION("""COMPUTED_VALUE"""),4489985.0) -> 4489985 | F78: 593997468330
A79: {=IFERROR( INDEX(FEBRERO!B:B, MATCH(E79, FEBRERO!T:T, 0)), IFERROR( INDEX(MARZO!B:B, MATCH(E79, MARZO!T:T, 0)), "" ) )} -> 46065 | B79: =IFERROR(__xludf.DUMMYFUNCTION("""COMPUTED_VALUE"""),"Vilma Verdezoto") -> Vilma Verdezoto | C79: =IFERROR(__xludf.DUMMYFUNCTION("""COMPUTED_VALUE"""),"Cuchillo Tazaki™") -> Cuchillo Tazaki™ | D79: =IFERROR(__xludf.DUMMYFUNCTION("""COMPUTED_VALUE"""),"PENDIENTE") -> PENDIENTE | E79: =IFERROR(__xludf.DUMMYFUNCTION("""COMPUTED_VALUE"""),4492585.0) -> 4492585 | F79: 593982905505
A80: {=IFERROR( INDEX(FEBRERO!B:B, MATCH(E80, FEBRERO!T:T, 0)), IFERROR( INDEX(MARZO!B:B, MATCH(E80, MARZO!T:T, 0)), "" ) )} -> 46065 | B80: =IFERROR(__xludf.DUMMYFUNCTION("""COMPUTED_VALUE"""),"Christian Barragán") -> Christian Barragán | C80: =IFERROR(__xludf.DUMMYFUNCTION("""COMPUTED_VALUE"""),"FilmPro®") -> FilmPro® | D80: =IFERROR(__xludf.DUMMYFUNCTION("""COMPUTED_VALUE"""),"PENDIENTE") -> PENDIENTE | E80: =IFERROR(__xludf.DUMMYFUNCTION("""COMPUTED_VALUE"""),4493142.0) -> 4493142 | F80: 593981268434
A81: {=IFERROR( INDEX(FEBRERO!B:B, MATCH(E81, FEBRERO!T:T, 0)), IFERROR( INDEX(MARZO!B:B, MATCH(E81, MARZO!T:T, 0)), "" ) )} -> 46065 | B81: =IFERROR(__xludf.DUMMYFUNCTION("""COMPUTED_VALUE""")," Luis Francisco Sánchez Lima ") -> Luis Francisco Sánchez Lima | C81: =IFERROR(__xludf.DUMMYFUNCTION("""COMPUTED_VALUE"""),"Cuchillo Tazaki™") -> Cuchillo Tazaki™ | D81: =IFERROR(__xludf.DUMMYFUNCTION("""COMPUTED_VALUE"""),"PENDIENTE") -> PENDIENTE | E81: =IFERROR(__xludf.DUMMYFUNCTION("""COMPUTED_VALUE"""),4493589.0) -> 4493589 | F81: 593959898815
A82: {=IFERROR( INDEX(FEBRERO!B:B, MATCH(E82, FEBRERO!T:T, 0)), IFERROR( INDEX(MARZO!B:B, MATCH(E82, MARZO!T:T, 0)), "" ) )} -> 46065 | B82: =IFERROR(__xludf.DUMMYFUNCTION("""COMPUTED_VALUE""")," Antoñia Tanguila ") -> Antoñia Tanguila | C82: =IFERROR(__xludf.DUMMYFUNCTION("""COMPUTED_VALUE"""),"Cuchillo Tazaki™") -> Cuchillo Tazaki™ | D82: =IFERROR(__xludf.DUMMYFUNCTION("""COMPUTED_VALUE"""),"PENDIENTE") -> PENDIENTE | E82: =IFERROR(__xludf.DUMMYFUNCTION("""COMPUTED_VALUE"""),4494048.0) -> 4494048 | F82: 593981890586
A83: {=IFERROR( INDEX(FEBRERO!B:B, MATCH(E83, FEBRERO!T:T, 0)), IFERROR( INDEX(MARZO!B:B, MATCH(E83, MARZO!T:T, 0)), "" ) )} -> 46065 | B83: =IFERROR(__xludf.DUMMYFUNCTION("""COMPUTED_VALUE"""),"Jorge Peralta") -> Jorge Peralta | C83: =IFERROR(__xludf.DUMMYFUNCTION("""COMPUTED_VALUE"""),"FilmPro®") -> FilmPro® | D83: =IFERROR(__xludf.DUMMYFUNCTION("""COMPUTED_VALUE"""),"PENDIENTE") -> PENDIENTE | E83: =IFERROR(__xludf.DUMMYFUNCTION("""COMPUTED_VALUE"""),4494455.0) -> 4494455 | F83: 593992868172
A84: {=IFERROR( INDEX(FEBRERO!B:B, MATCH(E84, FEBRERO!T:T, 0)), IFERROR( INDEX(MARZO!B:B, MATCH(E84, MARZO!T:T, 0)), "" ) )} -> 46065 | B84: =IFERROR(__xludf.DUMMYFUNCTION("""COMPUTED_VALUE"""),"Lenin Vivanco") -> Lenin Vivanco | C84: =IFERROR(__xludf.DUMMYFUNCTION("""COMPUTED_VALUE"""),"Cuchillo Tazaki™") -> Cuchillo Tazaki™ | D84: =IFERROR(__xludf.DUMMYFUNCTION("""COMPUTED_VALUE"""),"PENDIENTE") -> PENDIENTE | E84: =IFERROR(__xludf.DUMMYFUNCTION("""COMPUTED_VALUE"""),4494577.0) -> 4494577 | F84: 593991101095
A85: {=IFERROR( INDEX(FEBRERO!B:B, MATCH(E85, FEBRERO!T:T, 0)), IFERROR( INDEX(MARZO!B:B, MATCH(E85, MARZO!T:T, 0)), "" ) )} -> 46065 | B85: =IFERROR(__xludf.DUMMYFUNCTION("""COMPUTED_VALUE"""),"Juan dalgo") -> Juan dalgo | C85: =IFERROR(__xludf.DUMMYFUNCTION("""COMPUTED_VALUE"""),"Cuchillo Tazaki™") -> Cuchillo Tazaki™ | D85: =IFERROR(__xludf.DUMMYFUNCTION("""COMPUTED_VALUE"""),"PENDIENTE") -> PENDIENTE | E85: =IFERROR(__xludf.DUMMYFUNCTION("""COMPUTED_VALUE"""),4523232.0) -> 4523232 | F85: 593981401730
A86: {=IFERROR( INDEX(FEBRERO!B:B, MATCH(E86, FEBRERO!T:T, 0)), IFERROR( INDEX(MARZO!B:B, MATCH(E86, MARZO!T:T, 0)), "" ) )} -> 46066 | B86: =IFERROR(__xludf.DUMMYFUNCTION("""COMPUTED_VALUE"""),"Mariuxi Briones") -> Mariuxi Briones | C86: =IFERROR(__xludf.DUMMYFUNCTION("""COMPUTED_VALUE"""),"FilmPro®") -> FilmPro® | D86: =IFERROR(__xludf.DUMMYFUNCTION("""COMPUTED_VALUE"""),"PENDIENTE") -> PENDIENTE | E86: =IFERROR(__xludf.DUMMYFUNCTION("""COMPUTED_VALUE"""),4497704.0) -> 4497704 | F86: 593996782585
A87: {=IFERROR( INDEX(FEBRERO!B:B, MATCH(E87, FEBRERO!T:T, 0)), IFERROR( INDEX(MARZO!B:B, MATCH(E87, MARZO!T:T, 0)), "" ) )} -> 46066 | B87: =IFERROR(__xludf.DUMMYFUNCTION("""COMPUTED_VALUE"""),"Francisco pico pico") -> Francisco pico pico | C87: =IFERROR(__xludf.DUMMYFUNCTION("""COMPUTED_VALUE"""),"Cuchillo Tazaki™") -> Cuchillo Tazaki™ | D87: =IFERROR(__xludf.DUMMYFUNCTION("""COMPUTED_VALUE"""),"PENDIENTE") -> PENDIENTE | E87: =IFERROR(__xludf.DUMMYFUNCTION("""COMPUTED_VALUE"""),4499614.0) -> 4499614 | F87: 593994074409
A88: {=IFERROR( INDEX(FEBRERO!B:B, MATCH(E88, FEBRERO!T:T, 0)), IFERROR( INDEX(MARZO!B:B, MATCH(E88, MARZO!T:T, 0)), "" ) )} -> 46066 | B88: =IFERROR(__xludf.DUMMYFUNCTION("""COMPUTED_VALUE"""),"Carlos Martinez") -> Carlos Martinez | C88: =IFERROR(__xludf.DUMMYFUNCTION("""COMPUTED_VALUE"""),"Cuchillo Tazaki™") -> Cuchillo Tazaki™ | D88: =IFERROR(__xludf.DUMMYFUNCTION("""COMPUTED_VALUE"""),"PENDIENTE") -> PENDIENTE | E88: =IFERROR(__xludf.DUMMYFUNCTION("""COMPUTED_VALUE"""),4500415.0) -> 4500415 | F88: 593992315938
A89: {=IFERROR( INDEX(FEBRERO!B:B, MATCH(E89, FEBRERO!T:T, 0)), IFERROR( INDEX(MARZO!B:B, MATCH(E89, MARZO!T:T, 0)), "" ) )} -> 46066 | B89: =IFERROR(__xludf.DUMMYFUNCTION("""COMPUTED_VALUE"""),"Diego Donoso") -> Diego Donoso | C89: =IFERROR(__xludf.DUMMYFUNCTION("""COMPUTED_VALUE"""),"FilmPro®") -> FilmPro® | D89: =IFERROR(__xludf.DUMMYFUNCTION("""COMPUTED_VALUE"""),"PENDIENTE") -> PENDIENTE | E89: =IFERROR(__xludf.DUMMYFUNCTION("""COMPUTED_VALUE"""),4501265.0) -> 4501265 | F89: 593999337297
A90: {=IFERROR( INDEX(FEBRERO!B:B, MATCH(E90, FEBRERO!T:T, 0)), IFERROR( INDEX(MARZO!B:B, MATCH(E90, MARZO!T:T, 0)), "" ) )} -> 46066 | B90: =IFERROR(__xludf.DUMMYFUNCTION("""COMPUTED_VALUE"""),"Luis Martinez Martinez") -> Luis Martinez Martinez | C90: =IFERROR(__xludf.DUMMYFUNCTION("""COMPUTED_VALUE"""),"Cuchillo Tazaki™") -> Cuchillo Tazaki™ | D90: =IFERROR(__xludf.DUMMYFUNCTION("""COMPUTED_VALUE"""),"PENDIENTE") -> PENDIENTE | E90: =IFERROR(__xludf.DUMMYFUNCTION("""COMPUTED_VALUE"""),4502579.0) -> 4502579 | F90: 593985755887
A91: {=IFERROR( INDEX(FEBRERO!B:B, MATCH(E91, FEBRERO!T:T, 0)), IFERROR( INDEX(MARZO!B:B, MATCH(E91, MARZO!T:T, 0)), "" ) )} -> 46066 | B91: =IFERROR(__xludf.DUMMYFUNCTION("""COMPUTED_VALUE"""),"Edgar Borja") -> Edgar Borja | C91: =IFERROR(__xludf.DUMMYFUNCTION("""COMPUTED_VALUE"""),"FilmPro®") -> FilmPro® | D91: =IFERROR(__xludf.DUMMYFUNCTION("""COMPUTED_VALUE"""),"PENDIENTE") -> PENDIENTE | E91: =IFERROR(__xludf.DUMMYFUNCTION("""COMPUTED_VALUE"""),4505079.0) -> 4505079 | F91: 593992618226
A92: {=IFERROR( INDEX(FEBRERO!B:B, MATCH(E92, FEBRERO!T:T, 0)), IFERROR( INDEX(MARZO!B:B, MATCH(E92, MARZO!T:T, 0)), "" ) )} -> 46066 | B92: =IFERROR(__xludf.DUMMYFUNCTION("""COMPUTED_VALUE"""),"Galo Chicaiza") -> Galo Chicaiza | C92: =IFERROR(__xludf.DUMMYFUNCTION("""COMPUTED_VALUE"""),"FilmPro®") -> FilmPro® | D92: =IFERROR(__xludf.DUMMYFUNCTION("""COMPUTED_VALUE"""),"PENDIENTE") -> PENDIENTE | E92: =IFERROR(__xludf.DUMMYFUNCTION("""COMPUTED_VALUE"""),4505403.0) -> 4505403 | F92: 593962042029
A93: {=IFERROR( INDEX(FEBRERO!B:B, MATCH(E93, FEBRERO!T:T, 0)), IFERROR( INDEX(MARZO!B:B, MATCH(E93, MARZO!T:T, 0)), "" ) )} -> 46067 | B93: =IFERROR(__xludf.DUMMYFUNCTION("""COMPUTED_VALUE"""),"Jefferson Alfonso Carchi Guaman") -> Jefferson Alfonso Carchi Guaman | C93: =IFERROR(__xludf.DUMMYFUNCTION("""COMPUTED_VALUE"""),"FilmPro®") -> FilmPro® | D93: =IFERROR(__xludf.DUMMYFUNCTION("""COMPUTED_VALUE"""),"PENDIENTE") -> PENDIENTE | E93: =IFERROR(__xludf.DUMMYFUNCTION("""COMPUTED_VALUE"""),4506940.0) -> 4506940 | F93: 593994229984
A94: {=IFERROR( INDEX(FEBRERO!B:B, MATCH(E94, FEBRERO!T:T, 0)), IFERROR( INDEX(MARZO!B:B, MATCH(E94, MARZO!T:T, 0)), "" ) )} -> 46067 | B94: =IFERROR(__xludf.DUMMYFUNCTION("""COMPUTED_VALUE"""),"Antony smith García García") -> Antony smith García García | C94: =IFERROR(__xludf.DUMMYFUNCTION("""COMPUTED_VALUE"""),"FilmPro®") -> FilmPro® | D94: =IFERROR(__xludf.DUMMYFUNCTION("""COMPUTED_VALUE"""),"PENDIENTE") -> PENDIENTE | E94: =IFERROR(__xludf.DUMMYFUNCTION("""COMPUTED_VALUE"""),4510290.0) -> 4510290 | F94: 593968948141
A95: {=IFERROR( INDEX(FEBRERO!B:B, MATCH(E95, FEBRERO!T:T, 0)), IFERROR( INDEX(MARZO!B:B, MATCH(E95, MARZO!T:T, 0)), "" ) )} -> 46067 | B95: =IFERROR(__xludf.DUMMYFUNCTION("""COMPUTED_VALUE"""),"Diego Sacoto Arias") -> Diego Sacoto Arias | C95: =IFERROR(__xludf.DUMMYFUNCTION("""COMPUTED_VALUE"""),"Cuchillo Tazaki™") -> Cuchillo Tazaki™ | D95: =IFERROR(__xludf.DUMMYFUNCTION("""COMPUTED_VALUE"""),"PENDIENTE") -> PENDIENTE | E95: =IFERROR(__xludf.DUMMYFUNCTION("""COMPUTED_VALUE"""),4523371.0) -> 4523371 | F95: 593995888637
A96: {=IFERROR( INDEX(FEBRERO!B:B, MATCH(E96, FEBRERO!T:T, 0)), IFERROR( INDEX(MARZO!B:B, MATCH(E96, MARZO!T:T, 0)), "" ) )} -> 46067 | B96: =IFERROR(__xludf.DUMMYFUNCTION("""COMPUTED_VALUE"""),"Edison Javier Macías Yanez") -> Edison Javier Macías Yanez | C96: =IFERROR(__xludf.DUMMYFUNCTION("""COMPUTED_VALUE"""),"Cuchillo Tazaki™") -> Cuchillo Tazaki™ | D96: =IFERROR(__xludf.DUMMYFUNCTION("""COMPUTED_VALUE"""),"PENDIENTE") -> PENDIENTE | E96: =IFERROR(__xludf.DUMMYFUNCTION("""COMPUTED_VALUE"""),4523380.0) -> 4523380 | F96: 593992100352
A97: {=IFERROR( INDEX(FEBRERO!B:B, MATCH(E97, FEBRERO!T:T, 0)), IFERROR( INDEX(MARZO!B:B, MATCH(E97, MARZO!T:T, 0)), "" ) )} -> 46067 | B97: =IFERROR(__xludf.DUMMYFUNCTION("""COMPUTED_VALUE"""),"Irene Murillo Murillo") -> Irene Murillo Murillo | C97: =IFERROR(__xludf.DUMMYFUNCTION("""COMPUTED_VALUE"""),"Cuchillo Tazaki™") -> Cuchillo Tazaki™ | D97: =IFERROR(__xludf.DUMMYFUNCTION("""COMPUTED_VALUE"""),"PENDIENTE") -> PENDIENTE | E97: =IFERROR(__xludf.DUMMYFUNCTION("""COMPUTED_VALUE"""),4523383.0) -> 4523383 | F97: 593988511385
A98: {=IFERROR( INDEX(FEBRERO!B:B, MATCH(E98, FEBRERO!T:T, 0)), IFERROR( INDEX(MARZO!B:B, MATCH(E98, MARZO!T:T, 0)), "" ) )} -> 46068 | B98: =IFERROR(__xludf.DUMMYFUNCTION("""COMPUTED_VALUE"""),"Luis Guacho") -> Luis Guacho | C98: =IFERROR(__xludf.DUMMYFUNCTION("""COMPUTED_VALUE"""),"Cuchillo Tazaki™") -> Cuchillo Tazaki™ | D98: =IFERROR(__xludf.DUMMYFUNCTION("""COMPUTED_VALUE"""),"PENDIENTE") -> PENDIENTE | E98: =IFERROR(__xludf.DUMMYFUNCTION("""COMPUTED_VALUE"""),4523436.0) -> 4523436 | F98: 593959889626
A99: {=IFERROR( INDEX(FEBRERO!B:B, MATCH(E99, FEBRERO!T:T, 0)), IFERROR( INDEX(MARZO!B:B, MATCH(E99, MARZO!T:T, 0)), "" ) )} -> 46068 | B99: =IFERROR(__xludf.DUMMYFUNCTION("""COMPUTED_VALUE"""),"Jorge Baldeon") -> Jorge Baldeon | C99: =IFERROR(__xludf.DUMMYFUNCTION("""COMPUTED_VALUE"""),"Cuchillo Tazaki™") -> Cuchillo Tazaki™ | D99: =IFERROR(__xludf.DUMMYFUNCTION("""COMPUTED_VALUE"""),"PENDIENTE") -> PENDIENTE | E99: =IFERROR(__xludf.DUMMYFUNCTION("""COMPUTED_VALUE"""),4523441.0) -> 4523441 | F99: 593981497095
A100: {=IFERROR( INDEX(FEBRERO!B:B, MATCH(E100, FEBRERO!T:T, 0)), IFERROR( INDEX(MARZO!B:B, MATCH(E100, MARZO!T:T, 0)), "" ) )} -> 46068 | B100: =IFERROR(__xludf.DUMMYFUNCTION("""COMPUTED_VALUE"""),"Manuel Baez") -> Manuel Baez | C100: =IFERROR(__xludf.DUMMYFUNCTION("""COMPUTED_VALUE"""),"Cuchillo Tazaki™") -> Cuchillo Tazaki™ | D100: =IFERROR(__xludf.DUMMYFUNCTION("""COMPUTED_VALUE"""),"PENDIENTE") -> PENDIENTE | E100: =IFERROR(__xludf.DUMMYFUNCTION("""COMPUTED_VALUE"""),4523465.0) -> 4523465 | F100: 593992987410
...

Sheet MAPA_ESTADOS
A1: Estado fuente | B1: Estado final
A2: PENDIENTE CONFIRMACION | B2: PENDIENTE
A3: PENDIENTE | B3: PROCESO
A4: DESPACHADAS A SU DESTINO | B4: PROCESO
A5: GUIA_GENERADA | B5: PROCESO
A6: DEVOLUCION EN BODEGA | B6: PROCESO
A7: SALIO A RUTA | B7: PROCESO
A8: EN REPARTO | B8: PROCESO
A9: EN CAMINO | B9: PROCESO
A10: EN BODEGA | B10: PROCESO
A11: EN BODEGA ORIGEN | B11: PROCESO
A12: DESTINATARIO RE-PROGRAMA FECHA DE ENTREGA | B12: PROCESO
... A31: EN TRÁNSITO | B31: PROCESO

Sheet REPORTE_DROPI
A1: =IFERROR(__xludf.DUMMYFUNCTION("IMPORTRANGE( ""https://docs.google.com/spreadsheets/d/1vI8VDTQAvS4ylg1dS3pl-50GbsXENtde9coaP9K7IA8/edit?gid=1263028431#gid=1263028431"", ""REPORTE_DROPI!A:BA"" ) "),"FECHA DE REPORTE") -> FECHA DE REPORTE | B1: =IFERROR(__xludf.DUMMYFUNCTION("""COMPUTED_VALUE"""),"ID") -> ID | C1: =IFERROR(__xludf.DUMMYFUNCTION("""COMPUTED_VALUE"""),"HORA") -> HORA | D1: =IFERROR(__xludf.DUMMYFUNCTION("""COMPUTED_VALUE"""),"FECHA") -> FECHA | E1: =IFERROR(__xludf.DUMMYFUNCTION("""COMPUTED_VALUE"""),"NOMBRE CLIENTE") -> NOMBRE CLIENTE | F1: =IFERROR(__xludf.DUMMYFUNCTION("""COMPUTED_VALUE"""),"TELÉFONO") -> TELÉFONO | G1: =IFERROR(__xludf.DUMMYFUNCTION("""COMPUTED_VALUE"""),"EMAIL") -> EMAIL | H1: =IFERROR(__xludf.DUMMYFUNCTION("""COMPUTED_VALUE"""),"TIPO DE IDENTIFICACION") -> TIPO DE IDENTIFICACION | I1: =IFERROR(__xludf.DUMMYFUNCTION("""COMPUTED_VALUE"""),"NRO DE IDENTIFICACION") -> NRO DE IDENTIFICACION | J1: =IFERROR(__xludf.DUMMYFUNCTION("""COMPUTED_VALUE"""),"NÚMERO GUIA") -> NÚMERO GUIA | K1: =IFERROR(__xludf.DUMMYFUNCTION("""COMPUTED_VALUE"""),"ESTATUS") -> ESTATUS | L1: =IFERROR(__xludf.DUMMYFUNCTION("""COMPUTED_VALUE"""),"TIPO DE ENVIO") -> TIPO DE ENVIO | M1: =IFERROR(__xludf.DUMMYFUNCTION("""COMPUTED_VALUE"""),"DEPARTAMENTO DESTINO") -> DEPARTAMENTO DESTINO | N1: =IFERROR(__xludf.DUMMYFUNCTION("""COMPUTED_VALUE"""),"CIUDAD DESTINO") -> CIUDAD DESTINO | O1: =IFERROR(__xludf.DUMMYFUNCTION("""COMPUTED_VALUE"""),"DIRECCION") -> DIRECCION | P1: =IFERROR(__xludf.DUMMYFUNCTION("""COMPUTED_VALUE"""),"NOTAS") -> NOTAS | Q1: =IFERROR(__xludf.DUMMYFUNCTION("""COMPUTED_VALUE"""),"TRANSPORTADORA") -> TRANSPORTADORA | R1: =IFERROR(__xludf.DUMMYFUNCTION("""COMPUTED_VALUE"""),"TOTAL DE LA ORDEN") -> TOTAL DE LA ORDEN | S1: =IFERROR(__xludf.DUMMYFUNCTION("""COMPUTED_VALUE"""),"GANANCIA") -> GANANCIA | T1: =IFERROR(__xludf.DUMMYFUNCTION("""COMPUTED_VALUE"""),"PRECIO FLETE") -> PRECIO FLETE | U1: =IFERROR(__xludf.DUMMYFUNCTION("""COMPUTED_VALUE"""),"COSTO DEVOLUCION FLETE") -> COSTO DEVOLUCION FLETE | V1: =IFERROR(__xludf.DUMMYFUNCTION("""COMPUTED_VALUE"""),"COMISION") -> COMISION | W1: =IFERROR(__xludf.DUMMYFUNCTION("""COMPUTED_VALUE"""),"% COMISION DE LA PLATAFORMMA") -> % COMISION DE LA PLATAFORMMA | X1: =IFERROR(__xludf.DUMMYFUNCTION("""COMPUTED_VALUE"""),"PRECIO PROVEEDOR") -> PRECIO PROVEEDOR | Y1: =IFERROR(__xludf.DUMMYFUNCTION("""COMPUTED_VALUE"""),"PRECIO PROVEEDOR X CANTIDAD") -> PRECIO PROVEEDOR X CANTIDAD | Z1: =IFERROR(__xludf.DUMMYFUNCTION("""COMPUTED_VALUE"""),"PRODUCTO ID") -> PRODUCTO ID | AA1: =IFERROR(__xludf.DUMMYFUNCTION("""COMPUTED_VALUE"""),"SKU") -> SKU | AB1: =IFERROR(__xludf.DUMMYFUNCTION("""COMPUTED_VALUE"""),"VARIACION ID") -> VARIACION ID | AC1: =IFERROR(__xludf.DUMMYFUNCTION("""COMPUTED_VALUE"""),"PRODUCTO") -> PRODUCTO | AD1: =IFERROR(__xludf.DUMMYFUNCTION("""COMPUTED_VALUE"""),"VARIACION") -> VARIACION | AE1: =IFERROR(__xludf.DUMMYFUNCTION("""COMPUTED_VALUE"""),"CANTIDAD") -> CANTIDAD | AF1: =IFERROR(__xludf.DUMMYFUNCTION("""COMPUTED_VALUE"""),"NOVEDAD") -> NOVEDAD | AG1: =IFERROR(__xludf.DUMMYFUNCTION("""COMPUTED_VALUE"""),"FUE SOLUCIONADA LA NOVEDAD") -> FUE SOLUCIONADA LA NOVEDAD | AH1: =IFERROR(__xludf.DUMMYFUNCTION("""COMPUTED_VALUE"""),"HORA DE NOVEDAD") -> HORA DE NOVEDAD | AI1: =IFERROR(__xludf.DUMMYFUNCTION("""COMPUTED_VALUE"""),"FECHA DE NOVEDAD") -> FECHA DE NOVEDAD | AJ1: =IFERROR(__xludf.DUMMYFUNCTION("""COMPUTED_VALUE"""),"SOLUCIÓN") -> SOLUCIÓN | AK1: =IFERROR(__xludf.DUMMYFUNCTION("""COMPUTED_VALUE"""),"HORA DE SOLUCIÓN") -> HORA DE SOLUCIÓN | AL1: =IFERROR(__xludf.DUMMYFUNCTION("""COMPUTED_VALUE"""),"FECHA DE SOLUCIÓN") -> FECHA DE SOLUCIÓN | AM1: =IFERROR(__xludf.DUMMYFUNCTION("""COMPUTED_VALUE"""),"OBSERVACIÓN") -> OBSERVACIÓN | AN1: =IFERROR(__xludf.DUMMYFUNCTION("""COMPUTED_VALUE"""),"HORA DE ÚLTIMO MOVIMIENTO") -> HORA DE ÚLTIMO MOVIMIENTO | AO1: =IFERROR(__xludf.DUMMYFUNCTION("""COMPUTED_VALUE"""),"FECHA DE ÚLTIMO MOVIMIENTO") -> FECHA DE ÚLTIMO MOVIMIENTO | AP1: =IFERROR(__xludf.DUMMYFUNCTION("""COMPUTED_VALUE"""),"ÚLTIMO MOVIMIENTO") -> ÚLTIMO MOVIMIENTO | AQ1: =IFERROR(__xludf.DUMMYFUNCTION("""COMPUTED_VALUE"""),"CONCEPTO ÚLTIMO MOVIMIENTO") -> CONCEPTO ÚLTIMO MOVIMIENTO | AR1: =IFERROR(__xludf.DUMMYFUNCTION("""COMPUTED_VALUE"""),"UBICACIÓN DE ÚLTIMO MOVIMIENTO") -> UBICACIÓN DE ÚLTIMO MOVIMIENTO | AS1: =IFERROR(__xludf.DUMMYFUNCTION("""COMPUTED_VALUE"""),"VENDEDOR") -> VENDEDOR | AT1: =IFERROR(__xludf.DUMMYFUNCTION("""COMPUTED_VALUE"""),"TIPO DE TIENDA") -> TIPO DE TIENDA | AU1: =IFERROR(__xludf.DUMMYFUNCTION("""COMPUTED_VALUE"""),"TIENDA") -> TIENDA | AV1: =IFERROR(__xludf.DUMMYFUNCTION("""COMPUTED_VALUE"""),"ID DE ORDEN DE TIENDA") -> ID DE ORDEN DE TIENDA | AW1: =IFERROR(__xludf.DUMMYFUNCTION("""COMPUTED_VALUE"""),"NUMERO DE PEDIDO DE TIENDA") -> NUMERO DE PEDIDO DE TIENDA | AX1: =IFERROR(__xludf.DUMMYFUNCTION("""COMPUTED_VALUE"""),"TAGS") -> TAGS | AY1: =IFERROR(__xludf.DUMMYFUNCTION("""COMPUTED_VALUE"""),"FECHA GUIA GENERADA") -> FECHA GUIA GENERADA | AZ1: =IFERROR(__xludf.DUMMYFUNCTION("""COMPUTED_VALUE"""),"CONTADOR DE INDEMNIZACIONES") -> CONTADOR DE INDEMNIZACIONES | BA1: =IFERROR(__xludf.DUMMYFUNCTION("""COMPUTED_VALUE"""),"CONCEPTO ÚLTIMA INDENMIZACIÓN") -> CONCEPTO ÚLTIMA INDENMIZACIÓN
A2: =IFERROR(__xludf.DUMMYFUNCTION("""COMPUTED_VALUE"""),"27-03-2026") -> 27-03-2026 | B2: =IFERROR(__xludf.DUMMYFUNCTION("""COMPUTED_VALUE"""),4925510.0) -> 4925510 | C2: =IFERROR(__xludf.DUMMYFUNCTION("""COMPUTED_VALUE"""),"00:02") -> 00:02 | D2: =IFERROR(__xludf.DUMMYFUNCTION("""COMPUTED_VALUE"""),"27-03-2026") -> 27-03-2026 | E2: =IFERROR(__xludf.DUMMYFUNCTION("""COMPUTED_VALUE"""),"Jorge García") -> Jorge García | F2: =IFERROR(__xludf.DUMMYFUNCTION("""COMPUTED_VALUE"""),"994767785") -> 994767785 | G2: =IFERROR(__xludf.DUMMYFUNCTION("""COMPUTED_VALUE"""),"garciagorge593@gmail.com") -> garciagorge593@gmail.com | K2: =IFERROR(__xludf.DUMMYFUNCTION("""COMPUTED_VALUE"""),"PENDIENTE CONFIRMACION") -> PENDIENTE CONFIRMACION | L2: =IFERROR(__xludf.DUMMYFUNCTION("""COMPUTED_VALUE"""),"CON RECAUDO") -> CON RECAUDO | M2: =IFERROR(__xludf.DUMMYFUNCTION("""COMPUTED_VALUE"""),"SANTO DOMINGO DE LOS TSACHILAS") -> SANTO DOMINGO DE LOS TSACHILAS | N2: =IFERROR(__xludf.DUMMYFUNCTION("""COMPUTED_VALUE"""),"SANTO DOMINGO") -> SANTO DOMINGO | O2: =IFERROR(__xludf.DUMMYFUNCTION("""COMPUTED_VALUE"""),"Av chone y rio chila Bomboli cafeteria sr bolon -") -> Av chone y rio chila Bomboli cafeteria sr bolon - | Q2: =IFERROR(__xludf.DUMMYFUNCTION("""COMPUTED_VALUE"""),"GINTRACOM") -> GINTRACOM | R2: =IFERROR(__xludf.DUMMYFUNCTION("""COMPUTED_VALUE"""),22.0) -> 22 | T2: =IFERROR(__xludf.DUMMYFUNCTION("""COMPUTED_VALUE"""),5.84) -> 5.84 | U2: =IFERROR(__xludf.DUMMYFUNCTION("""COMPUTED_VALUE"""),0.0) -> 0 | V2: =IFERROR(__xludf.DUMMYFUNCTION("""COMPUTED_VALUE"""),0.0) -> 0 | W2: =IFERROR(__xludf.DUMMYFUNCTION("""COMPUTED_VALUE"""),0.0) -> 0 | X2: =IFERROR(__xludf.DUMMYFUNCTION("""COMPUTED_VALUE"""),2.4) -> 2.4 | Y2: =IFERROR(__xludf.DUMMYFUNCTION("""COMPUTED_VALUE"""),4.8) -> 4.8 | Z2: =IFERROR(__xludf.DUMMYFUNCTION("""COMPUTED_VALUE"""),119189.0) -> 119189 | AA2: =IFERROR(__xludf.DUMMYFUNCTION("""COMPUTED_VALUE"""),"CUCHILLO DE CHEF") -> CUCHILLO DE CHEF | AC2: =IFERROR(__xludf.DUMMYFUNCTION("""COMPUTED_VALUE"""),"CUCHILLO DE CHEF") -> CUCHILLO DE CHEF | AE2: =IFERROR(__xludf.DUMMYFUNCTION("""COMPUTED_VALUE"""),2.0) -> 2 | AT2: =IFERROR(__xludf.DUMMYFUNCTION("""COMPUTED_VALUE"""),"SHOPIFY") -> SHOPIFY | AU2: =IFERROR(__xludf.DUMMYFUNCTION("""COMPUTED_VALUE"""),"IMPORTEX EC") -> IMPORTEX EC | AV2: =IFERROR(__xludf.DUMMYFUNCTION("""COMPUTED_VALUE"""),"6606506917932") -> 6606506917932 | AW2: =IFERROR(__xludf.DUMMYFUNCTION("""COMPUTED_VALUE"""),6837.0) -> 6837
A3: =IFERROR(__xludf.DUMMYFUNCTION("""COMPUTED_VALUE"""),"27-03-2026") -> 27-03-2026 | B3: =IFERROR(__xludf.DUMMYFUNCTION("""COMPUTED_VALUE"""),4925487.0) -> 4925487 | C3: =IFERROR(__xludf.DUMMYFUNCTION("""COMPUTED_VALUE"""),"23:57") -> 23:57 | D3: =IFERROR(__xludf.DUMMYFUNCTION("""COMPUTED_VALUE"""),"26-03-2026") -> 26-03-2026 | E3: =IFERROR(__xludf.DUMMYFUNCTION("""COMPUTED_VALUE"""),"Mercedes Betancourt Bustos") -> Mercedes Betancourt Bustos | F3: =IFERROR(__xludf.DUMMYFUNCTION("""COMPUTED_VALUE"""),"939130538") -> 939130538 | G3: =IFERROR(__xludf.DUMMYFUNCTION("""COMPUTED_VALUE"""),"pilarbustos2025@gmail.com") -> pilarbustos2025@gmail.com | K3: =IFERROR(__xludf.DUMMYFUNCTION("""COMPUTED_VALUE"""),"PENDIENTE CONFIRMACION") -> PENDIENTE CONFIRMACION | L3: =IFERROR(__xludf.DUMMYFUNCTION("""COMPUTED_VALUE"""),"CON RECAUDO") -> CON RECAUDO | M3: =IFERROR(__xludf.DUMMYFUNCTION("""COMPUTED_VALUE"""),"PICHINCHA") -> PICHINCHA | N3: =IFERROR(__xludf.DUMMYFUNCTION("""COMPUTED_VALUE"""),"QUITO") -> QUITO | O3: =IFERROR(__xludf.DUMMYFUNCTION("""COMPUTED_VALUE"""),"Juan León Mera 263 y Charles Darwin Armenia 2, frente a la escuela Albany -") -> Juan León Mera 263 y Charles Darwin Armenia 2, frente a la escuela Albany - | Q3: =IFERROR(__xludf.DUMMYFUNCTION("""COMPUTED_VALUE"""),"GINTRACOM") -> GINTRACOM | R3: =IFERROR(__xludf.DUMMYFUNCTION("""COMPUTED_VALUE"""),32.0) -> 32 | T3: =IFERROR(__xludf.DUMMYFUNCTION("""COMPUTED_VALUE"""),6.24) -> 6.24 | U3: =IFERROR(__xludf.DUMMYFUNCTION("""COMPUTED_VALUE"""),0.0) -> 0 | V3: =IFERROR(__xludf.DUMMYFUNCTION("""COMPUTED_VALUE"""),0.0) -> 0 | W3: =IFERROR(__xludf.DUMMYFUNCTION("""COMPUTED_VALUE"""),0.0) -> 0 | X3: =IFERROR(__xludf.DUMMYFUNCTION("""COMPUTED_VALUE"""),2.4) -> 2.4 | Y3: =IFERROR(__xludf.DUMMYFUNCTION("""COMPUTED_VALUE"""),9.6) -> 9.6 | Z3: =IFERROR(__xludf.DUMMYFUNCTION("""COMPUTED_VALUE"""),119189.0) -> 119189 | AA3: =IFERROR(__xludf.DUMMYFUNCTION("""COMPUTED_VALUE"""),"CUCHILLO DE CHEF") -> CUCHILLO DE CHEF | AC3: =IFERROR(__xludf.DUMMYFUNCTION("""COMPUTED_VALUE"""),"CUCHILLO DE CHEF") -> CUCHILLO DE CHEF | AE3: =IFERROR(__xludf.DUMMYFUNCTION("""COMPUTED_VALUE"""),4.0) -> 4 | AT3: =IFERROR(__xludf.DUMMYFUNCTION("""COMPUTED_VALUE"""),"SHOPIFY") -> SHOPIFY | AU3: =IFERROR(__xludf.DUMMYFUNCTION("""COMPUTED_VALUE"""),"IMPORTEX EC") -> IMPORTEX EC | AV3: =IFERROR(__xludf.DUMMYFUNCTION("""COMPUTED_VALUE"""),"6606502559788") -> 6606502559788 | AW3: =IFERROR(__xludf.DUMMYFUNCTION("""COMPUTED_VALUE"""),6836.0) -> 6836
A4: =IFERROR(__xludf.DUMMYFUNCTION("""COMPUTED_VALUE"""),"27-03-2026") -> 27-03-2026 | B4: =IFERROR(__xludf.DUMMYFUNCTION("""COMPUTED_VALUE"""),4925060.0) -> 4925060 | C4: =IFERROR(__xludf.DUMMYFUNCTION("""COMPUTED_VALUE"""),"22:52") -> 22:52 | D4: =IFERROR(__xludf.DUMMYFUNCTION("""COMPUTED_VALUE"""),"26-03-2026") -> 26-03-2026 | E4: =IFERROR(__xludf.DUMMYFUNCTION("""COMPUTED_VALUE"""),"Jhonny Alberto Cojitambo balón") -> Jhonny Alberto Cojitambo balón | F4: =IFERROR(__xludf.DUMMYFUNCTION("""COMPUTED_VALUE"""),"967582617") -> 967582617 | G4: =IFERROR(__xludf.DUMMYFUNCTION("""COMPUTED_VALUE"""),"cojitambojhonny@gmail.com") -> cojitambojhonny@gmail.com | K4: =IFERROR(__xludf.DUMMYFUNCTION("""COMPUTED_VALUE"""),"PENDIENTE CONFIRMACION") -> PENDIENTE CONFIRMACION | L4: =IFERROR(__xludf.DUMMYFUNCTION("""COMPUTED_VALUE"""),"CON RECAUDO") -> CON RECAUDO | M4: =IFERROR(__xludf.DUMMYFUNCTION("""COMPUTED_VALUE"""),"SANTA ELENA") -> SANTA ELENA | N4: =IFERROR(__xludf.DUMMYFUNCTION("""COMPUTED_VALUE"""),"PUERTO SANTA ROSA") -> PUERTO SANTA ROSA | O4: =IFERROR(__xludf.DUMMYFUNCTION("""COMPUTED_VALUE"""),"Calle 56 Av 39 Diagonal estafio rio guayas frente a casa pastoral -") -> Calle 56 Av 39 Diagonal estafio rio guayas frente a casa pastoral - | Q4: =IFERROR(__xludf.DUMMYFUNCTION("""COMPUTED_VALUE"""),"LAARCOURIER") -> LAARCOURIER | R4: =IFERROR(__xludf.DUMMYFUNCTION("""COMPUTED_VALUE"""),22.0) -> 22 | T4: =IFERROR(__xludf.DUMMYFUNCTION("""COMPUTED_VALUE"""),6.8) -> 6.8 | U4: =IFERROR(__xludf.DUMMYFUNCTION("""COMPUTED_VALUE"""),0.0) -> 0 | V4: =IFERROR(__xludf.DUMMYFUNCTION("""COMPUTED_VALUE"""),0.0) -> 0 | W4: =IFERROR(__xludf.DUMMYFUNCTION("""COMPUTED_VALUE"""),0.0) -> 0 | X4: =IFERROR(__xludf.DUMMYFUNCTION("""COMPUTED_VALUE"""),2.4) -> 2.4 | Y4: =IFERROR(__xludf.DUMMYFUNCTION("""COMPUTED_VALUE"""),4.8) -> 4.8 | Z4: =IFERROR(__xludf.DUMMYFUNCTION("""COMPUTED_VALUE"""),119189.0) -> 119189 | AA4: =IFERROR(__xludf.DUMMYFUNCTION("""COMPUTED_VALUE"""),"CUCHILLO DE CHEF") -> CUCHILLO DE CHEF | AC4: =IFERROR(__xludf.DUMMYFUNCTION("""COMPUTED_VALUE"""),"CUCHILLO DE CHEF") -> CUCHILLO DE CHEF | AE4: =IFERROR(__xludf.DUMMYFUNCTION("""COMPUTED_VALUE"""),2.0) -> 2 | AT4: =IFERROR(__xludf.DUMMYFUNCTION("""COMPUTED_VALUE"""),"SHOPIFY") -> SHOPIFY | AU4: =IFERROR(__xludf.DUMMYFUNCTION("""COMPUTED_VALUE"""),"IMPORTEX EC") -> IMPORTEX EC | AV4: =IFERROR(__xludf.DUMMYFUNCTION("""COMPUTED_VALUE"""),"6606394490924") -> 6606394490924 | AW4: =IFERROR(__xludf.DUMMYFUNCTION("""COMPUTED_VALUE"""),6835.0) -> 6835
A5: =IFERROR(__xludf.DUMMYFUNCTION("""COMPUTED_VALUE"""),"27-03-2026") -> 27-03-2026 | B5: =IFERROR(__xludf.DUMMYFUNCTION("""COMPUTED_VALUE"""),4924635.0) -> 4924635 | C5: =IFERROR(__xludf.DUMMYFUNCTION("""COMPUTED_VALUE"""),"22:10") -> 22:10 | D5: =IFERROR(__xludf.DUMMYFUNCTION("""COMPUTED_VALUE"""),"26-03-2026") -> 26-03-2026 | E5: =IFERROR(__xludf.DUMMYFUNCTION("""COMPUTED_VALUE"""),"Néstor Rodriguez") -> Néstor Rodriguez | F5: =IFERROR(__xludf.DUMMYFUNCTION("""COMPUTED_VALUE"""),"995336267") -> 995336267 | G5: =IFERROR(__xludf.DUMMYFUNCTION("""COMPUTED_VALUE"""),"nestorarn77@gmail.com") -> nestorarn77@gmail.com | K5: =IFERROR(__xludf.DUMMYFUNCTION("""COMPUTED_VALUE"""),"PENDIENTE CONFIRMACION") -> PENDIENTE CONFIRMACION | L5: =IFERROR(__xludf.DUMMYFUNCTION("""COMPUTED_VALUE"""),"CON RECAUDO") -> CON RECAUDO | M5: =IFERROR(__xludf.DUMMYFUNCTION("""COMPUTED_VALUE"""),"PICHINCHA") -> PICHINCHA | N5: =IFERROR(__xludf.DUMMYFUNCTION("""COMPUTED_VALUE"""),"CONOCOTO") -> CONOCOTO | O5: =IFERROR(__xludf.DUMMYFUNCTION("""COMPUTED_VALUE"""),"Julio matovelle bosques de valle 2 y charles darwin La armenia -") -> Julio matovelle bosques de valle 2 y charles darwin La armenia - | Q5: =IFERROR(__xludf.DUMMYFUNCTION("""COMPUTED_VALUE"""),"GINTRACOM") -> GINTRACOM | R5: =IFERROR(__xludf.DUMMYFUNCTION("""COMPUTED_VALUE"""),27.0) -> 27 | T5: =IFERROR(__xludf.DUMMYFUNCTION("""COMPUTED_VALUE"""),6.03) -> 6.03 | U5: =IFERROR(__xludf.DUMMYFUNCTION("""COMPUTED_VALUE"""),0.0) -> 0 | V5: =IFERROR(__xludf.DUMMYFUNCTION("""COMPUTED_VALUE"""),0.0) -> 0 | W5: =IFERROR(__xludf.DUMMYFUNCTION("""COMPUTED_VALUE"""),0.0) -> 0 | X5: =IFERROR(__xludf.DUMMYFUNCTION("""COMPUTED_VALUE"""),2.4) -> 2.4 | Y5: =IFERROR(__xludf.DUMMYFUNCTION("""COMPUTED_VALUE"""),7.2) -> 7.2 | Z5: =IFERROR(__xludf.DUMMYFUNCTION("""COMPUTED_VALUE"""),119189.0) -> 119189 | AA5: =IFERROR(__xludf.DUMMYFUNCTION("""COMPUTED_VALUE"""),"CUCHILLO DE CHEF") -> CUCHILLO DE CHEF | AC5: =IFERROR(__xludf.DUMMYFUNCTION("""COMPUTED_VALUE"""),"CUCHILLO DE CHEF") -> CUCHILLO DE CHEF | AE5: =IFERROR(__xludf.DUMMYFUNCTION("""COMPUTED_VALUE"""),3.0) -> 3 | AT5: =IFERROR(__xludf.DUMMYFUNCTION("""COMPUTED_VALUE"""),"SHOPIFY") -> SHOPIFY | AU5: =IFERROR(__xludf.DUMMYFUNCTION("""COMPUTED_VALUE"""),"IMPORTEX EC") -> IMPORTEX EC | AV5: =IFERROR(__xludf.DUMMYFUNCTION("""COMPUTED_VALUE"""),"6606323875884") -> 6606323875884 | AW5: =IFERROR(__xludf.DUMMYFUNCTION("""COMPUTED_VALUE"""),6833.0) -> 6833
A6: =IFERROR(__xludf.DUMMYFUNCTION("""COMPUTED_VALUE"""),"27-03-2026") -> 27-03-2026 | B6: =IFERROR(__xludf.DUMMYFUNCTION("""COMPUTED_VALUE"""),4924022.0) -> 4924022 | C6: =IFERROR(__xludf.DUMMYFUNCTION("""COMPUTED_VALUE"""),"21:05") -> 21:05 | D6: =IFERROR(__xludf.DUMMYFUNCTION("""COMPUTED_VALUE"""),"26-03-2026") -> 26-03-2026 | E6: =IFERROR(__xludf.DUMMYFUNCTION("""COMPUTED_VALUE"""),"Luis Aizaga") -> Luis Aizaga | F6: =IFERROR(__xludf.DUMMYFUNCTION("""COMPUTED_VALUE"""),"986729725") -> 986729725 | G6: =IFERROR(__xludf.DUMMYFUNCTION("""COMPUTED_VALUE"""),"gluisalberto18@gmail.com") -> gluisalberto18@gmail.com | K6: =IFERROR(__xludf.DUMMYFUNCTION("""COMPUTED_VALUE"""),"PENDIENTE CONFIRMACION") -> PENDIENTE CONFIRMACION | L6: =IFERROR(__xludf.DUMMYFUNCTION("""COMPUTED_VALUE"""),"CON RECAUDO") -> CON RECAUDO | M6: =IFERROR(__xludf.DUMMYFUNCTION("""COMPUTED_VALUE"""),"GUAYAS") -> GUAYAS | N6: =IFERROR(__xludf.DUMMYFUNCTION("""COMPUTED_VALUE"""),"GUAYAQUIL") -> GUAYAQUIL | O6: =IFERROR(__xludf.DUMMYFUNCTION("""COMPUTED_VALUE"""),"Guayacanes Av José Luis tamayo Guayacanes Mz82 V2 -") -> Guayacanes Av José Luis tamayo Guayacanes Mz82 V2 - | Q6: =IFERROR(__xludf.DUMMYFUNCTION("""COMPUTED_VALUE"""),"GINTRACOM") -> GINTRACOM | R6: =IFERROR(__xludf.DUMMYFUNCTION("""COMPUTED_VALUE"""),32.0) -> 32 | T6: =IFERROR(__xludf.DUMMYFUNCTION("""COMPUTED_VALUE"""),4.63) -> 4.63 | U6: =IFERROR(__xludf.DUMMYFUNCTION("""COMPUTED_VALUE"""),0.0) -> 0 | V6: =IFERROR(__xludf.DUMMYFUNCTION("""COMPUTED_VALUE"""),0.0) -> 0 | W6: =IFERROR(__xludf.DUMMYFUNCTION("""COMPUTED_VALUE"""),0.0) -> 0 | X6: =IFERROR(__xludf.DUMMYFUNCTION("""COMPUTED_VALUE"""),2.4) -> 2.4 | Y6: =IFERROR(__xludf.DUMMYFUNCTION("""COMPUTED_VALUE"""),9.6) -> 9.6 | Z6: =IFERROR(__xludf.DUMMYFUNCTION("""COMPUTED_VALUE"""),119189.0) -> 119189 | AA6: =IFERROR(__xludf.DUMMYFUNCTION("""COMPUTED_VALUE"""),"CUCHILLO DE CHEF") -> CUCHILLO DE CHEF | AC6: =IFERROR(__xludf.DUMMYFUNCTION("""COMPUTED_VALUE"""),"CUCHILLO DE CHEF") -> CUCHILLO DE CHEF | AE6: =IFERROR(__xludf.DUMMYFUNCTION("""COMPUTED_VALUE"""),4.0) -> 4 | AT6: =IFERROR(__xludf.DUMMYFUNCTION("""COMPUTED_VALUE"""),"SHOPIFY") -> SHOPIFY | AU6: =IFERROR(__xludf.DUMMYFUNCTION("""COMPUTED_VALUE"""),"IMPORTEX EC") -> IMPORTEX EC | AV6: =IFERROR(__xludf.DUMMYFUNCTION("""COMPUTED_VALUE"""),"6606192836652") -> 6606192836652 | AW6: =IFERROR(__xludf.DUMMYFUNCTION("""COMPUTED_VALUE"""),6831.0) -> 6831
A7: =IFERROR(__xludf.DUMMYFUNCTION("""COMPUTED_VALUE"""),"27-03-2026") -> 27-03-2026 | B7: =IFERROR(__xludf.DUMMYFUNCTION("""COMPUTED_VALUE"""),4923947.0) -> 4923947 | C7: =IFERROR(__xludf.DUMMYFUNCTION("""COMPUTED_VALUE"""),"20:57") -> 20:57 | D7: =IFERROR(__xludf.DUMMYFUNCTION("""COMPUTED_VALUE"""),"26-03-2026") -> 26-03-2026 | E7: =IFERROR(__xludf.DUMMYFUNCTION("""COMPUTED_VALUE"""),"Gloria Sigcha") -> Gloria Sigcha | F7: =IFERROR(__xludf.DUMMYFUNCTION("""COMPUTED_VALUE"""),"958964033") -> 958964033 | G7: =IFERROR(__xludf.DUMMYFUNCTION("""COMPUTED_VALUE"""),"mariomera19enero@gimail.com") -> mariomera19enero@gimail.com | K7: =IFERROR(__xludf.DUMMYFUNCTION("""COMPUTED_VALUE"""),"PENDIENTE CONFIRMACION") -> PENDIENTE CONFIRMACION | L7: =IFERROR(__xludf.DUMMYFUNCTION("""COMPUTED_VALUE"""),"CON RECAUDO") -> CON RECAUDO | M7: =IFERROR(__xludf.DUMMYFUNCTION("""COMPUTED_VALUE"""),"PICHINCHA") -> PICHINCHA | N7: =IFERROR(__xludf.DUMMYFUNCTION("""COMPUTED_VALUE"""),"QUITO") -> QUITO | O7: =IFERROR(__xludf.DUMMYFUNCTION("""COMPUTED_VALUE"""),"José Jiménez y Ordoñes Carcelen frente. La iglesia corazón de Jesús -") -> José Jiménez y Ordoñes Carcelen frente. La iglesia corazón de Jesús - | Q7: =IFERROR(__xludf.DUMMYFUNCTION("""COMPUTED_VALUE"""),"GINTRACOM") -> GINTRACOM | R7: =IFERROR(__xludf.DUMMYFUNCTION("""COMPUTED_VALUE"""),22.0) -> 22 | T7: =IFERROR(__xludf.DUMMYFUNCTION("""COMPUTED_VALUE"""),5.84) -> 5.84 | U7: =IFERROR(__xludf.DUMMYFUNCTION("""COMPUTED_VALUE"""),0.0) -> 0 | V7: =IFERROR(__xludf.DUMMYFUNCTION("""COMPUTED_VALUE"""),0.0) -> 0 | W7: =IFERROR(__xludf.DUMMYFUNCTION("""COMPUTED_VALUE"""),0.0) -> 0 | X7: =IFERROR(__xludf.DUMMYFUNCTION("""COMPUTED_VALUE"""),2.4) -> 2.4 | Y7: =IFERROR(__xludf.DUMMYFUNCTION("""COMPUTED_VALUE"""),4.8) -> 4.8 | Z7: =IFERROR(__xludf.DUMMYFUNCTION("""COMPUTED_VALUE"""),119189.0) -> 119189 | AA7: =IFERROR(__xludf.DUMMYFUNCTION("""COMPUTED_VALUE"""),"CUCHILLO DE CHEF") -> CUCHILLO DE CHEF | AC7: =IFERROR(__xludf.DUMMYFUNCTION("""COMPUTED_VALUE"""),"CUCHILLO DE CHEF") -> CUCHILLO DE CHEF | AE7: =IFERROR(__xludf.DUMMYFUNCTION("""COMPUTED_VALUE"""),2.0) -> 2 | AT7: =IFERROR(__xludf.DUMMYFUNCTION("""COMPUTED_VALUE"""),"SHOPIFY") -> SHOPIFY | AU7: =IFERROR(__xludf.DUMMYFUNCTION("""COMPUTED_VALUE"""),"IMPORTEX EC") -> IMPORTEX EC | AV7: =IFERROR(__xludf.DUMMYFUNCTION("""COMPUTED_VALUE"""),"6606176092204") -> 6606176092204 | AW7: =IFERROR(__xludf.DUMMYFUNCTION("""COMPUTED_VALUE"""),6830.0) -> 6830
A8: =IFERROR(__xludf.DUMMYFUNCTION("""COMPUTED_VALUE"""),"27-03-2026") -> 27-03-2026 | B8: =IFERROR(__xludf.DUMMYFUNCTION("""COMPUTED_VALUE"""),4923888.0) -> 4923888 | C8: =IFERROR(__xludf.DUMMYFUNCTION("""COMPUTED_VALUE"""),"20:50") -> 20:50 | D8: =IFERROR(__xludf.DUMMYFUNCTION("""COMPUTED_VALUE"""),"26-03-2026") -> 26-03-2026 | E8: =IFERROR(__xludf.DUMMYFUNCTION("""COMPUTED_VALUE"""),"Antonio Sánchez") -> Antonio Sánchez | F8: =IFERROR(__xludf.DUMMYFUNCTION("""COMPUTED_VALUE"""),"989147228") -> 989147228 | G8: =IFERROR(__xludf.DUMMYFUNCTION("""COMPUTED_VALUE"""),"fabianantoniosb120@gmail.com") -> fabianantoniosb120@gmail.com | K8: =IFERROR(__xludf.DUMMYFUNCTION("""COMPUTED_VALUE"""),"PENDIENTE CONFIRMACION") -> PENDIENTE CONFIRMACION | L8: =IFERROR(__xludf.DUMMYFUNCTION("""COMPUTED_VALUE"""),"CON RECAUDO") -> CON RECAUDO | M8: =IFERROR(__xludf.DUMMYFUNCTION("""COMPUTED_VALUE"""),"LOS RIOS") -> LOS RIOS | N8: =IFERROR(__xludf.DUMMYFUNCTION("""COMPUTED_VALUE"""),"BABA") -> BABA | O8: =IFERROR(__xludf.DUMMYFUNCTION("""COMPUTED_VALUE"""),"Por Servientrega lo retiró en baba hay Servientrega allí retiro yo Baba -") -> Por Servientrega lo retiró en baba hay Servientrega allí retiro yo Baba - | Q8: =IFERROR(__xludf.DUMMYFUNCTION("""COMPUTED_VALUE"""),"GINTRACOM") -> GINTRACOM | R8: =IFERROR(__xludf.DUMMYFUNCTION("""COMPUTED_VALUE"""),22.0) -> 22 | T8: =IFERROR(__xludf.DUMMYFUNCTION("""COMPUTED_VALUE"""),6.41) -> 6.41 | U8: =IFERROR(__xludf.DUMMYFUNCTION("""COMPUTED_VALUE"""),0.0) -> 0 | V8: =IFERROR(__xludf.DUMMYFUNCTION("""COMPUTED_VALUE"""),0.0) -> 0 | W8: =IFERROR(__xludf.DUMMYFUNCTION("""COMPUTED_VALUE"""),0.0) -> 0 | X8: =IFERROR(__xludf.DUMMYFUNCTION("""COMPUTED_VALUE"""),2.4) -> 2.4 | Y8: =IFERROR(__xludf.DUMMYFUNCTION("""COMPUTED_VALUE"""),4.8) -> 4.8 | Z8: =IFERROR(__xludf.DUMMYFUNCTION("""COMPUTED_VALUE"""),119189.0) -> 119189 | AA8: =IFERROR(__xludf.DUMMYFUNCTION("""COMPUTED_VALUE"""),"CUCHILLO DE CHEF") -> CUCHILLO DE CHEF | AC8: =IFERROR(__xludf.DUMMYFUNCTION("""COMPUTED_VALUE"""),"CUCHILLO DE CHEF") -> CUCHILLO DE CHEF | AE8: =IFERROR(__xludf.DUMMYFUNCTION("""COMPUTED_VALUE"""),2.0) -> 2 | AT8: =IFERROR(__xludf.DUMMYFUNCTION("""COMPUTED_VALUE"""),"SHOPIFY") -> SHOPIFY | AU8: =IFERROR(__xludf.DUMMYFUNCTION("""COMPUTED_VALUE"""),"IMPORTEX EC") -> IMPORTEX EC | AV8: =IFERROR(__xludf.DUMMYFUNCTION("""COMPUTED_VALUE"""),"6606163673132") -> 6606163673132 | AW8: =IFERROR(__xludf.DUMMYFUNCTION("""COMPUTED_VALUE"""),6829.0) -> 6829
A9: =IFERROR(__xludf.DUMMYFUNCTION("""COMPUTED_VALUE"""),"27-03-2026") -> 27-03-2026 | B9: =IFERROR(__xludf.DUMMYFUNCTION("""COMPUTED_VALUE"""),4923799.0) -> 4923799 | C9: =IFERROR(__xludf.DUMMYFUNCTION("""COMPUTED_VALUE"""),"20:41") -> 20:41 | D9: =IFERROR(__xludf.DUMMYFUNCTION("""COMPUTED_VALUE"""),"26-03-2026") -> 26-03-2026 | E9: =IFERROR(__xludf.DUMMYFUNCTION("""COMPUTED_VALUE"""),"Angel humberto Lopez zambrano") -> Angel humberto Lopez zambrano | F9: =IFERROR(__xludf.DUMMYFUNCTION("""COMPUTED_VALUE"""),"984444705") -> 984444705 | G9: =IFERROR(__xludf.DUMMYFUNCTION("""COMPUTED_VALUE"""),"angellopezzambrano@gmail.com") -> angellopezzambrano@gmail.com | K9: =IFERROR(__xludf.DUMMYFUNCTION("""COMPUTED_VALUE"""),"PENDIENTE CONFIRMACION") -> PENDIENTE CONFIRMACION | L9: =IFERROR(__xludf.DUMMYFUNCTION("""COMPUTED_VALUE"""),"CON RECAUDO") -> CON RECAUDO | M9: =IFERROR(__xludf.DUMMYFUNCTION("""COMPUTED_VALUE"""),"LOS RIOS") -> LOS RIOS | N9: =IFERROR(__xludf.DUMMYFUNCTION("""COMPUTED_VALUE"""),"QUEVEDO") -> QUEVEDO | O9: =IFERROR(__xludf.DUMMYFUNCTION("""COMPUTED_VALUE"""),"Anillo vial quevedo ventanas pasando la gasolinera karolina a 300 metros Recinto la sucre en la via principal -") -> Anillo vial quevedo ventanas pasando la gasolinera karolina a 300 metros Recinto la sucre en la via principal - | Q9: =IFERROR(__xludf.DUMMYFUNCTION("""COMPUTED_VALUE"""),"GINTRACOM") -> GINTRACOM | R9: =IFERROR(__xludf.DUMMYFUNCTION("""COMPUTED_VALUE"""),22.0) -> 22 | T9: =IFERROR(__xludf.DUMMYFUNCTION("""COMPUTED_VALUE"""),5.84) -> 5.84 | U9: =IFERROR(__xludf.DUMMYFUNCTION("""COMPUTED_VALUE"""),0.0) -> 0 | V9: =IFERROR(__xludf.DUMMYFUNCTION("""COMPUTED_VALUE"""),0.0) -> 0 | W9: =IFERROR(__xludf.DUMMYFUNCTION("""COMPUTED_VALUE"""),0.0) -> 0 | X9: =IFERROR(__xludf.DUMMYFUNCTION("""COMPUTED_VALUE"""),2.4) -> 2.4 | Y9: =IFERROR(__xludf.DUMMYFUNCTION("""COMPUTED_VALUE"""),4.8) -> 4.8 | Z9: =IFERROR(__xludf.DUMMYFUNCTION("""COMPUTED_VALUE"""),119189.0) -> 119189 | AA9: =IFERROR(__xludf.DUMMYFUNCTION("""COMPUTED_VALUE"""),"CUCHILLO DE CHEF") -> CUCHILLO DE CHEF | AC9: =IFERROR(__xludf.DUMMYFUNCTION("""COMPUTED_VALUE"""),"CUCHILLO DE CHEF") -> CUCHILLO DE CHEF | AE9: =IFERROR(__xludf.DUMMYFUNCTION("""COMPUTED_VALUE"""),2.0) -> 2 | AT9: =IFERROR(__xludf.DUMMYFUNCTION("""COMPUTED_VALUE"""),"SHOPIFY") -> SHOPIFY | AU9: =IFERROR(__xludf.DUMMYFUNCTION("""COMPUTED_VALUE"""),"IMPORTEX EC") -> IMPORTEX EC | AV9: =IFERROR(__xludf.DUMMYFUNCTION("""COMPUTED_VALUE"""),"6606143684652") -> 6606143684652 | AW9: =IFERROR(__xludf.DUMMYFUNCTION("""COMPUTED_VALUE"""),6828.0) -> 6828
A10: =IFERROR(__xludf.DUMMYFUNCTION("""COMPUTED_VALUE"""),"27-03-2026") -> 27-03-2026 | B10: =IFERROR(__xludf.DUMMYFUNCTION("""COMPUTED_VALUE"""),4923790.0) -> 4923790 | C10: =IFERROR(__xludf.DUMMYFUNCTION("""COMPUTED_VALUE"""),"20:40") -> 20:40 | D10: =IFERROR(__xludf.DUMMYFUNCTION("""COMPUTED_VALUE"""),"26-03-2026") -> 26-03-2026 | E10: =IFERROR(__xludf.DUMMYFUNCTION("""COMPUTED_VALUE"""),"Margarita León") -> Margarita León | F10: =IFERROR(__xludf.DUMMYFUNCTION("""COMPUTED_VALUE"""),"997914127") -> 997914127 | G10: =IFERROR(__xludf.DUMMYFUNCTION("""COMPUTED_VALUE"""),"margaritaleon259@gmail.com") -> margaritaleon259@gmail.com | K10: =IFERROR(__xludf.DUMMYFUNCTION("""COMPUTED_VALUE"""),"PENDIENTE CONFIRMACION") -> PENDIENTE CONFIRMACION | L10: =IFERROR(__xludf.DUMMYFUNCTION("""COMPUTED_VALUE"""),"CON RECAUDO") -> CON RECAUDO | M10: =IFERROR(__xludf.DUMMYFUNCTION("""COMPUTED_VALUE"""),"GUAYAS") -> GUAYAS | N10: =IFERROR(__xludf.DUMMYFUNCTION("""COMPUTED_VALUE"""),"GUAYAQUIL") -> GUAYAQUIL | O10: =IFERROR(__xludf.DUMMYFUNCTION("""COMPUTED_VALUE"""),"Orquídeas Orquídeas -") -> Orquídeas Orquídeas - | Q10: =IFERROR(__xludf.DUMMYFUNCTION("""COMPUTED_VALUE"""),"GINTRACOM") -> GINTRACOM | R10: =IFERROR(__xludf.DUMMYFUNCTION("""COMPUTED_VALUE"""),22.0) -> 22 | T10: =IFERROR(__xludf.DUMMYFUNCTION("""COMPUTED_VALUE"""),4.23) -> 4.23 | U10: =IFERROR(__xludf.DUMMYFUNCTION("""COMPUTED_VALUE"""),0.0) -> 0 | V10: =IFERROR(__xludf.DUMMYFUNCTION("""COMPUTED_VALUE"""),0.0) -> 0 | W10: =IFERROR(__xludf.DUMMYFUNCTION("""COMPUTED_VALUE"""),0.0) -> 0 | X10: =IFERROR(__xludf.DUMMYFUNCTION("""COMPUTED_VALUE"""),2.4) -> 2.4 | Y10: =IFERROR(__xludf.DUMMYFUNCTION("""COMPUTED_VALUE"""),4.8) -> 4.8 | Z10: =IFERROR(__xludf.DUMMYFUNCTION("""COMPUTED_VALUE"""),119189.0) -> 119189 | AA10: =IFERROR(__xludf.DUMMYFUNCTION("""COMPUTED_VALUE"""),"CUCHILLO DE CHEF") -> CUCHILLO DE CHEF | AC10: =IFERROR(__xludf.DUMMYFUNCTION("""COMPUTED_VALUE"""),"CUCHILLO DE CHEF") -> CUCHILLO DE CHEF | AE10: =IFERROR(__xludf.DUMMYFUNCTION("""COMPUTED_VALUE"""),2.0) -> 2 | AT10: =IFERROR(__xludf.DUMMYFUNCTION("""COMPUTED_VALUE"""),"SHOPIFY") -> SHOPIFY | AU10: =IFERROR(__xludf.DUMMYFUNCTION("""COMPUTED_VALUE"""),"IMPORTEX EC") -> IMPORTEX EC | AV10: =IFERROR(__xludf.DUMMYFUNCTION("""COMPUTED_VALUE"""),"6606142013484") -> 6606142013484 | AW10: =IFERROR(__xludf.DUMMYFUNCTION("""COMPUTED_VALUE"""),6827.0) -> 6827
A11: =IFERROR(__xludf.DUMMYFUNCTION("""COMPUTED_VALUE"""),"27-03-2026") -> 27-03-2026 | B11: =IFERROR(__xludf.DUMMYFUNCTION("""COMPUTED_VALUE"""),4923734.0) -> 4923734 | C11: =IFERROR(__xludf.DUMMYFUNCTION("""COMPUTED_VALUE"""),"20:33") -> 20:33 | D11: =IFERROR(__xludf.DUMMYFUNCTION("""COMPUTED_VALUE"""),"26-03-2026") -> 26-03-2026 | E11: =IFERROR(__xludf.DUMMYFUNCTION("""COMPUTED_VALUE"""),"Lupe Hidalgo") -> Lupe Hidalgo | F11: =IFERROR(__xludf.DUMMYFUNCTION("""COMPUTED_VALUE"""),"978738187") -> 978738187 | K11: =IFERROR(__xludf.DUMMYFUNCTION("""COMPUTED_VALUE"""),"PENDIENTE CONFIRMACION") -> PENDIENTE CONFIRMACION | L11: =IFERROR(__xludf.DUMMYFUNCTION("""COMPUTED_VALUE"""),"CON RECAUDO") -> CON RECAUDO | M11: =IFERROR(__xludf.DUMMYFUNCTION("""COMPUTED_VALUE"""),"PICHINCHA") -> PICHINCHA | N11: =IFERROR(__xludf.DUMMYFUNCTION("""COMPUTED_VALUE"""),"YARUQUI") -> YARUQUI | O11: =IFERROR(__xludf.DUMMYFUNCTION("""COMPUTED_VALUE"""),"Panamericana Norte km 32 Fundación oftalmológica del valle -") -> Panamericana Norte km 32 Fundación oftalmológica del valle - | Q11: =IFERROR(__xludf.DUMMYFUNCTION("""COMPUTED_VALUE"""),"GINTRACOM") -> GINTRACOM | R11: =IFERROR(__xludf.DUMMYFUNCTION("""COMPUTED_VALUE"""),22.0) -> 22 | T11: =IFERROR(__xludf.DUMMYFUNCTION("""COMPUTED_VALUE"""),6.41) -> 6.41 | U11: =IFERROR(__xludf.DUMMYFUNCTION("""COMPUTED_VALUE"""),0.0) -> 0 | V11: =IFERROR(__xludf.DUMMYFUNCTION("""COMPUTED_VALUE"""),0.0) -> 0 | W11: =IFERROR(__xludf.DUMMYFUNCTION("""COMPUTED_VALUE"""),0.0) -> 0 | X11: =IFERROR(__xludf.DUMMYFUNCTION("""COMPUTED_VALUE"""),2.4) -> 2.4 | Y11: =IFERROR(__xludf.DUMMYFUNCTION("""COMPUTED_VALUE"""),4.8) -> 4.8 | Z11: =IFERROR(__xludf.DUMMYFUNCTION("""COMPUTED_VALUE"""),119189.0) -> 119189 | AA11: =IFERROR(__xludf.DUMMYFUNCTION("""COMPUTED_VALUE"""),"CUCHILLO DE CHEF") -> CUCHILLO DE CHEF | AC11: =IFERROR(__xludf.DUMMYFUNCTION("""COMPUTED_VALUE"""),"CUCHILLO DE CHEF") -> CUCHILLO DE CHEF | AE11: =IFERROR(__xludf.DUMMYFUNCTION("""COMPUTED_VALUE"""),2.0) -> 2 | AT11: =IFERROR(__xludf.DUMMYFUNCTION("""COMPUTED_VALUE"""),"SHOPIFY") -> SHOPIFY | AU11: =IFERROR(__xludf.DUMMYFUNCTION("""COMPUTED_VALUE"""),"IMPORTEX EC") -> IMPORTEX EC | AV11: =IFERROR(__xludf.DUMMYFUNCTION("""COMPUTED_VALUE"""),"6606131232812") -> 6606131232812 | AW11: =IFERROR(__xludf.DUMMYFUNCTION("""COMPUTED_VALUE"""),6826.0) -> 6826
A12: =IFERROR(__xludf.DUMMYFUNCTION("""COMPUTED_VALUE"""),"27-03-2026") -> 27-03-2026 | B12: =IFERROR(__xludf.DUMMYFUNCTION("""COMPUTED_VALUE"""),4923404.0) -> 4923404 | C12: =IFERROR(__xludf.DUMMYFUNCTION("""COMPUTED_VALUE"""),"19:58") -> 19:58 | D12: =IFERROR(__xludf.DUMMYFUNCTION("""COMPUTED_VALUE"""),"26-03-2026") -> 26-03-2026 | E12: =IFERROR(__xludf.DUMMYFUNCTION("""COMPUTED_VALUE"""),"Michel Campoverde") -> Michel Campoverde | F12: =IFERROR(__xludf.DUMMYFUNCTION("""COMPUTED_VALUE"""),"991393778") -> 991393778 | G12: =IFERROR(__xludf.DUMMYFUNCTION("""COMPUTED_VALUE"""),"michel1campoverde@gmail.com") -> michel1campoverde@gmail.com | K12: =IFERROR(__xludf.DUMMYFUNCTION("""COMPUTED_VALUE"""),"PENDIENTE CONFIRMACION") -> PENDIENTE CONFIRMACION | L12: =IFERROR(__xludf.DUMMYFUNCTION("""COMPUTED_VALUE"""),"CON RECAUDO") -> CON RECAUDO | M12: =IFERROR(__xludf.DUMMYFUNCTION("""COMPUTED_VALUE"""),"EL ORO") -> EL ORO | N12: =IFERROR(__xludf.DUMMYFUNCTION("""COMPUTED_VALUE"""),"MACHALA") -> MACHALA | O12: =IFERROR(__xludf.DUMMYFUNCTION("""COMPUTED_VALUE"""),"Urbanización La Carolina Conjunto Mediterráneo 2 Villa 4 -") -> Urbanización La Carolina Conjunto Mediterráneo 2 Villa 4 - | Q12: =IFERROR(__xludf.DUMMYFUNCTION("""COMPUTED_VALUE"""),"GINTRACOM") -> GINTRACOM | R12: =IFERROR(__xludf.DUMMYFUNCTION("""COMPUTED_VALUE"""),20.0) -> 20 | T12: =IFERROR(__xludf.DUMMYFUNCTION("""COMPUTED_VALUE"""),5.76) -> 5.76 | U12: =IFERROR(__xludf.DUMMYFUNCTION("""COMPUTED_VALUE"""),0.0) -> 0 | V12: =IFERROR(__xludf.DUMMYFUNCTION("""COMPUTED_VALUE"""),0.0) -> 0 | W12: =IFERROR(__xludf.DUMMYFUNCTION("""COMPUTED_VALUE"""),0.0) -> 0 | X12: =IFERROR(__xludf.DUMMYFUNCTION("""COMPUTED_VALUE"""),1.0) -> 1 | Y12: =IFERROR(__xludf.DUMMYFUNCTION("""COMPUTED_VALUE"""),2.0) -> 2 | Z12: =IFERROR(__xludf.DUMMYFUNCTION("""COMPUTED_VALUE"""),2764.0) -> 2764 | AA12: =IFERROR(__xludf.DUMMYFUNCTION("""COMPUTED_VALUE"""),"14030581") -> 14030581 | AC12: =IFERROR(__xludf.DUMMYFUNCTION("""COMPUTED_VALUE"""),"AFILADOR DE CUCHILLOS") -> AFILADOR DE CUCHILLOS | AE12: =IFERROR(__xludf.DUMMYFUNCTION("""COMPUTED_VALUE"""),2.0) -> 2 | AT12: =IFERROR(__xludf.DUMMYFUNCTION("""COMPUTED_VALUE"""),"SHOPIFY") -> SHOPIFY | AU12: =IFERROR(__xludf.DUMMYFUNCTION("""COMPUTED_VALUE"""),"IMPORTEX EC") -> IMPORTEX EC | AV12: =IFERROR(__xludf.DUMMYFUNCTION("""COMPUTED_VALUE"""),"6606052982828") -> 6606052982828 | AW12: =IFERROR(__xludf.DUMMYFUNCTION("""COMPUTED_VALUE"""),6825.0) -> 6825
A13: =IFERROR(__xludf.DUMMYFUNCTION("""COMPUTED_VALUE"""),"27-03-2026") -> 27-03-2026 | B13: =IFERROR(__xludf.DUMMYFUNCTION("""COMPUTED_VALUE"""),4923194.0) -> 4923194 | C13: =IFERROR(__xludf.DUMMYFUNCTION("""COMPUTED_VALUE"""),"19:33") -> 19:33 | D13: =IFERROR(__xludf.DUMMYFUNCTION("""COMPUTED_VALUE"""),"26-03-2026") -> 26-03-2026 | E13: =IFERROR(__xludf.DUMMYFUNCTION("""COMPUTED_VALUE"""),"Hernando Enriquez") -> Hernando Enriquez | F13: =IFERROR(__xludf.DUMMYFUNCTION("""COMPUTED_VALUE"""),"982856884") -> 982856884 | K13: =IFERROR(__xludf.DUMMYFUNCTION("""COMPUTED_VALUE"""),"PENDIENTE CONFIRMACION") -> PENDIENTE CONFIRMACION | L13: =IFERROR(__xludf.DUMMYFUNCTION("""COMPUTED_VALUE"""),"CON RECAUDO") -> CON RECAUDO | M13: =IFERROR(__xludf.DUMMYFUNCTION("""COMPUTED_VALUE"""),"CARCHI") -> CARCHI | N13: =IFERROR(__xludf.DUMMYFUNCTION("""COMPUTED_VALUE"""),"LA PAZ") -> LA PAZ | O13: =IFERROR(__xludf.DUMMYFUNCTION("""COMPUTED_VALUE"""),"28 de octubre y ataualpa Frente al súper mercadito -") -> 28 de octubre y ataualpa Frente al súper mercadito - | Q13: =IFERROR(__xludf.DUMMYFUNCTION("""COMPUTED_VALUE"""),"SERVIENTREGA") -> SERVIENTREGA | R13: =IFERROR(__xludf.DUMMYFUNCTION("""COMPUTED_VALUE"""),20.0) -> 20 | T13: =IFERROR(__xludf.DUMMYFUNCTION("""COMPUTED_VALUE"""),7.67) -> 7.67 | U13: =IFERROR(__xludf.DUMMYFUNCTION("""COMPUTED_VALUE"""),0.0) -> 0 | V13: =IFERROR(__xludf.DUMMYFUNCTION("""COMPUTED_VALUE"""),0.0) -> 0 | W13: =IFERROR(__xludf.DUMMYFUNCTION("""COMPUTED_VALUE"""),0.0) -> 0 | X13: =IFERROR(__xludf.DUMMYFUNCTION("""COMPUTED_VALUE"""),1.0) -> 1 | Y13: =IFERROR(__xludf.DUMMYFUNCTION("""COMPUTED_VALUE"""),2.0) -> 2 | Z13: =IFERROR(__xludf.DUMMYFUNCTION("""COMPUTED_VALUE"""),2764.0) -> 2764 | AA13: =IFERROR(__xludf.DUMMYFUNCTION("""COMPUTED_VALUE"""),"14030581") -> 14030581 | AC13: =IFERROR(__xludf.DUMMYFUNCTION("""COMPUTED_VALUE"""),"AFILADOR DE CUCHILLOS") -> AFILADOR DE CUCHILLOS | AE13: =IFERROR(__xludf.DUMMYFUNCTION("""COMPUTED_VALUE"""),2.0) -> 2 | AT13: =IFERROR(__xludf.DUMMYFUNCTION("""COMPUTED_VALUE"""),"SHOPIFY") -> SHOPIFY | AU13: =IFERROR(__xludf.DUMMYFUNCTION("""COMPUTED_VALUE"""),"IMPORTEX EC") -> IMPORTEX EC | AV13: =IFERROR(__xludf.DUMMYFUNCTION("""COMPUTED_VALUE"""),"6606005436460") -> 6606005436460 | AW13: =IFERROR(__xludf.DUMMYFUNCTION("""COMPUTED_VALUE"""),6824.0) -> 6824
A14: =IFERROR(__xludf.DUMMYFUNCTION("""COMPUTED_VALUE"""),"27-03-2026") -> 27-03-2026 | B14: =IFERROR(__xludf.DUMMYFUNCTION("""COMPUTED_VALUE"""),4922565.0) -> 4922565 | C14: =IFERROR(__xludf.DUMMYFUNCTION("""COMPUTED_VALUE"""),"18:05") -> 18:05 | D14: =IFERROR(__xludf.DUMMYFUNCTION("""COMPUTED_VALUE"""),"26-03-2026") -> 26-03-2026 | E14: =IFERROR(__xludf.DUMMYFUNCTION("""COMPUTED_VALUE"""),"Jefferson Arguello bajaña") -> Jefferson Arguello bajaña | F14: =IFERROR(__xludf.DUMMYFUNCTION("""COMPUTED_VALUE"""),"981263532") -> 981263532 | K14: =IFERROR(__xludf.DUMMYFUNCTION("""COMPUTED_VALUE"""),"PENDIENTE CONFIRMACION") -> PENDIENTE CONFIRMACION | L14: =IFERROR(__xludf.DUMMYFUNCTION("""COMPUTED_VALUE"""),"CON RECAUDO") -> CON RECAUDO | M14: =IFERROR(__xludf.DUMMYFUNCTION("""COMPUTED_VALUE"""),"GUAYAS") -> GUAYAS | N14: =IFERROR(__xludf.DUMMYFUNCTION("""COMPUTED_VALUE"""),"GUAYAQUIL") -> GUAYAQUIL | O14: =IFERROR(__xludf.DUMMYFUNCTION("""COMPUTED_VALUE"""),"Gallegos Lara y segundo callejón sedalana Cristo del consuelo -") -> Gallegos Lara y segundo callejón sedalana Cristo del consuelo - | Q14: =IFERROR(__xludf.DUMMYFUNCTION("""COMPUTED_VALUE"""),"GINTRACOM") -> GINTRACOM | R14: =IFERROR(__xludf.DUMMYFUNCTION("""COMPUTED_VALUE"""),27.0) -> 27 | T14: =IFERROR(__xludf.DUMMYFUNCTION("""COMPUTED_VALUE"""),4.42) -> 4.42 | U14: =IFERROR(__xludf.DUMMYFUNCTION("""COMPUTED_VALUE"""),0.0) -> 0 | V14: =IFERROR(__xludf.DUMMYFUNCTION("""COMPUTED_VALUE"""),0.0) -> 0 | W14: =IFERROR(__xludf.DUMMYFUNCTION("""COMPUTED_VALUE"""),0.0) -> 0 | X14: =IFERROR(__xludf.DUMMYFUNCTION("""COMPUTED_VALUE"""),2.4) -> 2.4 | Y14: =IFERROR(__xludf.DUMMYFUNCTION("""COMPUTED_VALUE"""),7.2) -> 7.2 | Z14: =IFERROR(__xludf.DUMMYFUNCTION("""COMPUTED_VALUE"""),119189.0) -> 119189 | AA14: =IFERROR(__xludf.DUMMYFUNCTION("""COMPUTED_VALUE"""),"CUCHILLO DE CHEF") -> CUCHILLO DE CHEF | AC14: =IFERROR(__xludf.DUMMYFUNCTION("""COMPUTED_VALUE"""),"CUCHILLO DE CHEF") -> CUCHILLO DE CHEF | AE14: =IFERROR(__xludf.DUMMYFUNCTION("""COMPUTED_VALUE"""),3.0) -> 3 | AT14: =IFERROR(__xludf.DUMMYFUNCTION("""COMPUTED_VALUE"""),"SHOPIFY") -> SHOPIFY | AU14: =IFERROR(__xludf.DUMMYFUNCTION("""COMPUTED_VALUE"""),"IMPORTEX EC") -> IMPORTEX EC | AV14: =IFERROR(__xludf.DUMMYFUNCTION("""COMPUTED_VALUE"""),"6605828096044") -> 6605828096044 | AW14: =IFERROR(__xludf.DUMMYFUNCTION("""COMPUTED_VALUE"""),6823.0) -> 6823
A15: =IFERROR(__xludf.DUMMYFUNCTION("""COMPUTED_VALUE"""),"27-03-2026") -> 27-03-2026 | B15: =IFERROR(__xludf.DUMMYFUNCTION("""COMPUTED_VALUE"""),4922304.0) -> 4922304 | C15: =IFERROR(__xludf.DUMMYFUNCTION("""COMPUTED_VALUE"""),"17:34") -> 17:34 | D15: =IFERROR(__xludf.DUMMYFUNCTION("""COMPUTED_VALUE"""),"26-03-2026") -> 26-03-2026 | E15: =IFERROR(__xludf.DUMMYFUNCTION("""COMPUTED_VALUE"""),"Pedro Milton Reyes Gonzalez") -> Pedro Milton Reyes Gonzalez | F15: =IFERROR(__xludf.DUMMYFUNCTION("""COMPUTED_VALUE"""),"999459383") -> 999459383 | G15: =IFERROR(__xludf.DUMMYFUNCTION("""COMPUTED_VALUE"""),"pedromilton65@gmail.com") -> pedromilton65@gmail.com | K15: =IFERROR(__xludf.DUMMYFUNCTION("""COMPUTED_VALUE"""),"PENDIENTE CONFIRMACION") -> PENDIENTE CONFIRMACION | L15: =IFERROR(__xludf.DUMMYFUNCTION("""COMPUTED_VALUE"""),"CON RECAUDO") -> CON RECAUDO | M15: =IFERROR(__xludf.DUMMYFUNCTION("""COMPUTED_VALUE"""),"CAÑAR") -> CAÑAR | N15: =IFERROR(__xludf.DUMMYFUNCTION("""COMPUTED_VALUE"""),"LA TRONCAL") -> LA TRONCAL | O15: =IFERROR(__xludf.DUMMYFUNCTION("""COMPUTED_VALUE"""),"Décima cuarta este y segunda norte A Ciudadela 22de Marzo décima cuarta este y segunda norte A -") -> Décima cuarta este y segunda norte A Ciudadela 22de Marzo décima cuarta este y segunda norte A - | Q15: =IFERROR(__xludf.DUMMYFUNCTION("""COMPUTED_VALUE"""),"GINTRACOM") -> GINTRACOM | R15: =IFERROR(__xludf.DUMMYFUNCTION("""COMPUTED_VALUE"""),32.0) -> 32 | T15: =IFERROR(__xludf.DUMMYFUNCTION("""COMPUTED_VALUE"""),6.24) -> 6.24 | U15: =IFERROR(__xludf.DUMMYFUNCTION("""COMPUTED_VALUE"""),0.0) -> 0 | V15: =IFERROR(__xludf.DUMMYFUNCTION("""COMPUTED_VALUE"""),0.0) -> 0 | W15: =IFERROR(__xludf.DUMMYFUNCTION("""COMPUTED_VALUE"""),0.0) -> 0 | X15: =IFERROR(__xludf.DUMMYFUNCTION("""COMPUTED_VALUE"""),2.4) -> 2.4 | Y15: =IFERROR(__xludf.DUMMYFUNCTION("""COMPUTED_VALUE"""),9.6) -> 9.6 | Z15: =IFERROR(__xludf.DUMMYFUNCTION("""COMPUTED_VALUE"""),119189.0) -> 119189 | AA15: =IFERROR(__xludf.DUMMYFUNCTION("""COMPUTED_VALUE"""),"CUCHILLO DE CHEF") -> CUCHILLO DE CHEF | AC15: =IFERROR(__xludf.DUMMYFUNCTION("""COMPUTED_VALUE"""),"CUCHILLO DE CHEF") -> CUCHILLO DE CHEF | AE15: =IFERROR(__xludf.DUMMYFUNCTION("""COMPUTED_VALUE"""),4.0) -> 4 | AT15: =IFERROR(__xludf.DUMMYFUNCTION("""COMPUTED_VALUE"""),"SHOPIFY") -> SHOPIFY | AU15: =IFERROR(__xludf.DUMMYFUNCTION("""COMPUTED_VALUE"""),"IMPORTEX EC") -> IMPORTEX EC | AV15: =IFERROR(__xludf.DUMMYFUNCTION("""COMPUTED_VALUE"""),"6605775732780") -> 6605775732780 | AW15: =IFERROR(__xludf.DUMMYFUNCTION("""COMPUTED_VALUE"""),6822.0) -> 6822
A16: =IFERROR(__xludf.DUMMYFUNCTION("""COMPUTED_VALUE"""),"27-03-2026") -> 27-03-2026 | B16: =IFERROR(__xludf.DUMMYFUNCTION("""COMPUTED_VALUE"""),4922049.0) -> 4922049 | C16: =IFERROR(__xludf.DUMMYFUNCTION("""COMPUTED_VALUE"""),"17:00") -> 17:00 | D16: =IFERROR(__xludf.DUMMYFUNCTION("""COMPUTED_VALUE"""),"26-03-2026") -> 26-03-2026 | E16: =IFERROR(__xludf.DUMMYFUNCTION("""COMPUTED_VALUE"""),"Francisco Caceres") -> Francisco Caceres | F16: =IFERROR(__xludf.DUMMYFUNCTION("""COMPUTED_VALUE"""),"993034467") -> 993034467 | G16: =IFERROR(__xludf.DUMMYFUNCTION("""COMPUTED_VALUE"""),"jarothcr@gmail.com") -> jarothcr@gmail.com | K16: =IFERROR(__xludf.DUMMYFUNCTION("""COMPUTED_VALUE"""),"PENDIENTE CONFIRMACION") -> PENDIENTE CONFIRMACION | L16: =IFERROR(__xludf.DUMMYFUNCTION("""COMPUTED_VALUE"""),"CON RECAUDO") -> CON RECAUDO | M16: =IFERROR(__xludf.DUMMYFUNCTION("""COMPUTED_VALUE"""),"MANABI") -> MANABI | N16: =IFERROR(__xludf.DUMMYFUNCTION("""COMPUTED_VALUE"""),"PORTOVIEJO") -> PORTOVIEJO | O16: =IFERROR(__xludf.DUMMYFUNCTION("""COMPUTED_VALUE"""),"San Eduardo Y 11 De Avosto Andres de vera -") -> San Eduardo Y 11 De Avosto Andres de vera - | Q16: =IFERROR(__xludf.DUMMYFUNCTION("""COMPUTED_VALUE"""),"GINTRACOM") -> GINTRACOM | R16: =IFERROR(__xludf.DUMMYFUNCTION("""COMPUTED_VALUE"""),22.0) -> 22 | T16: =IFERROR(__xludf.DUMMYFUNCTION("""COMPUTED_VALUE"""),5.84) -> 5.84 | U16: =IFERROR(__xludf.DUMMYFUNCTION("""COMPUTED_VALUE"""),0.0) -> 0 | V16: =IFERROR(__xludf.DUMMYFUNCTION("""COMPUTED_VALUE"""),0.0) -> 0 | W16: =IFERROR(__xludf.DUMMYFUNCTION("""COMPUTED_VALUE"""),0.0) -> 0 | X16: =IFERROR(__xludf.DUMMYFUNCTION("""COMPUTED_VALUE"""),2.4) -> 2.4 | Y16: =IFERROR(__xludf.DUMMYFUNCTION("""COMPUTED_VALUE"""),4.8) -> 4.8 | Z16: =IFERROR(__xludf.DUMMYFUNCTION("""COMPUTED_VALUE"""),119189.0) -> 119189 | AA16: =IFERROR(__xludf.DUMMYFUNCTION("""COMPUTED_VALUE"""),"CUCHILLO DE CHEF") -> CUCHILLO DE CHEF | AC16: =IFERROR(__xludf.DUMMYFUNCTION("""COMPUTED_VALUE"""),"CUCHILLO DE CHEF") -> CUCHILLO DE CHEF | AE16: =IFERROR(__xludf.DUMMYFUNCTION("""COMPUTED_VALUE"""),2.0) -> 2 | AT16: =IFERROR(__xludf.DUMMYFUNCTION("""COMPUTED_VALUE"""),"SHOPIFY") -> SHOPIFY | AU16: =IFERROR(__xludf.DUMMYFUNCTION("""COMPUTED_VALUE"""),"IMPORTEX EC") -> IMPORTEX EC | AV16: =IFERROR(__xludf.DUMMYFUNCTION("""COMPUTED_VALUE"""),"6605723566124") -> 6605723566124 | AW16: =IFERROR(__xludf.DUMMYFUNCTION("""COMPUTED_VALUE"""),6821.0) -> 6821
A17: =IFERROR(__xludf.DUMMYFUNCTION("""COMPUTED_VALUE"""),"27-03-2026") -> 27-03-2026 | B17: =IFERROR(__xludf.DUMMYFUNCTION("""COMPUTED_VALUE"""),4920617.0) -> 4920617 | C17: =IFERROR(__xludf.DUMMYFUNCTION("""COMPUTED_VALUE"""),"14:30") -> 14:30 | D17: =IFERROR(__xludf.DUMMYFUNCTION("""COMPUTED_VALUE"""),"26-03-2026") -> 26-03-2026 | E17: =IFERROR(__xludf.DUMMYFUNCTION("""COMPUTED_VALUE"""),"Felipe Condo") -> Felipe Condo | F17: =IFERROR(__xludf.DUMMYFUNCTION("""COMPUTED_VALUE"""),"986860264") -> 986860264 | G17: =IFERROR(__xludf.DUMMYFUNCTION("""COMPUTED_VALUE"""),"angelfelipe100@yahoo.es") -> angelfelipe100@yahoo.es | K17: =IFERROR(__xludf.DUMMYFUNCTION("""COMPUTED_VALUE"""),"PENDIENTE CONFIRMACION") -> PENDIENTE CONFIRMACION | L17: =IFERROR(__xludf.DUMMYFUNCTION("""COMPUTED_VALUE"""),"CON RECAUDO") -> CON RECAUDO | M17: =IFERROR(__xludf.DUMMYFUNCTION("""COMPUTED_VALUE"""),"GUAYAS") -> GUAYAS | N17: =IFERROR(__xludf.DUMMYFUNCTION("""COMPUTED_VALUE"""),"GUAYAQUIL") -> GUAYAQUIL | O17: =IFERROR(__xludf.DUMMYFUNCTION("""COMPUTED_VALUE"""),"Cdla. Las. Orqyideas, mz 1039, casa 39 Casa comunal iglesia catolica -") -> Cdla. Las. Orqyideas, mz 1039, casa 39 Casa comunal iglesia catolica - | Q17: =IFERROR(__xludf.DUMMYFUNCTION("""COMPUTED_VALUE"""),"GINTRACOM") -> GINTRACOM | R17: =IFERROR(__xludf.DUMMYFUNCTION("""COMPUTED_VALUE"""),27.0) -> 27 | T17: =IFERROR(__xludf.DUMMYFUNCTION("""COMPUTED_VALUE"""),4.42) -> 4.42 | U17: =IFERROR(__xludf.DUMMYFUNCTION("""COMPUTED_VALUE"""),0.0) -> 0 | V17: =IFERROR(__xludf.DUMMYFUNCTION("""COMPUTED_VALUE"""),0.0) -> 0 | W17: =IFERROR(__xludf.DUMMYFUNCTION("""COMPUTED_VALUE"""),0.0) -> 0 | X17: =IFERROR(__xludf.DUMMYFUNCTION("""COMPUTED_VALUE"""),2.4) -> 2.4 | Y17: =IFERROR(__xludf.DUMMYFUNCTION("""COMPUTED_VALUE"""),7.2) -> 7.2 | Z17: =IFERROR(__xludf.DUMMYFUNCTION("""COMPUTED_VALUE"""),119189.0) -> 119189 | AA17: =IFERROR(__xludf.DUMMYFUNCTION("""COMPUTED_VALUE"""),"CUCHILLO DE CHEF") -> CUCHILLO DE CHEF | AC17: =IFERROR(__xludf.DUMMYFUNCTION("""COMPUTED_VALUE"""),"CUCHILLO DE CHEF") -> CUCHILLO DE CHEF | AE17: =IFERROR(__xludf.DUMMYFUNCTION("""COMPUTED_VALUE"""),3.0) -> 3 | AT17: =IFERROR(__xludf.DUMMYFUNCTION("""COMPUTED_VALUE"""),"SHOPIFY") -> SHOPIFY | AU17: =IFERROR(__xludf.DUMMYFUNCTION("""COMPUTED_VALUE"""),"IMPORTEX EC") -> IMPORTEX EC | AV17: =IFERROR(__xludf.DUMMYFUNCTION("""COMPUTED_VALUE"""),"6605454114860") -> 6605454114860 | AW17: =IFERROR(__xludf.DUMMYFUNCTION("""COMPUTED_VALUE"""),6820.0) -> 6820
A18: =IFERROR(__xludf.DUMMYFUNCTION("""COMPUTED_VALUE"""),"27-03-2026") -> 27-03-2026 | B18: =IFERROR(__xludf.DUMMYFUNCTION("""COMPUTED_VALUE"""),4907820.0) -> 4907820 | C18: =IFERROR(__xludf.DUMMYFUNCTION("""COMPUTED_VALUE"""),"10:59") -> 10:59 | D18: =IFERROR(__xludf.DUMMYFUNCTION("""COMPUTED_VALUE"""),"25-03-2026") -> 25-03-2026 | E18: =IFERROR(__xludf.DUMMYFUNCTION("""COMPUTED_VALUE"""),"Germán Jiménez") -> Germán Jiménez | F18: =IFERROR(__xludf.DUMMYFUNCTION("""COMPUTED_VALUE"""),"985063080") -> 985063080 | J18: =IFERROR(__xludf.DUMMYFUNCTION("""COMPUTED_VALUE"""),"185035175") -> 185035175 | K18: =IFERROR(__xludf.DUMMYFUNCTION("""COMPUTED_VALUE"""),"PARA RETIRO EN AGENCIA SERVIENTREGA") -> PARA RETIRO EN AGENCIA SERVIENTREGA | L18: =IFERROR(__xludf.DUMMYFUNCTION("""COMPUTED_VALUE"""),"CON RECAUDO") -> CON RECAUDO | M18: =IFERROR(__xludf.DUMMYFUNCTION("""COMPUTED_VALUE"""),"NAPO") -> NAPO | N18: =IFERROR(__xludf.DUMMYFUNCTION("""COMPUTED_VALUE"""),"TENA") -> TENA | O18: =IFERROR(__xludf.DUMMYFUNCTION("""COMPUTED_VALUE"""),"RETIRA EN CS . TENA_PRINCIPAL - AV PANO SN VICTOR HUGO SAN MIGUEL") -> RETIRA EN CS . TENA_PRINCIPAL - AV PANO SN VICTOR HUGO SAN MIGUEL | Q18: =IFERROR(__xludf.DUMMYFUNCTION("""COMPUTED_VALUE"""),"SERVIENTREGA") -> SERVIENTREGA | R18: =IFERROR(__xludf.DUMMYFUNCTION("""COMPUTED_VALUE"""),20.0) -> 20 | T18: =IFERROR(__xludf.DUMMYFUNCTION("""COMPUTED_VALUE"""),7.67) -> 7.67 | U18: =IFERROR(__xludf.DUMMYFUNCTION("""COMPUTED_VALUE"""),0.0) -> 0 | V18: =IFERROR(__xludf.DUMMYFUNCTION("""COMPUTED_VALUE"""),0.0) -> 0 | W18: =IFERROR(__xludf.DUMMYFUNCTION("""COMPUTED_VALUE"""),0.0) -> 0 | X18: =IFERROR(__xludf.DUMMYFUNCTION("""COMPUTED_VALUE"""),2.2) -> 2.2 | Y18: =IFERROR(__xludf.DUMMYFUNCTION("""COMPUTED_VALUE"""),4.4) -> 4.4 | Z18: =IFERROR(__xludf.DUMMYFUNCTION("""COMPUTED_VALUE"""),111894.0) -> 111894 | AA18: =IFERROR(__xludf.DUMMYFUNCTION("""COMPUTED_VALUE"""),"LYIC5M40067") -> LYIC5M40067 | AC18: =IFERROR(__xludf.DUMMYFUNCTION("""COMPUTED_VALUE"""),"Limpiador de Parabrisas y Ventanas") -> Limpiador de Parabrisas y Ventanas | AE18: =IFERROR(__xludf.DUMMYFUNCTION("""COMPUTED_VALUE"""),2.0) -> 2 | AN18: =IFERROR(__xludf.DUMMYFUNCTION("""COMPUTED_VALUE"""),"19:18") -> 19:18 | AO18: =IFERROR(__xludf.DUMMYFUNCTION("""COMPUTED_VALUE"""),"26-03-2026") -> 26-03-2026 | AP18: =IFERROR(__xludf.DUMMYFUNCTION("""COMPUTED_VALUE"""),"INGRESANDO EN AGENCIA") -> INGRESANDO EN AGENCIA | AQ18: =IFERROR(__xludf.DUMMYFUNCTION("""COMPUTED_VALUE"""),".") -> . | AY18: =IFERROR(__xludf.DUMMYFUNCTION("""COMPUTED_VALUE"""),"25/03/2026") -> 25/03/2026
A19: =IFERROR(__xludf.DUMMYFUNCTION("""COMPUTED_VALUE"""),"27-03-2026") -> 27-03-2026 | B19: =IFERROR(__xludf.DUMMYFUNCTION("""COMPUTED_VALUE"""),4907159.0) -> 4907159 | C19: =IFERROR(__xludf.DUMMYFUNCTION("""COMPUTED_VALUE"""),"10:08") -> 10:08 | D19: =IFERROR(__xludf.DUMMYFUNCTION("""COMPUTED_VALUE"""),"25-03-2026") -> 25-03-2026 | E19: =IFERROR(__xludf.DUMMYFUNCTION("""COMPUTED_VALUE"""),"Luis Bonilla") -> Luis Bonilla | F19: =IFERROR(__xludf.DUMMYFUNCTION("""COMPUTED_VALUE"""),"996015589") -> 996015589 | J19: =IFERROR(__xludf.DUMMYFUNCTION("""COMPUTED_VALUE"""),"185035812") -> 185035812 | K19: =IFERROR(__xludf.DUMMYFUNCTION("""COMPUTED_VALUE"""),"GUIA_GENERADA") -> GUIA_GENERADA | L19: =IFERROR(__xludf.DUMMYFUNCTION("""COMPUTED_VALUE"""),"CON RECAUDO") -> CON RECAUDO | M19: =IFERROR(__xludf.DUMMYFUNCTION("""COMPUTED_VALUE"""),"IMBABURA") -> IMBABURA | N19: =IFERROR(__xludf.DUMMYFUNCTION("""COMPUTED_VALUE"""),"OTAVALO") -> OTAVALO | O19: =IFERROR(__xludf.DUMMYFUNCTION("""COMPUTED_VALUE"""),"RETIRA EN CS : OTAVALO_PRINCIPAL - MORALES S/N Y ROCA") -> RETIRA EN CS : OTAVALO_PRINCIPAL - MORALES S/N Y ROCA | Q19: =IFERROR(__xludf.DUMMYFUNCTION("""COMPUTED_VALUE"""),"SERVIENTREGA") -> SERVIENTREGA | R19: =IFERROR(__xludf.DUMMYFUNCTION("""COMPUTED_VALUE"""),20.0) -> 20 | T19: =IFERROR(__xludf.DUMMYFUNCTION("""COMPUTED_VALUE"""),7.67) -> 7.67 | U19: =IFERROR(__xludf.DUMMYFUNCTION("""COMPUTED_VALUE"""),0.0) -> 0 | V19: =IFERROR(__xludf.DUMMYFUNCTION("""COMPUTED_VALUE"""),0.0) -> 0 | W19: =IFERROR(__xludf.DUMMYFUNCTION("""COMPUTED_VALUE"""),0.0) -> 0 | X19: =IFERROR(__xludf.DUMMYFUNCTION("""COMPUTED_VALUE"""),2.1) -> 2.1 | Y19: =IFERROR(__xludf.DUMMYFUNCTION("""COMPUTED_VALUE"""),4.2) -> 4.2 | Z19: =IFERROR(__xludf.DUMMYFUNCTION("""COMPUTED_VALUE"""),106245.0) -> 106245 | AA19: =IFERROR(__xludf.DUMMYFUNCTION("""COMPUTED_VALUE"""),"IMP-045-CEPLIMAUT") -> IMP-045-CEPLIMAUT | AC19: =IFERROR(__xludf.DUMMYFUNCTION("""COMPUTED_VALUE"""),"LIMPIADOR DE PARABRISAS Y VENTANAS") -> LIMPIADOR DE PARABRISAS Y VENTANAS | AE19: =IFERROR(__xludf.DUMMYFUNCTION("""COMPUTED_VALUE"""),2.0) -> 2 | AN19: =IFERROR(__xludf.DUMMYFUNCTION("""COMPUTED_VALUE"""),"16:08") -> 16:08 | AO19: =IFERROR(__xludf.DUMMYFUNCTION("""COMPUTED_VALUE"""),"25-03-2026") -> 25-03-2026 | AP19: =IFERROR(__xludf.DUMMYFUNCTION("""COMPUTED_VALUE"""),"GENERADO") -> GENERADO | AQ19: =IFERROR(__xludf.DUMMYFUNCTION("""COMPUTED_VALUE"""),".") -> . | AY19: =IFERROR(__xludf.DUMMYFUNCTION("""COMPUTED_VALUE"""),"25/03/2026") -> 25/03/2026
A20: =IFERROR(__xludf.DUMMYFUNCTION("""COMPUTED_VALUE"""),"27-03-2026") -> 27-03-2026 | B20: =IFERROR(__xludf.DUMMYFUNCTION("""COMPUTED_VALUE"""),4898027.0) -> 4898027 | C20: =IFERROR(__xludf.DUMMYFUNCTION("""COMPUTED_VALUE"""),"12:34") -> 12:34 | D20: =IFERROR(__xludf.DUMMYFUNCTION("""COMPUTED_VALUE"""),"24-03-2026") -> 24-03-2026 | E20: =IFERROR(__xludf.DUMMYFUNCTION("""COMPUTED_VALUE"""),"Fernando Zamora") -> Fernando Zamora | F20: =IFERROR(__xludf.DUMMYFUNCTION("""COMPUTED_VALUE"""),"964251134") -> 964251134 | J20: =IFERROR(__xludf.DUMMYFUNCTION("""COMPUTED_VALUE"""),"D001449719") -> D001449719 | K20: =IFERROR(__xludf.DUMMYFUNCTION("""COMPUTED_VALUE"""),"EN REPARTO") -> EN REPARTO | L20: =IFERROR(__xludf.DUMMYFUNCTION("""COMPUTED_VALUE"""),"CON RECAUDO") -> CON RECAUDO | M20: =IFERROR(__xludf.DUMMYFUNCTION("""COMPUTED_VALUE"""),"GUAYAS") -> GUAYAS | N20: =IFERROR(__xludf.DUMMYFUNCTION("""COMPUTED_VALUE"""),"GUAYAQUIL") -> GUAYAQUIL | O20: =IFERROR(__xludf.DUMMYFUNCTION("""COMPUTED_VALUE"""),"BASTIÓN popular bloque 1B - En el dispensario Tipo C") -> BASTIÓN popular bloque 1B - En el dispensario Tipo C | Q20: =IFERROR(__xludf.DUMMYFUNCTION("""COMPUTED_VALUE"""),"GINTRACOM") -> GINTRACOM | R20: =IFERROR(__xludf.DUMMYFUNCTION("""COMPUTED_VALUE"""),19.0) -> 19 | T20: =IFERROR(__xludf.DUMMYFUNCTION("""COMPUTED_VALUE"""),4.11) -> 4.11 | U20: =IFERROR(__xludf.DUMMYFUNCTION("""COMPUTED_VALUE"""),0.0) -> 0 | V20: =IFERROR(__xludf.DUMMYFUNCTION("""COMPUTED_VALUE"""),0.0) -> 0 | W20: =IFERROR(__xludf.DUMMYFUNCTION("""COMPUTED_VALUE"""),0.0) -> 0 | X20: =IFERROR(__xludf.DUMMYFUNCTION("""COMPUTED_VALUE"""),2.4) -> 2.4 | Y20: =IFERROR(__xludf.DUMMYFUNCTION("""COMPUTED_VALUE"""),2.4) -> 2.4 | Z20: =IFERROR(__xludf.DUMMYFUNCTION("""COMPUTED_VALUE"""),119189.0) -> 119189 | AA20: =IFERROR(__xludf.DUMMYFUNCTION("""COMPUTED_VALUE"""),"CUCHILLO DE CHEF") -> CUCHILLO DE CHEF | AC20: =IFERROR(__xludf.DUMMYFUNCTION("""COMPUTED_VALUE"""),"CUCHILLO DE CHEF") -> CUCHILLO DE CHEF | AE20: =IFERROR(__xludf.DUMMYFUNCTION("""COMPUTED_VALUE"""),1.0) -> 1 | AN20: =IFERROR(__xludf.DUMMYFUNCTION("""COMPUTED_VALUE"""),"10:45") -> 10:45 | AO20: =IFERROR(__xludf.DUMMYFUNCTION("""COMPUTED_VALUE"""),"26-03-2026") -> 26-03-2026 | AP20: =IFERROR(__xludf.DUMMYFUNCTION("""COMPUTED_VALUE"""),"EN REPARTO") -> EN REPARTO | AQ20: =IFERROR(__xludf.DUMMYFUNCTION("""COMPUTED_VALUE"""),"EN REPARTO") -> EN REPARTO | AS20: =IFERROR(__xludf.DUMMYFUNCTION("""COMPUTED_VALUE"""),"PAUL BORJA") -> PAUL BORJA | AY20: =IFERROR(__xludf.DUMMYFUNCTION("""COMPUTED_VALUE"""),"24/03/2026") -> 24/03/2026
A21: =IFERROR(__xludf.DUMMYFUNCTION("""COMPUTED_VALUE"""),"27-03-2026") -> 27-03-2026 | B21: =IFERROR(__xludf.DUMMYFUNCTION("""COMPUTED_VALUE"""),4890075.0) -> 4890075 | C21: =IFERROR(__xludf.DUMMYFUNCTION("""COMPUTED_VALUE"""),"17:14") -> 17:14 | D21: =IFERROR(__xludf.DUMMYFUNCTION("""COMPUTED_VALUE"""),"23-03-2026") -> 23-03-2026 | E21: =IFERROR(__xludf.DUMMYFUNCTION("""COMPUTED_VALUE"""),"ERMINSON ALBERTO ALVAREZ Acuña ALVAREZ ACUÑA") -> ERMINSON ALBERTO ALVAREZ Acuña ALVAREZ ACUÑA | F21: =IFERROR(__xludf.DUMMYFUNCTION("""COMPUTED_VALUE"""),"986605425") -> 986605425 | J21: =IFERROR(__xludf.DUMMYFUNCTION("""COMPUTED_VALUE"""),"185028953") -> 185028953 | K21: =IFERROR(__xludf.DUMMYFUNCTION("""COMPUTED_VALUE"""),"PARA RETIRO EN AGENCIA SERVIENTREGA") -> PARA RETIRO EN AGENCIA SERVIENTREGA | L21: =IFERROR(__xludf.DUMMYFUNCTION("""COMPUTED_VALUE"""),"CON RECAUDO") -> CON RECAUDO | M21: =IFERROR(__xludf.DUMMYFUNCTION("""COMPUTED_VALUE"""),"ZAMORA CHINCHIPE") -> ZAMORA CHINCHIPE | N21: =IFERROR(__xludf.DUMMYFUNCTION("""COMPUTED_VALUE"""),"YANTZAZA") -> YANTZAZA | O21: =IFERROR(__xludf.DUMMYFUNCTION("""COMPUTED_VALUE"""),"RETIRA EN CS: YANTZAZA_IVAN RIOFRIO, IVAN RIOFRIO Y MARTIN AYUY") -> RETIRA EN CS: YANTZAZA_IVAN RIOFRIO, IVAN RIOFRIO Y MARTIN AYUY | Q21: =IFERROR(__xludf.DUMMYFUNCTION("""COMPUTED_VALUE"""),"SERVIENTREGA") -> SERVIENTREGA | R21: =IFERROR(__xludf.DUMMYFUNCTION("""COMPUTED_VALUE"""),20.0) -> 20 | T21: =IFERROR(__xludf.DUMMYFUNCTION("""COMPUTED_VALUE"""),7.67) -> 7.67 | U21: =IFERROR(__xludf.DUMMYFUNCTION("""COMPUTED_VALUE"""),0.0) -> 0 | V21: =IFERROR(__xludf.DUMMYFUNCTION("""COMPUTED_VALUE"""),0.0) -> 0 | W21: =IFERROR(__xludf.DUMMYFUNCTION("""COMPUTED_VALUE"""),0.0) -> 0 | X21: =IFERROR(__xludf.DUMMYFUNCTION("""COMPUTED_VALUE"""),2.21) -> 2.21 | Y21: =IFERROR(__xludf.DUMMYFUNCTION("""COMPUTED_VALUE"""),4.42) -> 4.42 | Z21: =IFERROR(__xludf.DUMMYFUNCTION("""COMPUTED_VALUE"""),120732.0) -> 120732 | AA21: =IFERROR(__xludf.DUMMYFUNCTION("""COMPUTED_VALUE"""),"PROV-LMPVT") -> PROV-LMPVT | AC21: =IFERROR(__xludf.DUMMYFUNCTION("""COMPUTED_VALUE"""),"LIMPIADOR DE PARABRISAS Y VENTANAS") -> LIMPIADOR DE PARABRISAS Y VENTANAS | AE21: =IFERROR(__xludf.DUMMYFUNCTION("""COMPUTED_VALUE"""),2.0) -> 2 | AN21: =IFERROR(__xludf.DUMMYFUNCTION("""COMPUTED_VALUE"""),"01:00") -> 01:00 | AO21: =IFERROR(__xludf.DUMMYFUNCTION("""COMPUTED_VALUE"""),"27-03-2026") -> 27-03-2026 | AP21: =IFERROR(__xludf.DUMMYFUNCTION("""COMPUTED_VALUE"""),"Novedad en CS") -> Novedad en CS | AQ21: =IFERROR(__xludf.DUMMYFUNCTION("""COMPUTED_VALUE"""),"{}") -> {} | AT21: =IFERROR(__xludf.DUMMYFUNCTION("""COMPUTED_VALUE"""),"CHATEA PRO") -> CHATEA PRO | AU21: =IFERROR(__xludf.DUMMYFUNCTION("""COMPUTED_VALUE"""),"CHATEA PRO") -> CHATEA PRO | AY21: =IFERROR(__xludf.DUMMYFUNCTION("""COMPUTED_VALUE"""),"24/03/2026") -> 24/03/2026
A22: =IFERROR(__xludf.DUMMYFUNCTION("""COMPUTED_VALUE"""),"27-03-2026") -> 27-03-2026 | B22: =IFERROR(__xludf.DUMMYFUNCTION("""COMPUTED_VALUE"""),4889470.0) -> 4889470 | C22: =IFERROR(__xludf.DUMMYFUNCTION("""COMPUTED_VALUE"""),"16:09") -> 16:09 | D22: =IFERROR(__xludf.DUMMYFUNCTION("""COMPUTED_VALUE"""),"23-03-2026") -> 23-03-2026 | E22: =IFERROR(__xludf.DUMMYFUNCTION("""COMPUTED_VALUE"""),"Fausto chango Chango caizabanda") -> Fausto chango Chango caizabanda | F22: =IFERROR(__xludf.DUMMYFUNCTION("""COMPUTED_VALUE"""),"981017807") -> 981017807 | G22: =IFERROR(__xludf.DUMMYFUNCTION("""COMPUTED_VALUE"""),"faustochangoc@gmail.com") -> faustochangoc@gmail.com | K22: =IFERROR(__xludf.DUMMYFUNCTION("""COMPUTED_VALUE"""),"PENDIENTE CONFIRMACION") -> PENDIENTE CONFIRMACION | L22: =IFERROR(__xludf.DUMMYFUNCTION("""COMPUTED_VALUE"""),"CON RECAUDO") -> CON RECAUDO | M22: =IFERROR(__xludf.DUMMYFUNCTION("""COMPUTED_VALUE"""),"TUNGURAHUA") -> TUNGURAHUA | N22: =IFERROR(__xludf.DUMMYFUNCTION("""COMPUTED_VALUE"""),"SAN PEDRO DE PELILEO") -> SAN PEDRO DE PELILEO | O22: =IFERROR(__xludf.DUMMYFUNCTION("""COMPUTED_VALUE"""),"Avenida confraternidad Al frente parque paquilla pelileo -") -> Avenida confraternidad Al frente parque paquilla pelileo - | Q22: =IFERROR(__xludf.DUMMYFUNCTION("""COMPUTED_VALUE"""),"LAARCOURIER") -> LAARCOURIER | R22: =IFERROR(__xludf.DUMMYFUNCTION("""COMPUTED_VALUE"""),33.0) -> 33 | T22: =IFERROR(__xludf.DUMMYFUNCTION("""COMPUTED_VALUE"""),7.43) -> 7.43 | U22: =IFERROR(__xludf.DUMMYFUNCTION("""COMPUTED_VALUE"""),0.0) -> 0 | V22: =IFERROR(__xludf.DUMMYFUNCTION("""COMPUTED_VALUE"""),0.0) -> 0 | W22: =IFERROR(__xludf.DUMMYFUNCTION("""COMPUTED_VALUE"""),0.0) -> 0 | X22: =IFERROR(__xludf.DUMMYFUNCTION("""COMPUTED_VALUE"""),2.85) -> 2.85 | Y22: =IFERROR(__xludf.DUMMYFUNCTION("""COMPUTED_VALUE"""),11.4) -> 11.4 | Z22: =IFERROR(__xludf.DUMMYFUNCTION("""COMPUTED_VALUE"""),129724.0) -> 129724 | AA22: =IFERROR(__xludf.DUMMYFUNCTION("""COMPUTED_VALUE"""),"TSTBP") -> TSTBP | AC22: =IFERROR(__xludf.DUMMYFUNCTION("""COMPUTED_VALUE"""),"Tira Selladora Tope Bloqueador Puertas") -> Tira Selladora Tope Bloqueador Puertas | AE22: =IFERROR(__xludf.DUMMYFUNCTION("""COMPUTED_VALUE"""),4.0) -> 4 | AT22: =IFERROR(__xludf.DUMMYFUNCTION("""COMPUTED_VALUE"""),"SHOPIFY") -> SHOPIFY | AU22: =IFERROR(__xludf.DUMMYFUNCTION("""COMPUTED_VALUE"""),"IMPORTEX EC") -> IMPORTEX EC | AV22: =IFERROR(__xludf.DUMMYFUNCTION("""COMPUTED_VALUE"""),"6593760657452") -> 6593760657452 | AW22: =IFERROR(__xludf.DUMMYFUNCTION("""COMPUTED_VALUE"""),6781.0) -> 6781
A23: =IFERROR(__xludf.DUMMYFUNCTION("""COMPUTED_VALUE"""),"27-03-2026") -> 27-03-2026 | B23: =IFERROR(__xludf.DUMMYFUNCTION("""COMPUTED_VALUE"""),4888200.0) -> 4888200 | C23: =IFERROR(__xludf.DUMMYFUNCTION("""COMPUTED_VALUE"""),"14:15") -> 14:15 | D23: =IFERROR(__xludf.DUMMYFUNCTION("""COMPUTED_VALUE"""),"23-03-2026") -> 23-03-2026 | E23: =IFERROR(__xludf.DUMMYFUNCTION("""COMPUTED_VALUE"""),"Lus Figuero") -> Lus Figuero | F23: =IFERROR(__xludf.DUMMYFUNCTION("""COMPUTED_VALUE"""),"999401421") -> 999401421 | J23: =IFERROR(__xludf.DUMMYFUNCTION("""COMPUTED_VALUE"""),"185028975") -> 185028975 | K23: =IFERROR(__xludf.DUMMYFUNCTION("""COMPUTED_VALUE"""),"PARA RETIRO EN AGENCIA SERVIENTREGA") -> PARA RETIRO EN AGENCIA SERVIENTREGA | L23: =IFERROR(__xludf.DUMMYFUNCTION("""COMPUTED_VALUE"""),"CON RECAUDO") -> CON RECAUDO | M23: =IFERROR(__xludf.DUMMYFUNCTION("""COMPUTED_VALUE"""),"GUAYAS") -> GUAYAS | N23: =IFERROR(__xludf.DUMMYFUNCTION("""COMPUTED_VALUE"""),"NOBOL") -> NOBOL | O23: =IFERROR(__xludf.DUMMYFUNCTION("""COMPUTED_VALUE"""),"RETIRA CS: NOBOL_RENAN OLMEDO, CALLE RENAN OLMEDO Y AV RIO AMAZONAS MZ40 SL 543 JUNTO AL MERCADO MUNICIPAL") -> RETIRA CS: NOBOL_RENAN OLMEDO, CALLE RENAN OLMEDO Y AV RIO AMAZONAS MZ40 SL 543 JUNTO AL MERCADO MUNICIPAL | Q23: =IFERROR(__xludf.DUMMYFUNCTION("""COMPUTED_VALUE"""),"SERVIENTREGA") -> SERVIENTREGA | R23: =IFERROR(__xludf.DUMMYFUNCTION("""COMPUTED_VALUE"""),20.0) -> 20 | T23: =IFERROR(__xludf.DUMMYFUNCTION("""COMPUTED_VALUE"""),7.67) -> 7.67 | U23: =IFERROR(__xludf.DUMMYFUNCTION("""COMPUTED_VALUE"""),0.0) -> 0 | V23: =IFERROR(__xludf.DUMMYFUNCTION("""COMPUTED_VALUE"""),0.0) -> 0 | W23: =IFERROR(__xludf.DUMMYFUNCTION("""COMPUTED_VALUE"""),0.0) -> 0 | X23: =IFERROR(__xludf.DUMMYFUNCTION("""COMPUTED_VALUE"""),2.21) -> 2.21 | Y23: =IFERROR(__xludf.DUMMYFUNCTION("""COMPUTED_VALUE"""),4.42) -> 4.42 | Z23: =IFERROR(__xludf.DUMMYFUNCTION("""COMPUTED_VALUE"""),120732.0) -> 120732 | AA23: =IFERROR(__xludf.DUMMYFUNCTION("""COMPUTED_VALUE"""),"PROV-LMPVT") -> PROV-LMPVT | AC23: =IFERROR(__xludf.DUMMYFUNCTION("""COMPUTED_VALUE"""),"LIMPIADOR DE PARABRISAS Y VENTANAS") -> LIMPIADOR DE PARABRISAS Y VENTANAS | AE23: =IFERROR(__xludf.DUMMYFUNCTION("""COMPUTED_VALUE"""),2.0) -> 2 | AN23: =IFERROR(__xludf.DUMMYFUNCTION("""COMPUTED_VALUE"""),"01:01") -> 01:01 | AO23: =IFERROR(__xludf.DUMMYFUNCTION("""COMPUTED_VALUE"""),"27-03-2026") -> 27-03-2026 | AP23: =IFERROR(__xludf.DUMMYFUNCTION("""COMPUTED_VALUE"""),"Ingresando en Agencia NOBOL_RENAN OLMEDO") -> Ingresando en Agencia NOBOL_RENAN OLMEDO | AQ23: =IFERROR(__xludf.DUMMYFUNCTION("""COMPUTED_VALUE"""),"{}") -> {} | AT23: =IFERROR(__xludf.DUMMYFUNCTION("""COMPUTED_VALUE"""),"CHATEA PRO") -> CHATEA PRO | AU23: =IFERROR(__xludf.DUMMYFUNCTION("""COMPUTED_VALUE"""),"CHATEA PRO") -> CHATEA PRO | AY23: =IFERROR(__xludf.DUMMYFUNCTION("""COMPUTED_VALUE"""),"24/03/2026") -> 24/03/2026
A24: =IFERROR(__xludf.DUMMYFUNCTION("""COMPUTED_VALUE"""),"27-03-2026") -> 27-03-2026 | B24: =IFERROR(__xludf.DUMMYFUNCTION("""COMPUTED_VALUE"""),4886972.0) -> 4886972 | C24: =IFERROR(__xludf.DUMMYFUNCTION("""COMPUTED_VALUE"""),"12:27") -> 12:27 | D24: =IFERROR(__xludf.DUMMYFUNCTION("""COMPUTED_VALUE"""),"23-03-2026") -> 23-03-2026 | E24: =IFERROR(__xludf.DUMMYFUNCTION("""COMPUTED_VALUE"""),"FERNANDO ORTIZ") -> FERNANDO ORTIZ | F24: =IFERROR(__xludf.DUMMYFUNCTION("""COMPUTED_VALUE"""),"962156461") -> 962156461 | G24: =IFERROR(__xludf.DUMMYFUNCTION("""COMPUTED_VALUE"""),"fer.89pl@gmail.com") -> fer.89pl@gmail.com | J24: =IFERROR(__xludf.DUMMYFUNCTION("""COMPUTED_VALUE"""),"D001449736") -> D001449736 | K24: =IFERROR(__xludf.DUMMYFUNCTION("""COMPUTED_VALUE"""),"ENTREGADO") -> ENTREGADO | L24: =IFERROR(__xludf.DUMMYFUNCTION("""COMPUTED_VALUE"""),"CON RECAUDO") -> CON RECAUDO | M24: =IFERROR(__xludf.DUMMYFUNCTION("""COMPUTED_VALUE"""),"AZUAY") -> AZUAY | N24: =IFERROR(__xludf.DUMMYFUNCTION("""COMPUTED_VALUE"""),"CUENCA") -> CUENCA | O24: =IFERROR(__xludf.DUMMYFUNCTION("""COMPUTED_VALUE"""),"Calle Nicanor merchán y Eugenio espejo, Parque la libertad, dentro de la dirección de riesgos del gad municipal de cuenca") -> Calle Nicanor merchán y Eugenio espejo, Parque la libertad, dentro de la dirección de riesgos del gad municipal de cuenca | Q24: =IFERROR(__xludf.DUMMYFUNCTION("""COMPUTED_VALUE"""),"GINTRACOM") -> GINTRACOM | R24: =IFERROR(__xludf.DUMMYFUNCTION("""COMPUTED_VALUE"""),22.0) -> 22 | S24: =IFERROR(__xludf.DUMMYFUNCTION("""COMPUTED_VALUE"""),11.36) -> 11.36 | T24: =IFERROR(__xludf.DUMMYFUNCTION("""COMPUTED_VALUE"""),5.84) -> 5.84 | U24: =IFERROR(__xludf.DUMMYFUNCTION("""COMPUTED_VALUE"""),0.0) -> 0 | V24: =IFERROR(__xludf.DUMMYFUNCTION("""COMPUTED_VALUE"""),0.0) -> 0 | W24: =IFERROR(__xludf.DUMMYFUNCTION("""COMPUTED_VALUE"""),0.0) -> 0 | X24: =IFERROR(__xludf.DUMMYFUNCTION("""COMPUTED_VALUE"""),2.4) -> 2.4 | Y24: =IFERROR(__xludf.DUMMYFUNCTION("""COMPUTED_VALUE"""),4.8) -> 4.8 | Z24: =IFERROR(__xludf.DUMMYFUNCTION("""COMPUTED_VALUE"""),119189.0) -> 119189 | AA24: =IFERROR(__xludf.DUMMYFUNCTION("""COMPUTED_VALUE"""),"CUCHILLO DE CHEF") -> CUCHILLO DE CHEF | AC24: =IFERROR(__xludf.DUMMYFUNCTION("""COMPUTED_VALUE"""),"CUCHILLO DE CHEF") -> CUCHILLO DE CHEF | AE24: =IFERROR(__xludf.DUMMYFUNCTION("""COMPUTED_VALUE"""),2.0) -> 2 | AN24: =IFERROR(__xludf.DUMMYFUNCTION("""COMPUTED_VALUE"""),"15:57") -> 15:57 | AO24: =IFERROR(__xludf.DUMMYFUNCTION("""COMPUTED_VALUE"""),"26-03-2026") -> 26-03-2026 | AP24: =IFERROR(__xludf.DUMMYFUNCTION("""COMPUTED_VALUE"""),"ENTREGADA GINTRACOM") -> ENTREGADA GINTRACOM | AQ24: =IFERROR(__xludf.DUMMYFUNCTION("""COMPUTED_VALUE"""),"ENTREGADA GINTRACOM") -> ENTREGADA GINTRACOM | AT24: =IFERROR(__xludf.DUMMYFUNCTION("""COMPUTED_VALUE"""),"SHOPIFY") -> SHOPIFY | AU24: =IFERROR(__xludf.DUMMYFUNCTION("""COMPUTED_VALUE"""),"IMPORTEX EC") -> IMPORTEX EC | AV24: =IFERROR(__xludf.DUMMYFUNCTION("""COMPUTED_VALUE"""),"6598048546860") -> 6598048546860 | AW24: =IFERROR(__xludf.DUMMYFUNCTION("""COMPUTED_VALUE"""),6819.0) -> 6819 | AY24: =IFERROR(__xludf.DUMMYFUNCTION("""COMPUTED_VALUE"""),"24/03/2026") -> 24/03/2026
A25: =IFERROR(__xludf.DUMMYFUNCTION("""COMPUTED_VALUE"""),"27-03-2026") -> 27-03-2026 | B25: =IFERROR(__xludf.DUMMYFUNCTION("""COMPUTED_VALUE"""),4886943.0) -> 4886943 | C25: =IFERROR(__xludf.DUMMYFUNCTION("""COMPUTED_VALUE"""),"12:25") -> 12:25 | D25: =IFERROR(__xludf.DUMMYFUNCTION("""COMPUTED_VALUE"""),"23-03-2026") -> 23-03-2026 | E25: =IFERROR(__xludf.DUMMYFUNCTION("""COMPUTED_VALUE"""),"Josei Salem") -> Josei Salem | F25: =IFERROR(__xludf.DUMMYFUNCTION("""COMPUTED_VALUE"""),"98798022") -> 98798022 | K25: =IFERROR(__xludf.DUMMYFUNCTION("""COMPUTED_VALUE"""),"PENDIENTE CONFIRMACION") -> PENDIENTE CONFIRMACION | L25: =IFERROR(__xludf.DUMMYFUNCTION("""COMPUTED_VALUE"""),"CON RECAUDO") -> CON RECAUDO | M25: =IFERROR(__xludf.DUMMYFUNCTION("""COMPUTED_VALUE"""),"MANABI") -> MANABI | N25: =IFERROR(__xludf.DUMMYFUNCTION("""COMPUTED_VALUE"""),"MANTA") -> MANTA | O25: =IFERROR(__xludf.DUMMYFUNCTION("""COMPUTED_VALUE"""),"RETIRA EN CS: MANTA_CALLE 13, CALLE 13 AVE 21 Y 22") -> RETIRA EN CS: MANTA_CALLE 13, CALLE 13 AVE 21 Y 22 | Q25: =IFERROR(__xludf.DUMMYFUNCTION("""COMPUTED_VALUE"""),"SERVIENTREGA") -> SERVIENTREGA | R25: =IFERROR(__xludf.DUMMYFUNCTION("""COMPUTED_VALUE"""),24.99) -> 24.99 | T25: =IFERROR(__xludf.DUMMYFUNCTION("""COMPUTED_VALUE"""),6.31) -> 6.31 | U25: =IFERROR(__xludf.DUMMYFUNCTION("""COMPUTED_VALUE"""),0.0) -> 0 | V25: =IFERROR(__xludf.DUMMYFUNCTION("""COMPUTED_VALUE"""),0.0) -> 0 | W25: =IFERROR(__xludf.DUMMYFUNCTION("""COMPUTED_VALUE"""),0.0) -> 0 | X25: =IFERROR(__xludf.DUMMYFUNCTION("""COMPUTED_VALUE"""),2.1) -> 2.1 | Y25: =IFERROR(__xludf.DUMMYFUNCTION("""COMPUTED_VALUE"""),6.3) -> 6.3 | Z25: =IFERROR(__xludf.DUMMYFUNCTION("""COMPUTED_VALUE"""),106245.0) -> 106245 | AA25: =IFERROR(__xludf.DUMMYFUNCTION("""COMPUTED_VALUE"""),"IMP-045-CEPLIMAUT") -> IMP-045-CEPLIMAUT | AC25: =IFERROR(__xludf.DUMMYFUNCTION("""COMPUTED_VALUE"""),"LIMPIADOR DE PARABRISAS Y VENTANAS") -> LIMPIADOR DE PARABRISAS Y VENTANAS | AE25: =IFERROR(__xludf.DUMMYFUNCTION("""COMPUTED_VALUE"""),3.0) -> 3 | AS25: =IFERROR(__xludf.DUMMYFUNCTION("""COMPUTED_VALUE"""),"PAUL BORJA") -> PAUL BORJA
A26: =IFERROR(__xludf.DUMMYFUNCTION("""COMPUTED_VALUE"""),"27-03-2026") -> 27-03-2026 | B26: =IFERROR(__xludf.DUMMYFUNCTION("""COMPUTED_VALUE"""),4886533.0) -> 4886533 | C26: =IFERROR(__xludf.DUMMYFUNCTION("""COMPUTED_VALUE"""),"11:50") -> 11:50 | D26: =IFERROR(__xludf.DUMMYFUNCTION("""COMPUTED_VALUE"""),"23-03-2026") -> 23-03-2026 | E26: =IFERROR(__xludf.DUMMYFUNCTION("""COMPUTED_VALUE"""),"Witson Ortega") -> Witson Ortega | F26: =IFERROR(__xludf.DUMMYFUNCTION("""COMPUTED_VALUE"""),"981394613") -> 981394613 | J26: =IFERROR(__xludf.DUMMYFUNCTION("""COMPUTED_VALUE"""),"185025488") -> 185025488 | K26: =IFERROR(__xludf.DUMMYFUNCTION("""COMPUTED_VALUE"""),"ENTREGADO") -> ENTREGADO | L26: =IFERROR(__xludf.DUMMYFUNCTION("""COMPUTED_VALUE"""),"CON RECAUDO") -> CON RECAUDO | M26: =IFERROR(__xludf.DUMMYFUNCTION("""COMPUTED_VALUE"""),"AZUAY") -> AZUAY | N26: =IFERROR(__xludf.DUMMYFUNCTION("""COMPUTED_VALUE"""),"CUENCA") -> CUENCA | O26: =IFERROR(__xludf.DUMMYFUNCTION("""COMPUTED_VALUE"""),"RETIRA EN CS: CUENCA AV. GIL RAMIREZ DAVALOS, AV.GIL RAMIREZ DAVALOS Y FRANCISCO PIZARRO N3-89 FRENTE A LA GASOLINERA PYS") -> RETIRA EN CS: CUENCA AV. GIL RAMIREZ DAVALOS, AV.GIL RAMIREZ DAVALOS Y FRANCISCO PIZARRO N3-89 FRENTE A LA GASOLINERA PYS | Q26: =IFERROR(__xludf.DUMMYFUNCTION("""COMPUTED_VALUE"""),"SERVIENTREGA") -> SERVIENTREGA | R26: =IFERROR(__xludf.DUMMYFUNCTION("""COMPUTED_VALUE"""),20.0) -> 20 | S26: =IFERROR(__xludf.DUMMYFUNCTION("""COMPUTED_VALUE"""),9.61) -> 9.61 | T26: =IFERROR(__xludf.DUMMYFUNCTION("""COMPUTED_VALUE"""),5.97) -> 5.97 | U26: =IFERROR(__xludf.DUMMYFUNCTION("""COMPUTED_VALUE"""),0.0) -> 0 | V26: =IFERROR(__xludf.DUMMYFUNCTION("""COMPUTED_VALUE"""),0.0) -> 0 | W26: =IFERROR(__xludf.DUMMYFUNCTION("""COMPUTED_VALUE"""),0.0) -> 0 | X26: =IFERROR(__xludf.DUMMYFUNCTION("""COMPUTED_VALUE"""),2.21) -> 2.21 | Y26: =IFERROR(__xludf.DUMMYFUNCTION("""COMPUTED_VALUE"""),4.42) -> 4.42 | Z26: =IFERROR(__xludf.DUMMYFUNCTION("""COMPUTED_VALUE"""),120732.0) -> 120732 | AA26: =IFERROR(__xludf.DUMMYFUNCTION("""COMPUTED_VALUE"""),"PROV-LMPVT") -> PROV-LMPVT | AC26: =IFERROR(__xludf.DUMMYFUNCTION("""COMPUTED_VALUE"""),"LIMPIADOR DE PARABRISAS Y VENTANAS") -> LIMPIADOR DE PARABRISAS Y VENTANAS | AE26: =IFERROR(__xludf.DUMMYFUNCTION("""COMPUTED_VALUE"""),2.0) -> 2 | AN26: =IFERROR(__xludf.DUMMYFUNCTION("""COMPUTED_VALUE"""),"18:08") -> 18:08 | AO26: =IFERROR(__xludf.DUMMYFUNCTION("""COMPUTED_VALUE"""),"26-03-2026") -> 26-03-2026 | AP26: =IFERROR(__xludf.DUMMYFUNCTION("""COMPUTED_VALUE"""),"REPORTADO ENTREGADO EN AGENCIA") -> REPORTADO ENTREGADO EN AGENCIA | AQ26: =IFERROR(__xludf.DUMMYFUNCTION("""COMPUTED_VALUE"""),"WITSON ORTEGA") -> WITSON ORTEGA | AT26: =IFERROR(__xludf.DUMMYFUNCTION("""COMPUTED_VALUE"""),"CHATEA PRO") -> CHATEA PRO | AU26: =IFERROR(__xludf.DUMMYFUNCTION("""COMPUTED_VALUE"""),"CHATEA PRO") -> CHATEA PRO | AY26: =IFERROR(__xludf.DUMMYFUNCTION("""COMPUTED_VALUE"""),"23/03/2026") -> 23/03/2026
A27: =IFERROR(__xludf.DUMMYFUNCTION("""COMPUTED_VALUE"""),"27-03-2026") -> 27-03-2026 | B27: =IFERROR(__xludf.DUMMYFUNCTION("""COMPUTED_VALUE"""),4883341.0) -> 4883341 | C27: =IFERROR(__xludf.DUMMYFUNCTION("""COMPUTED_VALUE"""),"07:48") -> 07:48 | D27: =IFERROR(__xludf.DUMMYFUNCTION("""COMPUTED_VALUE"""),"23-03-2026") -> 23-03-2026 | E27: =IFERROR(__xludf.DUMMYFUNCTION("""COMPUTED_VALUE"""),"Guisela Aguirre") -> Guisela Aguirre | F27: =IFERROR(__xludf.DUMMYFUNCTION("""COMPUTED_VALUE"""),"985992365") -> 985992365 | G27: =IFERROR(__xludf.DUMMYFUNCTION("""COMPUTED_VALUE"""),"nereanaislaura567@gmail.com") -> nereanaislaura567@gmail.com | K27: =IFERROR(__xludf.DUMMYFUNCTION("""COMPUTED_VALUE"""),"PENDIENTE CONFIRMACION") -> PENDIENTE CONFIRMACION | L27: =IFERROR(__xludf.DUMMYFUNCTION("""COMPUTED_VALUE"""),"CON RECAUDO") -> CON RECAUDO | M27: =IFERROR(__xludf.DUMMYFUNCTION("""COMPUTED_VALUE"""),"GUAYAS") -> GUAYAS | N27: =IFERROR(__xludf.DUMMYFUNCTION("""COMPUTED_VALUE"""),"GUAYAQUIL") -> GUAYAQUIL | O27: =IFERROR(__xludf.DUMMYFUNCTION("""COMPUTED_VALUE"""),"Av. Vicente Trujillo entre esmeraldas y los rios Frente a las acacias -") -> Av. Vicente Trujillo entre esmeraldas y los rios Frente a las acacias - | Q27: =IFERROR(__xludf.DUMMYFUNCTION("""COMPUTED_VALUE"""),"GINTRACOM") -> GINTRACOM | R27: =IFERROR(__xludf.DUMMYFUNCTION("""COMPUTED_VALUE"""),27.0) -> 27 | T27: =IFERROR(__xludf.DUMMYFUNCTION("""COMPUTED_VALUE"""),4.42) -> 4.42 | U27: =IFERROR(__xludf.DUMMYFUNCTION("""COMPUTED_VALUE"""),0.0) -> 0 | V27: =IFERROR(__xludf.DUMMYFUNCTION("""COMPUTED_VALUE"""),0.0) -> 0 | W27: =IFERROR(__xludf.DUMMYFUNCTION("""COMPUTED_VALUE"""),0.0) -> 0 | X27: =IFERROR(__xludf.DUMMYFUNCTION("""COMPUTED_VALUE"""),2.4) -> 2.4 | Y27: =IFERROR(__xludf.DUMMYFUNCTION("""COMPUTED_VALUE"""),7.2) -> 7.2 | Z27: =IFERROR(__xludf.DUMMYFUNCTION("""COMPUTED_VALUE"""),119189.0) -> 119189 | AA27: =IFERROR(__xludf.DUMMYFUNCTION("""COMPUTED_VALUE"""),"CUCHILLO DE CHEF") -> CUCHILLO DE CHEF | AC27: =IFERROR(__xludf.DUMMYFUNCTION("""COMPUTED_VALUE"""),"CUCHILLO DE CHEF") -> CUCHILLO DE CHEF | AE27: =IFERROR(__xludf.DUMMYFUNCTION("""COMPUTED_VALUE"""),3.0) -> 3 | AT27: =IFERROR(__xludf.DUMMYFUNCTION("""COMPUTED_VALUE"""),"SHOPIFY") -> SHOPIFY | AU27: =IFERROR(__xludf.DUMMYFUNCTION("""COMPUTED_VALUE"""),"IMPORTEX EC") -> IMPORTEX EC | AV27: =IFERROR(__xludf.DUMMYFUNCTION("""COMPUTED_VALUE"""),"6597531926572") -> 6597531926572 | AW27: =IFERROR(__xludf.DUMMYFUNCTION("""COMPUTED_VALUE"""),6818.0) -> 6818
A28: =IFERROR(__xludf.DUMMYFUNCTION("""COMPUTED_VALUE"""),"27-03-2026") -> 27-03-2026 | B28: =IFERROR(__xludf.DUMMYFUNCTION("""COMPUTED_VALUE"""),4882668.0) -> 4882668 | C28: =IFERROR(__xludf.DUMMYFUNCTION("""COMPUTED_VALUE"""),"06:26") -> 06:26 | D28: =IFERROR(__xludf.DUMMYFUNCTION("""COMPUTED_VALUE"""),"23-03-2026") -> 23-03-2026 | E28: =IFERROR(__xludf.DUMMYFUNCTION("""COMPUTED_VALUE"""),"Luis Lema") -> Luis Lema | F28: =IFERROR(__xludf.DUMMYFUNCTION("""COMPUTED_VALUE"""),"987715920") -> 987715920 | G28: =IFERROR(__xludf.DUMMYFUNCTION("""COMPUTED_VALUE"""),"gerardolema1963@gmail.com") -> gerardolema1963@gmail.com | J28: =IFERROR(__xludf.DUMMYFUNCTION("""COMPUTED_VALUE"""),"D001449740") -> D001449740 | K28: =IFERROR(__xludf.DUMMYFUNCTION("""COMPUTED_VALUE"""),"NOVEDAD") -> NOVEDAD | L28: =IFERROR(__xludf.DUMMYFUNCTION("""COMPUTED_VALUE"""),"CON RECAUDO") -> CON RECAUDO | M28: =IFERROR(__xludf.DUMMYFUNCTION("""COMPUTED_VALUE"""),"PICHINCHA") -> PICHINCHA | N28: =IFERROR(__xludf.DUMMYFUNCTION("""COMPUTED_VALUE"""),"QUITO") -> QUITO | O28: =IFERROR(__xludf.DUMMYFUNCTION("""COMPUTED_VALUE"""),"Geranios #558 y las lilas, Puertas del sol, Frente al estadio, puertas del sol, portón celeste") -> Geranios #558 y las lilas, Puertas del sol, Frente al estadio, puertas del sol, portón celeste | Q28: =IFERROR(__xludf.DUMMYFUNCTION("""COMPUTED_VALUE"""),"GINTRACOM") -> GINTRACOM | R28: =IFERROR(__xludf.DUMMYFUNCTION("""COMPUTED_VALUE"""),32.0) -> 32 | T28: =IFERROR(__xludf.DUMMYFUNCTION("""COMPUTED_VALUE"""),6.24) -> 6.24 | U28: =IFERROR(__xludf.DUMMYFUNCTION("""COMPUTED_VALUE"""),0.0) -> 0 | V28: =IFERROR(__xludf.DUMMYFUNCTION("""COMPUTED_VALUE"""),0.0) -> 0 | W28: =IFERROR(__xludf.DUMMYFUNCTION("""COMPUTED_VALUE"""),0.0) -> 0 | X28: =IFERROR(__xludf.DUMMYFUNCTION("""COMPUTED_VALUE"""),2.4) -> 2.4 | Y28: =IFERROR(__xludf.DUMMYFUNCTION("""COMPUTED_VALUE"""),9.6) -> 9.6 | Z28: =IFERROR(__xludf.DUMMYFUNCTION("""COMPUTED_VALUE"""),119189.0) -> 119189 | AA28: =IFERROR(__xludf.DUMMYFUNCTION("""COMPUTED_VALUE"""),"CUCHILLO DE CHEF") -> CUCHILLO DE CHEF | AC28: =IFERROR(__xludf.DUMMYFUNCTION("""COMPUTED_VALUE"""),"CUCHILLO DE CHEF") -> CUCHILLO DE CHEF | AE28: =IFERROR(__xludf.DUMMYFUNCTION("""COMPUTED_VALUE"""),4.0) -> 4 | AF28: =IFERROR(__xludf.DUMMYFUNCTION("""COMPUTED_VALUE"""),"DESTINATARIO NO CONTESTA LLAMADAS NI WHATSAPP") -> DESTINATARIO NO CONTESTA LLAMADAS NI WHATSAPP | AG28: =IFERROR(__xludf.DUMMYFUNCTION("""COMPUTED_VALUE"""),"NO") -> NO | AH28: =IFERROR(__xludf.DUMMYFUNCTION("""COMPUTED_VALUE"""),"16:18") -> 16:18 | AI28: =IFERROR(__xludf.DUMMYFUNCTION("""COMPUTED_VALUE"""),"26-03-2026") -> 26-03-2026 | AN28: =IFERROR(__xludf.DUMMYFUNCTION("""COMPUTED_VALUE"""),"16:18") -> 16:18 | AO28: =IFERROR(__xludf.DUMMYFUNCTION("""COMPUTED_VALUE"""),"26-03-2026") -> 26-03-2026 | AP28: =IFERROR(__xludf.DUMMYFUNCTION("""COMPUTED_VALUE"""),"DESTINATARIO NO CONTESTA LLAMADAS NI WHATSAPP") -> DESTINATARIO NO CONTESTA LLAMADAS NI WHATSAPP | AQ28: =IFERROR(__xludf.DUMMYFUNCTION("""COMPUTED_VALUE"""),"DESTINATARIO NO CONTESTA LLAMADAS NI WHATSAPP") -> DESTINATARIO NO CONTESTA LLAMADAS NI WHATSAPP | AT28: =IFERROR(__xludf.DUMMYFUNCTION("""COMPUTED_VALUE"""),"SHOPIFY") -> SHOPIFY | AU28: =IFERROR(__xludf.DUMMYFUNCTION("""COMPUTED_VALUE"""),"IMPORTEX EC") -> IMPORTEX EC | AV28: =IFERROR(__xludf.DUMMYFUNCTION("""COMPUTED_VALUE"""),"6597453283372") -> 6597453283372 | AW28: =IFERROR(__xludf.DUMMYFUNCTION("""COMPUTED_VALUE"""),6817.0) -> 6817 | AY28: =IFERROR(__xludf.DUMMYFUNCTION("""COMPUTED_VALUE"""),"24/03/2026") -> 24/03/2026
A29: =IFERROR(__xludf.DUMMYFUNCTION("""COMPUTED_VALUE"""),"27-03-2026") -> 27-03-2026 | B29: =IFERROR(__xludf.DUMMYFUNCTION("""COMPUTED_VALUE"""),4881814.0) -> 4881814 | C29: =IFERROR(__xludf.DUMMYFUNCTION("""COMPUTED_VALUE"""),"00:35") -> 00:35 | D29: =IFERROR(__xludf.DUMMYFUNCTION("""COMPUTED_VALUE"""),"23-03-2026") -> 23-03-2026 | E29: =IFERROR(__xludf.DUMMYFUNCTION("""COMPUTED_VALUE"""),"Javier Rambay") -> Javier Rambay | F29: =IFERROR(__xludf.DUMMYFUNCTION("""COMPUTED_VALUE"""),"988783198") -> 988783198 | G29: =IFERROR(__xludf.DUMMYFUNCTION("""COMPUTED_VALUE"""),"javierrambay107@gmail.com") -> javierrambay107@gmail.com | J29: =IFERROR(__xludf.DUMMYFUNCTION("""COMPUTED_VALUE"""),"D001449741") -> D001449741 | K29: =IFERROR(__xludf.DUMMYFUNCTION("""COMPUTED_VALUE"""),"ENTREGADO") -> ENTREGADO | L29: =IFERROR(__xludf.DUMMYFUNCTION("""COMPUTED_VALUE"""),"CON RECAUDO") -> CON RECAUDO | M29: =IFERROR(__xludf.DUMMYFUNCTION("""COMPUTED_VALUE"""),"GUAYAS") -> GUAYAS | N29: =IFERROR(__xludf.DUMMYFUNCTION("""COMPUTED_VALUE"""),"GUAYAQUIL") -> GUAYAQUIL | O29: =IFERROR(__xludf.DUMMYFUNCTION("""COMPUTED_VALUE"""),"Calle 32Ava #905 y Francisco de marcos - Junto a distribuidora Bohórquez - REFERENCIA: Afuera hay un letrero que dice almuerzo en una palma") -> Calle 32Ava #905 y Francisco de marcos - Junto a distribuidora Bohórquez - REFERENCIA: Afuera hay un letrero que dice almuerzo en una palma | Q29: =IFERROR(__xludf.DUMMYFUNCTION("""COMPUTED_VALUE"""),"GINTRACOM") -> GINTRACOM | R29: =IFERROR(__xludf.DUMMYFUNCTION("""COMPUTED_VALUE"""),22.0) -> 22 | S29: =IFERROR(__xludf.DUMMYFUNCTION("""COMPUTED_VALUE"""),12.97) -> 12.97 | T29: =IFERROR(__xludf.DUMMYFUNCTION("""COMPUTED_VALUE"""),4.23) -> 4.23 | U29: =IFERROR(__xludf.DUMMYFUNCTION("""COMPUTED_VALUE"""),0.0) -> 0 | V29: =IFERROR(__xludf.DUMMYFUNCTION("""COMPUTED_VALUE"""),0.0) -> 0 | W29: =IFERROR(__xludf.DUMMYFUNCTION("""COMPUTED_VALUE"""),0.0) -> 0 | X29: =IFERROR(__xludf.DUMMYFUNCTION("""COMPUTED_VALUE"""),2.4) -> 2.4 | Y29: =IFERROR(__xludf.DUMMYFUNCTION("""COMPUTED_VALUE"""),4.8) -> 4.8 | Z29: =IFERROR(__xludf.DUMMYFUNCTION("""COMPUTED_VALUE"""),119189.0) -> 119189 | AA29: =IFERROR(__xludf.DUMMYFUNCTION("""COMPUTED_VALUE"""),"CUCHILLO DE CHEF") -> CUCHILLO DE CHEF | AC29: =IFERROR(__xludf.DUMMYFUNCTION("""COMPUTED_VALUE"""),"CUCHILLO DE CHEF") -> CUCHILLO DE CHEF | AE29: =IFERROR(__xludf.DUMMYFUNCTION("""COMPUTED_VALUE"""),2.0) -> 2 | AF29: =IFERROR(__xludf.DUMMYFUNCTION("""COMPUTED_VALUE"""),"DESTINATARIO NO CONTESTA LLAMADAS NI WHATSAPP") -> DESTINATARIO NO CONTESTA LLAMADAS NI WHATSAPP | AG29: =IFERROR(__xludf.DUMMYFUNCTION("""COMPUTED_VALUE"""),"NO") -> NO | AH29: =IFERROR(__xludf.DUMMYFUNCTION("""COMPUTED_VALUE"""),"12:12") -> 12:12 | AI29: =IFERROR(__xludf.DUMMYFUNCTION("""COMPUTED_VALUE"""),"26-03-2026") -> 26-03-2026 | AN29: =IFERROR(__xludf.DUMMYFUNCTION("""COMPUTED_VALUE"""),"12:12") -> 12:12 | AO29: =IFERROR(__xludf.DUMMYFUNCTION("""COMPUTED_VALUE"""),"26-03-2026") -> 26-03-2026 | AP29: =IFERROR(__xludf.DUMMYFUNCTION("""COMPUTED_VALUE"""),"DESTINATARIO NO CONTESTA LLAMADAS NI WHATSAPP") -> DESTINATARIO NO CONTESTA LLAMADAS NI WHATSAPP | AQ29: =IFERROR(__xludf.DUMMYFUNCTION("""COMPUTED_VALUE"""),"DESTINATARIO NO CONTESTA LLAMADAS NI WHATSAPP") -> DESTINATARIO NO CONTESTA LLAMADAS NI WHATSAPP | AT29: =IFERROR(__xludf.DUMMYFUNCTION("""COMPUTED_VALUE"""),"SHOPIFY") -> SHOPIFY | AU29: =IFERROR(__xludf.DUMMYFUNCTION("""COMPUTED_VALUE"""),"IMPORTEX EC") -> IMPORTEX EC | AV29: =IFERROR(__xludf.DUMMYFUNCTION("""COMPUTED_VALUE"""),"6597179473964") -> 6597179473964 | AW29: =IFERROR(__xludf.DUMMYFUNCTION("""COMPUTED_VALUE"""),6816.0) -> 6816 | AY29: =IFERROR(__xludf.DUMMYFUNCTION("""COMPUTED_VALUE"""),"24/03/2026") -> 24/03/2026
A30: =IFERROR(__xludf.DUMMYFUNCTION("""COMPUTED_VALUE"""),"27-03-2026") -> 27-03-2026 | B30: =IFERROR(__xludf.DUMMYFUNCTION("""COMPUTED_VALUE"""),4881682.0) -> 4881682 | C30: =IFERROR(__xludf.DUMMYFUNCTION("""COMPUTED_VALUE"""),"00:05") -> 00:05 | D30: =IFERROR(__xludf.DUMMYFUNCTION("""COMPUTED_VALUE"""),"23-03-2026") -> 23-03-2026 | E30: =IFERROR(__xludf.DUMMYFUNCTION("""COMPUTED_VALUE"""),"Fernando Zamora") -> Fernando Zamora | F30: =IFERROR(__xludf.DUMMYFUNCTION("""COMPUTED_VALUE"""),"964251134") -> 964251134 | G30: =IFERROR(__xludf.DUMMYFUNCTION("""COMPUTED_VALUE"""),"zamora23fernando@gmail.com") -> zamora23fernando@gmail.com | K30: =IFERROR(__xludf.DUMMYFUNCTION("""COMPUTED_VALUE"""),"CANCELADO") -> CANCELADO | L30: =IFERROR(__xludf.DUMMYFUNCTION("""COMPUTED_VALUE"""),"CON RECAUDO") -> CON RECAUDO | M30: =IFERROR(__xludf.DUMMYFUNCTION("""COMPUTED_VALUE"""),"GUAYAS") -> GUAYAS | N30: =IFERROR(__xludf.DUMMYFUNCTION("""COMPUTED_VALUE"""),"GUAYAQUIL") -> GUAYAQUIL | O30: =IFERROR(__xludf.DUMMYFUNCTION("""COMPUTED_VALUE"""),"FLOR DE BASTIÓN Parque California è -") -> FLOR DE BASTIÓN Parque California è - | Q30: =IFERROR(__xludf.DUMMYFUNCTION("""COMPUTED_VALUE"""),"GINTRACOM") -> GINTRACOM | R30: =IFERROR(__xludf.DUMMYFUNCTION("""COMPUTED_VALUE"""),22.0) -> 22 | T30: =IFERROR(__xludf.DUMMYFUNCTION("""COMPUTED_VALUE"""),4.23) -> 4.23 | U30: =IFERROR(__xludf.DUMMYFUNCTION("""COMPUTED_VALUE"""),0.0) -> 0 | V30: =IFERROR(__xludf.DUMMYFUNCTION("""COMPUTED_VALUE"""),0.0) -> 0 | W30: =IFERROR(__xludf.DUMMYFUNCTION("""COMPUTED_VALUE"""),0.0) -> 0 | X30: =IFERROR(__xludf.DUMMYFUNCTION("""COMPUTED_VALUE"""),2.4) -> 2.4 | Y30: =IFERROR(__xludf.DUMMYFUNCTION("""COMPUTED_VALUE"""),4.8) -> 4.8 | Z30: =IFERROR(__xludf.DUMMYFUNCTION("""COMPUTED_VALUE"""),119189.0) -> 119189 | AA30: =IFERROR(__xludf.DUMMYFUNCTION("""COMPUTED_VALUE"""),"CUCHILLO DE CHEF") -> CUCHILLO DE CHEF | AC30: =IFERROR(__xludf.DUMMYFUNCTION("""COMPUTED_VALUE"""),"CUCHILLO DE CHEF") -> CUCHILLO DE CHEF | AE30: =IFERROR(__xludf.DUMMYFUNCTION("""COMPUTED_VALUE"""),2.0) -> 2 | AT30: =IFERROR(__xludf.DUMMYFUNCTION("""COMPUTED_VALUE"""),"SHOPIFY") -> SHOPIFY | AU30: =IFERROR(__xludf.DUMMYFUNCTION("""COMPUTED_VALUE"""),"IMPORTEX EC") -> IMPORTEX EC | AV30: =IFERROR(__xludf.DUMMYFUNCTION("""COMPUTED_VALUE"""),"6597154340908") -> 6597154340908 | AW30: =IFERROR(__xludf.DUMMYFUNCTION("""COMPUTED_VALUE"""),6815.0) -> 6815
A31: =IFERROR(__xludf.DUMMYFUNCTION("""COMPUTED_VALUE"""),"27-03-2026") -> 27-03-2026 | B31: =IFERROR(__xludf.DUMMYFUNCTION("""COMPUTED_VALUE"""),4881620.0) -> 4881620 | C31: =IFERROR(__xludf.DUMMYFUNCTION("""COMPUTED_VALUE"""),"23:55") -> 23:55 | D31: =IFERROR(__xludf.DUMMYFUNCTION("""COMPUTED_VALUE"""),"22-03-2026") -> 22-03-2026 | E31: =IFERROR(__xludf.DUMMYFUNCTION("""COMPUTED_VALUE"""),"Blanca Pilatuña") -> Blanca Pilatuña | F31: =IFERROR(__xludf.DUMMYFUNCTION("""COMPUTED_VALUE"""),"960408217") -> 960408217 | G31: =IFERROR(__xludf.DUMMYFUNCTION("""COMPUTED_VALUE"""),"blankitapilatuna@gmail.com") -> blankitapilatuna@gmail.com | J31: =IFERROR(__xludf.DUMMYFUNCTION("""COMPUTED_VALUE"""),"D001449742") -> D001449742 | K31: =IFERROR(__xludf.DUMMYFUNCTION("""COMPUTED_VALUE"""),"NOVEDAD") -> NOVEDAD | L31: =IFERROR(__xludf.DUMMYFUNCTION("""COMPUTED_VALUE"""),"CON RECAUDO") -> CON RECAUDO | M31: =IFERROR(__xludf.DUMMYFUNCTION("""COMPUTED_VALUE"""),"PICHINCHA") -> PICHINCHA | N31: =IFERROR(__xludf.DUMMYFUNCTION("""COMPUTED_VALUE"""),"MACHACHI") -> MACHACHI | O31: =IFERROR(__xludf.DUMMYFUNCTION("""COMPUTED_VALUE"""),"Via Aloag, Portal de Machachi casa 123, REFERENCIA: FUERTE MILITAR ATAHUALPA, MACHACHI - LLAMARA WHATSAPP") -> Via Aloag, Portal de Machachi casa 123, REFERENCIA: FUERTE MILITAR ATAHUALPA, MACHACHI - LLAMARA WHATSAPP | Q31: =IFERROR(__xludf.DUMMYFUNCTION("""COMPUTED_VALUE"""),"GINTRACOM") -> GINTRACOM | R31: =IFERROR(__xludf.DUMMYFUNCTION("""COMPUTED_VALUE"""),22.0) -> 22 | T31: =IFERROR(__xludf.DUMMYFUNCTION("""COMPUTED_VALUE"""),6.41) -> 6.41 | U31: =IFERROR(__xludf.DUMMYFUNCTION("""COMPUTED_VALUE"""),0.0) -> 0 | V31: =IFERROR(__xludf.DUMMYFUNCTION("""COMPUTED_VALUE"""),0.0) -> 0 | W31: =IFERROR(__xludf.DUMMYFUNCTION("""COMPUTED_VALUE"""),0.0) -> 0 | X31: =IFERROR(__xludf.DUMMYFUNCTION("""COMPUTED_VALUE"""),2.4) -> 2.4 | Y31: =IFERROR(__xludf.DUMMYFUNCTION("""COMPUTED_VALUE"""),4.8) -> 4.8 | Z31: =IFERROR(__xludf.DUMMYFUNCTION("""COMPUTED_VALUE"""),119189.0) -> 119189 | AA31: =IFERROR(__xludf.DUMMYFUNCTION("""COMPUTED_VALUE"""),"CUCHILLO DE CHEF") -> CUCHILLO DE CHEF | AC31: =IFERROR(__xludf.DUMMYFUNCTION("""COMPUTED_VALUE"""),"CUCHILLO DE CHEF") -> CUCHILLO DE CHEF | AE31: =IFERROR(__xludf.DUMMYFUNCTION("""COMPUTED_VALUE"""),2.0) -> 2 | AF31: =IFERROR(__xludf.DUMMYFUNCTION("""COMPUTED_VALUE"""),"DESTINATARIO NO SE ENCUENTRA EN LUGAR DE ENTREGA.") -> DESTINATARIO NO SE ENCUENTRA EN LUGAR DE ENTREGA. | AG31: =IFERROR(__xludf.DUMMYFUNCTION("""COMPUTED_VALUE"""),"NO") -> NO | AH31: =IFERROR(__xludf.DUMMYFUNCTION("""COMPUTED_VALUE"""),"14:02") -> 14:02 | AI31: =IFERROR(__xludf.DUMMYFUNCTION("""COMPUTED_VALUE"""),"26-03-2026") -> 26-03-2026 | AN31: =IFERROR(__xludf.DUMMYFUNCTION("""COMPUTED_VALUE"""),"14:02") -> 14:02 | AO31: =IFERROR(__xludf.DUMMYFUNCTION("""COMPUTED_VALUE"""),"26-03-2026") -> 26-03-2026 | AP31: =IFERROR(__xludf.DUMMYFUNCTION("""COMPUTED_VALUE"""),"DESTINATARIO NO SE ENCUENTRA EN LUGAR DE ENTREGA.") -> DESTINATARIO NO SE ENCUENTRA EN LUGAR DE ENTREGA. | AQ31: =IFERROR(__xludf.DUMMYFUNCTION("""COMPUTED_VALUE"""),"DESTINATARIO NO SE ENCUENTRA EN LUGAR DE ENTREGA.") -> DESTINATARIO NO SE ENCUENTRA EN LUGAR DE ENTREGA. | AT31: =IFERROR(__xludf.DUMMYFUNCTION("""COMPUTED_VALUE"""),"SHOPIFY") -> SHOPIFY | AU31: =IFERROR(__xludf.DUMMYFUNCTION("""COMPUTED_VALUE"""),"IMPORTEX EC") -> IMPORTEX EC | AV31: =IFERROR(__xludf.DUMMYFUNCTION("""COMPUTED_VALUE"""),"6597145722924") -> 6597145722924 | AW31: =IFERROR(__xludf.DUMMYFUNCTION("""COMPUTED_VALUE"""),6814.0) -> 6814 | AY31: =IFERROR(__xludf.DUMMYFUNCTION("""COMPUTED_VALUE"""),"24/03/2026") -> 24/03/2026
A32: =IFERROR(__xludf.DUMMYFUNCTION("""COMPUTED_VALUE"""),"27-03-2026") -> 27-03-2026 | B32: =IFERROR(__xludf.DUMMYFUNCTION("""COMPUTED_VALUE"""),4880712.0) -> 4880712 | C32: =IFERROR(__xludf.DUMMYFUNCTION("""COMPUTED_VALUE"""),"22:28") -> 22:28 | D32: =IFERROR(__xludf.DUMMYFUNCTION("""COMPUTED_VALUE"""),"22-03-2026") -> 22-03-2026 | E32: =IFERROR(__xludf.DUMMYFUNCTION("""COMPUTED_VALUE"""),"Jackson Diomedes Portocarrero Vásquez") -> Jackson Diomedes Portocarrero Vásquez | F32: =IFERROR(__xludf.DUMMYFUNCTION("""COMPUTED_VALUE"""),"987233298") -> 987233298 | G32: =IFERROR(__xludf.DUMMYFUNCTION("""COMPUTED_VALUE"""),"jacksonportocarrero92@gmail.com") -> jacksonportocarrero92@gmail.com | K32: =IFERROR(__xludf.DUMMYFUNCTION("""COMPUTED_VALUE"""),"PENDIENTE CONFIRMACION") -> PENDIENTE CONFIRMACION | L32: =IFERROR(__xludf.DUMMYFUNCTION("""COMPUTED_VALUE"""),"CON RECAUDO") -> CON RECAUDO | M32: =IFERROR(__xludf.DUMMYFUNCTION("""COMPUTED_VALUE"""),"PICHINCHA") -> PICHINCHA | N32: =IFERROR(__xludf.DUMMYFUNCTION("""COMPUTED_VALUE"""),"QUITO") -> QUITO | O32: =IFERROR(__xludf.DUMMYFUNCTION("""COMPUTED_VALUE"""),"Av occidental condado Notaría 74 Notaría 74 av occidental Cojunto colinas el condado alado de la volacanizadora los gemelos -") -> Av occidental condado Notaría 74 Notaría 74 av occidental Cojunto colinas el condado alado de la volacanizadora los gemelos - | Q32: =IFERROR(__xludf.DUMMYFUNCTION("""COMPUTED_VALUE"""),"GINTRACOM") -> GINTRACOM | R32: =IFERROR(__xludf.DUMMYFUNCTION("""COMPUTED_VALUE"""),27.0) -> 27 | T32: =IFERROR(__xludf.DUMMYFUNCTION("""COMPUTED_VALUE"""),6.03) -> 6.03 | U32: =IFERROR(__xludf.DUMMYFUNCTION("""COMPUTED_VALUE"""),0.0) -> 0 | V32: =IFERROR(__xludf.DUMMYFUNCTION("""COMPUTED_VALUE"""),0.0) -> 0 | W32: =IFERROR(__xludf.DUMMYFUNCTION("""COMPUTED_VALUE"""),0.0) -> 0 | X32: =IFERROR(__xludf.DUMMYFUNCTION("""COMPUTED_VALUE"""),2.4) -> 2.4 | Y32: =IFERROR(__xludf.DUMMYFUNCTION("""COMPUTED_VALUE"""),7.2) -> 7.2 | Z32: =IFERROR(__xludf.DUMMYFUNCTION("""COMPUTED_VALUE"""),119189.0) -> 119189 | AA32: =IFERROR(__xludf.DUMMYFUNCTION("""COMPUTED_VALUE"""),"CUCHILLO DE CHEF") -> CUCHILLO DE CHEF | AC32: =IFERROR(__xludf.DUMMYFUNCTION("""COMPUTED_VALUE"""),"CUCHILLO DE CHEF") -> CUCHILLO DE CHEF | AE32: =IFERROR(__xludf.DUMMYFUNCTION("""COMPUTED_VALUE"""),3.0) -> 3 | AT32: =IFERROR(__xludf.DUMMYFUNCTION("""COMPUTED_VALUE"""),"SHOPIFY") -> SHOPIFY | AU32: =IFERROR(__xludf.DUMMYFUNCTION("""COMPUTED_VALUE"""),"IMPORTEX EC") -> IMPORTEX EC | AV32: =IFERROR(__xludf.DUMMYFUNCTION("""COMPUTED_VALUE"""),"6597034967084") -> 6597034967084 | AW32: =IFERROR(__xludf.DUMMYFUNCTION("""COMPUTED_VALUE"""),6813.0) -> 6813
A33: =IFERROR(__xludf.DUMMYFUNCTION("""COMPUTED_VALUE"""),"27-03-2026") -> 27-03-2026 | B33: =IFERROR(__xludf.DUMMYFUNCTION("""COMPUTED_VALUE"""),4880525.0) -> 4880525 | C33: =IFERROR(__xludf.DUMMYFUNCTION("""COMPUTED_VALUE"""),"22:18") -> 22:18 | D33: =IFERROR(__xludf.DUMMYFUNCTION("""COMPUTED_VALUE"""),"22-03-2026") -> 22-03-2026 | E33: =IFERROR(__xludf.DUMMYFUNCTION("""COMPUTED_VALUE"""),"José luis Santana cedeño") -> José luis Santana cedeño | F33: =IFERROR(__xludf.DUMMYFUNCTION("""COMPUTED_VALUE"""),"996415561") -> 996415561 | G33: =IFERROR(__xludf.DUMMYFUNCTION("""COMPUTED_VALUE"""),"joseluissantanacedeno7@gmail.com") -> joseluissantanacedeno7@gmail.com | J33: =IFERROR(__xludf.DUMMYFUNCTION("""COMPUTED_VALUE"""),"D001449743") -> D001449743 | K33: =IFERROR(__xludf.DUMMYFUNCTION("""COMPUTED_VALUE"""),"NOVEDAD") -> NOVEDAD | L33: =IFERROR(__xludf.DUMMYFUNCTION("""COMPUTED_VALUE"""),"CON RECAUDO") -> CON RECAUDO | M33: =IFERROR(__xludf.DUMMYFUNCTION("""COMPUTED_VALUE"""),"MANABI") -> MANABI | N33: =IFERROR(__xludf.DUMMYFUNCTION("""COMPUTED_VALUE"""),"MANTA") -> MANTA | O33: =IFERROR(__xludf.DUMMYFUNCTION("""COMPUTED_VALUE"""),"Via Rocafuerte y calle 4, Junto a crematorio Santa Marianita - manta") -> Via Rocafuerte y calle 4, Junto a crematorio Santa Marianita - manta | Q33: =IFERROR(__xludf.DUMMYFUNCTION("""COMPUTED_VALUE"""),"GINTRACOM") -> GINTRACOM | R33: =IFERROR(__xludf.DUMMYFUNCTION("""COMPUTED_VALUE"""),22.0) -> 22 | T33: =IFERROR(__xludf.DUMMYFUNCTION("""COMPUTED_VALUE"""),5.84) -> 5.84 | U33: =IFERROR(__xludf.DUMMYFUNCTION("""COMPUTED_VALUE"""),0.0) -> 0 | V33: =IFERROR(__xludf.DUMMYFUNCTION("""COMPUTED_VALUE"""),0.0) -> 0 | W33: =IFERROR(__xludf.DUMMYFUNCTION("""COMPUTED_VALUE"""),0.0) -> 0 | X33: =IFERROR(__xludf.DUMMYFUNCTION("""COMPUTED_VALUE"""),2.4) -> 2.4 | Y33: =IFERROR(__xludf.DUMMYFUNCTION("""COMPUTED_VALUE"""),4.8) -> 4.8 | Z33: =IFERROR(__xludf.DUMMYFUNCTION("""COMPUTED_VALUE"""),119189.0) -> 119189 | AA33: =IFERROR(__xludf.DUMMYFUNCTION("""COMPUTED_VALUE"""),"CUCHILLO DE CHEF") -> CUCHILLO DE CHEF | AC33: =IFERROR(__xludf.DUMMYFUNCTION("""COMPUTED_VALUE"""),"CUCHILLO DE CHEF") -> CUCHILLO DE CHEF | AE33: =IFERROR(__xludf.DUMMYFUNCTION("""COMPUTED_VALUE"""),2.0) -> 2 | AF33: =IFERROR(__xludf.DUMMYFUNCTION("""COMPUTED_VALUE"""),"DESTINATARIO INDICA QUE ESTÁ INCONFORME CON EL PRODUCTO. (NO RECIBE)") -> DESTINATARIO INDICA QUE ESTÁ INCONFORME CON EL PRODUCTO. (NO RECIBE) | AG33: =IFERROR(__xludf.DUMMYFUNCTION("""COMPUTED_VALUE"""),"NO") -> NO | AH33: =IFERROR(__xludf.DUMMYFUNCTION("""COMPUTED_VALUE"""),"11:17") -> 11:17 | AI33: =IFERROR(__xludf.DUMMYFUNCTION("""COMPUTED_VALUE"""),"26-03-2026") -> 26-03-2026 | AN33: =IFERROR(__xludf.DUMMYFUNCTION("""COMPUTED_VALUE"""),"11:23") -> 11:23 | AO33: =IFERROR(__xludf.DUMMYFUNCTION("""COMPUTED_VALUE"""),"26-03-2026") -> 26-03-2026 | AP33: =IFERROR(__xludf.DUMMYFUNCTION("""COMPUTED_VALUE"""),"DESTINATARIO INDICA QUE ESTÁ INCONFORME CON EL PRODUCTO. (NO RECIBE)") -> DESTINATARIO INDICA QUE ESTÁ INCONFORME CON EL PRODUCTO. (NO RECIBE) | AQ33: =IFERROR(__xludf.DUMMYFUNCTION("""COMPUTED_VALUE"""),"DESTINATARIO INDICA QUE ESTÁ INCONFORME CON EL PRODUCTO. (NO RECIBE)") -> DESTINATARIO INDICA QUE ESTÁ INCONFORME CON EL PRODUCTO. (NO RECIBE) | AT33: =IFERROR(__xludf.DUMMYFUNCTION("""COMPUTED_VALUE"""),"SHOPIFY") -> SHOPIFY | AU33: =IFERROR(__xludf.DUMMYFUNCTION("""COMPUTED_VALUE"""),"IMPORTEX EC") -> IMPORTEX EC | AV33: =IFERROR(__xludf.DUMMYFUNCTION("""COMPUTED_VALUE"""),"6597017600044") -> 6597017600044 | AW33: =IFERROR(__xludf.DUMMYFUNCTION("""COMPUTED_VALUE"""),6812.0) -> 6812 | AY33: =IFERROR(__xludf.DUMMYFUNCTION("""COMPUTED_VALUE"""),"24/03/2026") -> 24/03/2026
